[{"user_id": 1204886336701947910, "user_statuses": 6430, "name": "stjornudottirs", "tweet": "Shein, Boohoo, PLT... La fast fashion quoi \ud83e\udd71 Un fl\u00e9au \u00e9cologique et humanitaire pour des coupes pourries et de la qualit\u00e9 m\u00e9diocre, je pourrai plus acheter sur ces sites il n'y a rien \u00e0 y gagner https://t.co/xT2vB2CIPI", "retweets": 0, "location": "\ud83c\udf0d", "created": "06-Apr-2021", "followers": 63, "is_user_verified": false, "favorite_count": 2, "in_reply_to_status_id": null, "keyword": "boohoo", "language": "fr"}, {"user_id": 1043716758337662976, "user_statuses": 16498, "name": "aurorologue", "tweet": "Montpellier!!!!!!!\n\u00c7a doit \u00eatre tr\u00e8s boohoo l\u00e0 decors ce matin... ouvrez les fen\u00eatres, posez un moment le v\u00e9lo, sortez une minute....\npartagez vos aurores \ud83d\ude4f\ud83d\ude4f\ud83d\ude4f\n#aurorologie https://t.co/w11SFeYNWp", "retweets": 0, "location": "Montpellier, France", "created": "06-Apr-2021", "followers": 909, "is_user_verified": false, "favorite_count": 11, "in_reply_to_status_id": null, "keyword": "boohoo", "language": "fr"}, {"user_id": 1021732469526155266, "user_statuses": 3343, "name": "volamenaa", "tweet": "Moi je dis que c'est cher pcq j'habites \u00e0 la R\u00e9union, donc les frais \u00e0 30\u20ac non merci \ud83d\ude2d\ud83d\ude2d autant commander sur Boohoo https://t.co/42CqHp59Be", "retweets": 0, "location": "La R\u00e9union", "created": "06-Apr-2021", "followers": 249, "is_user_verified": false, "favorite_count": 0, "in_reply_to_status_id": null, "keyword": "boohoo", "language": "fr"}, {"user_id": 1332456402359623688, "user_statuses": 1596, "name": "6nda_", "tweet": "@loane_lft @krlnm @kgrb__ @mlavatos yen a zara et sur boohoo ch\u00e9rie", "retweets": 0, "location": "Maldives", "created": "06-Apr-2021", "followers": 161, "is_user_verified": false, "favorite_count": 1, "in_reply_to_status_id": 1379183996962226185, "keyword": "boohoo", "language": "fr"}, {"user_id": 1017864407270002689, "user_statuses": 39866, "name": "hanamnzali76", "tweet": "Pareil pour Boohoo hein https://t.co/vJ9i9QNoZi", "retweets": 0, "location": "Le Havre, France", "created": "06-Apr-2021", "followers": 613, "is_user_verified": false, "favorite_count": 0, "in_reply_to_status_id": null, "keyword": "boohoo", "language": "fr"}, {"user_id": 1155942427326386176, "user_statuses": 29925, "name": "youuu___", "tweet": "@merivm_ Boohoo collection petite et plt collection petite", "retweets": 0, "location": "", "created": "06-Apr-2021", "followers": 1307, "is_user_verified": false, "favorite_count": 0, "in_reply_to_status_id": 1379173399457636357, "keyword": "boohoo", "language": "fr"}, {"user_id": 1155942427326386176, "user_statuses": 29925, "name": "youuu___", "tweet": "@gsmlu1 Boohoo ou plt collection petite tu trouveras ton bonheur", "retweets": 0, "location": "", "created": "06-Apr-2021", "followers": 1307, "is_user_verified": false, "favorite_count": 0, "in_reply_to_status_id": 1379193359139545089, "keyword": "boohoo", "language": "fr"}, {"user_id": 725071752783630337, "user_statuses": 74856, "name": "souleygk_", "tweet": "Boohoo ils font plus de r\u00e9duction ou koi", "retweets": 0, "location": "", "created": "05-Apr-2021", "followers": 2457, "is_user_verified": false, "favorite_count": 1, "in_reply_to_status_id": null, "keyword": "boohoo", "language": "fr"}, {"user_id": 918059938047459329, "user_statuses": 12288, "name": "millayzss", "tweet": "@gamzee_1346 https://t.co/YgzZrcJjGt tiens (y\u2019a deux autres mod\u00e8les un peu plus fonc\u00e9 aussi)", "retweets": 4, "location": "Casablanca/Oran", "created": "05-Apr-2021", "followers": 1010, "is_user_verified": false, "favorite_count": 17, "in_reply_to_status_id": 1379187323536035842, "keyword": "boohoo", "language": "fr"}, {"user_id": 1550968718, "user_statuses": 74479, "name": "BabsM9", "tweet": "Euh y\u2019a pas la livraison gratuite que boohoo???", "retweets": 0, "location": "jsui invincible jvien du 93", "created": "05-Apr-2021", "followers": 1356, "is_user_verified": false, "favorite_count": 0, "in_reply_to_status_id": null, "keyword": "boohoo", "language": "fr"}, {"user_id": 1295311791476572160, "user_statuses": 607, "name": "SimoneNina5", "tweet": "@Sucres__ Chez moi c\u2019est zalando ou rien. On dirait les galeries lafayettes sur une seule appli. Tout le reste les plt, shein, boohoo et consorts c'est vraiment de la merde", "retweets": 0, "location": "Le V\u00e9sinet, France", "created": "05-Apr-2021", "followers": 12, "is_user_verified": false, "favorite_count": 2, "in_reply_to_status_id": 1379045654278848513, "keyword": "boohoo", "language": "fr"}, {"user_id": 3117773791, "user_statuses": 192609, "name": "RoddieMoiCa", "tweet": "@Quiconque__ Ptdrrr y\u2019a sur Ali Express d\u00e9j\u00e0 apr\u00e8s je pense boohoo PLT", "retweets": 0, "location": "Any/everywhere", "created": "05-Apr-2021", "followers": 1609, "is_user_verified": false, "favorite_count": 0, "in_reply_to_status_id": 1379187587814948864, "keyword": "boohoo", "language": "fr"}, {"user_id": 619863643, "user_statuses": 16732, "name": "kanan243", "tweet": "Boohoo c\u2019est une marque qu\u2019on sous-estim\u00e9 de ouf mais ils font des vrai truc", "retweets": 0, "location": "Pakistan", "created": "05-Apr-2021", "followers": 306, "is_user_verified": false, "favorite_count": 0, "in_reply_to_status_id": null, "keyword": "boohoo", "language": "fr"}, {"user_id": 1267157802277130244, "user_statuses": 2099, "name": "i_hsnn", "tweet": "@mlavatos les filles qui font 1m60 ou moins y\u2019en  sur boohoo petite qui sont parfait", "retweets": 0, "location": "nantess", "created": "05-Apr-2021", "followers": 709, "is_user_verified": false, "favorite_count": 31, "in_reply_to_status_id": 1379120616536731648, "keyword": "boohoo", "language": "fr"}, {"user_id": 1188938706075422725, "user_statuses": 1140, "name": "preciouuuus01", "tweet": "Ont/boohoo la qualit\u00e9 c\u2019est comme shein sur 80% des articles https://t.co/r8LP42tmXa", "retweets": 0, "location": "", "created": "05-Apr-2021", "followers": 122, "is_user_verified": false, "favorite_count": 0, "in_reply_to_status_id": null, "keyword": "boohoo", "language": "fr"}, {"user_id": 1332627397, "user_statuses": 80344, "name": "jamilagrs_", "tweet": "Merci \u00e0 asos, boohoo et new look pour leurs collections petite https://t.co/K5UpAFTdpg", "retweets": 0, "location": "Tours - Alger", "created": "05-Apr-2021", "followers": 1588, "is_user_verified": false, "favorite_count": 1, "in_reply_to_status_id": null, "keyword": "boohoo", "language": "fr"}, {"user_id": 1586731334, "user_statuses": 73421, "name": "jiminie__luv", "tweet": "Voir des gens achet\u00e9s des v\u00eatements qui sont fabriquer dans des conditions ignobles me d\u00e9goutent renseigner vous et arr\u00eat\u00e9 de support\u00e9 l'exploitation humaine...shein pire du pire. Comme pretty little thing, boohoo, et j'en passe. https://t.co/KTZlNepu0N", "retweets": 1, "location": "", "created": "05-Apr-2021", "followers": 1368, "is_user_verified": false, "favorite_count": 9, "in_reply_to_status_id": null, "keyword": "boohoo", "language": "fr"}, {"user_id": 863846895143309312, "user_statuses": 9176, "name": "svmjo", "tweet": "@stecyfenne regarde asos,bershka,boohoo tout ca apr\u00e8s pour les go j\u2019pense shein aussi", "retweets": 0, "location": "Atlanta, GA", "created": "05-Apr-2021", "followers": 839, "is_user_verified": false, "favorite_count": 2, "in_reply_to_status_id": 1379163227213475844, "keyword": "boohoo", "language": "fr"}, {"user_id": 588655310, "user_statuses": 60879, "name": "YrkFiger", "tweet": "Mais wallah la go elle a une seule robe rouge ou quoi ? \nElle conna\u00eet pas shein, asos, pltt, boohoo ? \n\n#MariesAu1erRegard", "retweets": 0, "location": "Paris (From Martinique)", "created": "05-Apr-2021", "followers": 685, "is_user_verified": false, "favorite_count": 1, "in_reply_to_status_id": null, "keyword": "boohoo", "language": "fr"}, {"user_id": 1124418203143278592, "user_statuses": 4207, "name": "insxrd", "tweet": "@ssaanani @lyyakmr Shein boohoo j\u2019en ai vu pleiiinns", "retweets": 0, "location": "l\u00e0-bas", "created": "05-Apr-2021", "followers": 113, "is_user_verified": false, "favorite_count": 0, "in_reply_to_status_id": 1379150573694509060, "keyword": "boohoo", "language": "fr"}, {"user_id": 551210415, "user_statuses": 5560, "name": "fromthediningtx", "tweet": "@juliadmts @Noholita @boohoo Y\u2019a pas \u00e0 \u00eatre aussi joli que \u00e7a \ud83e\udd72\ud83c\udf38 https://t.co/VPEQnfhemM", "retweets": 0, "location": "", "created": "05-Apr-2021", "followers": 322, "is_user_verified": false, "favorite_count": 1, "in_reply_to_status_id": 1379142750113792003, "keyword": "boohoo", "language": "fr"}, {"user_id": 1370431767535087617, "user_statuses": 128, "name": "juliadmts", "tweet": "La collection @Noholita X @boohoo c\u2019est une r\u00e9elle p\u00e9pite \u2728", "retweets": 0, "location": "", "created": "05-Apr-2021", "followers": 8, "is_user_verified": false, "favorite_count": 0, "in_reply_to_status_id": null, "keyword": "boohoo", "language": "fr"}, {"user_id": 1208719565917687813, "user_statuses": 3100, "name": "julianguillen_2", "tweet": "Y\u2019en a qui savent ou trouver de beaux ensemble t shirt/short de couleur pour l\u2019\u00e9t\u00e9 svp ? (a part sur boohoo)", "retweets": 0, "location": "", "created": "05-Apr-2021", "followers": 117, "is_user_verified": false, "favorite_count": 0, "in_reply_to_status_id": null, "keyword": "boohoo", "language": "fr"}, {"user_id": 1079391396866547712, "user_statuses": 327, "name": "Remaayo", "tweet": "@uhh_boohoo @Rapapouel T'es qui toi ?", "retweets": 0, "location": "", "created": "05-Apr-2021", "followers": 38, "is_user_verified": false, "favorite_count": 0, "in_reply_to_status_id": 1379127454363750404, "keyword": "boohoo", "language": "fr"}, {"user_id": 726834324633456640, "user_statuses": 28485, "name": "ngnabii", "tweet": "A boohoo cest fini les makeups de bad bitch on nous fait que du naturel et on shoot des robes \u00e0 fleurs. Tout \u00e7a c\u2019est votre faute \ud83d\ude12", "retweets": 3, "location": "Paris, France", "created": "05-Apr-2021", "followers": 15641, "is_user_verified": false, "favorite_count": 50, "in_reply_to_status_id": null, "keyword": "boohoo", "language": "fr"}, {"user_id": 1226603230760722434, "user_statuses": 19506, "name": "cindyatnk", "tweet": "Mon p\u00e8re m\u2019a montrer son tel avec boohoo dessus, j\u2019ai capt\u00e9 j\u2019ai capt\u00e9 \ud83d\ude3c", "retweets": 0, "location": "\ud83c\uddec\ud83c\uddf7", "created": "05-Apr-2021", "followers": 1000, "is_user_verified": false, "favorite_count": 3, "in_reply_to_status_id": null, "keyword": "boohoo", "language": "fr"}, {"user_id": 980801077967753216, "user_statuses": 5323, "name": "Mmamichouu", "tweet": "Boohoo ils ont fait -60% une fois et depuis lors plus rien,y\u2019a pas \u00e0 \u00eatre radin comme \u00e7a tchip", "retweets": 0, "location": "Lille, France", "created": "05-Apr-2021", "followers": 1292, "is_user_verified": false, "favorite_count": 5, "in_reply_to_status_id": null, "keyword": "boohoo", "language": "fr"}, {"user_id": 2594745706, "user_statuses": 116379, "name": "ishkk28", "tweet": "Boohoo a d\u00e9truit le pr\u00eat \u00e0 porter", "retweets": 0, "location": "", "created": "05-Apr-2021", "followers": 340, "is_user_verified": false, "favorite_count": 0, "in_reply_to_status_id": null, "keyword": "boohoo", "language": "fr"}, {"user_id": 1288839744399585280, "user_statuses": 1458, "name": "AdjouOmolara96", "tweet": "Demain je re\u00e7ois ma commande boohoo", "retweets": 0, "location": "Val-de-Marne, Ile-de-France", "created": "05-Apr-2021", "followers": 17, "is_user_verified": false, "favorite_count": 0, "in_reply_to_status_id": null, "keyword": "boohoo", "language": "fr"}, {"user_id": 934779480232595456, "user_statuses": 19707, "name": "nakad_1", "tweet": "\ud83e\uddfc\nShirt @boohoo PZZ62398-106-18\nCrop top @bershka \nJean @missguided 10148143011\nBag @asos 1827515 \nSneaker @nike blazer mid 77\u2019 \u00e0 Ile-de-France, France https://t.co/OSgYHu89Ce", "retweets": 0, "location": "Ile-de-France", "created": "05-Apr-2021", "followers": 26, "is_user_verified": false, "favorite_count": 0, "in_reply_to_status_id": null, "keyword": "boohoo", "language": "fr"}, {"user_id": 51023815, "user_statuses": 1015, "name": "xybinks", "tweet": "Vous souhaitez faire des \u00e9conomies sur vos achats en ligne ? \ud83e\udd14\n\nJusqu'\u00e0 -80% sur plusieurs site e-commerce ! \ud83d\ude31\n\nValable sur Amazon, Nike, Shein, Boohoo et bien plus ! \ud83d\ude09\n\nPour plus d'informations il suffit de m'envoyer un DM ! \ud83d\udce8 https://t.co/EZjwzJG7dl", "retweets": 21, "location": "France", "created": "05-Apr-2021", "followers": 11307, "is_user_verified": false, "favorite_count": 33, "in_reply_to_status_id": null, "keyword": "boohoo", "language": "fr"}, {"user_id": 1266392606419845122, "user_statuses": 18056, "name": "mnd__y", "tweet": "Boohoo le site il manque de vie c\u2019est abus\u00e9 !", "retweets": 0, "location": "", "created": "05-Apr-2021", "followers": 125, "is_user_verified": false, "favorite_count": 1, "in_reply_to_status_id": 1379087785487958016, "keyword": "boohoo", "language": "fr"}, {"user_id": 1266392606419845122, "user_statuses": 18056, "name": "mnd__y", "tweet": "Le site de PLT il donne plus envie que boohoo", "retweets": 0, "location": "", "created": "05-Apr-2021", "followers": 125, "is_user_verified": false, "favorite_count": 1, "in_reply_to_status_id": null, "keyword": "boohoo", "language": "fr"}, {"user_id": 2484957124, "user_statuses": 24920, "name": "anthonyybrillan", "tweet": "Dans 7 jours je re\u00e7ois ma commande Boohoo \ud83d\ude0d\ud83d\ude0d", "retweets": 0, "location": "", "created": "05-Apr-2021", "followers": 502, "is_user_verified": false, "favorite_count": 0, "in_reply_to_status_id": null, "keyword": "boohoo", "language": "fr"}, {"user_id": 2445600928, "user_statuses": 29754, "name": "sosolastarr", "tweet": "J'ai fait un panier missguided, shein, boohoo, asos. Attends la paye seulement", "retweets": 0, "location": "94", "created": "05-Apr-2021", "followers": 470, "is_user_verified": false, "favorite_count": 0, "in_reply_to_status_id": null, "keyword": "boohoo", "language": "fr"}, {"user_id": 814564238748516352, "user_statuses": 9963, "name": "yasagi_", "tweet": "boohoo pq c\u2019est bad ch\u00e8re comme \u00e7a", "retweets": 0, "location": "", "created": "05-Apr-2021", "followers": 178, "is_user_verified": false, "favorite_count": 0, "in_reply_to_status_id": null, "keyword": "boohoo", "language": "fr"}, {"user_id": 937026799191711744, "user_statuses": 53914, "name": "Kamisama10101", "tweet": "@abel0gy Sur les sites genre plt boohoo ect elle foyn toujours 1m70 c pour \u00e7a moi je regarde cat\u00e9gorie petite p5drrrr", "retweets": 0, "location": "\ub300\ud55c\ubbfc\uad6d \uc11c\uc6b8", "created": "05-Apr-2021", "followers": 243, "is_user_verified": false, "favorite_count": 1, "in_reply_to_status_id": 1379066423365009408, "keyword": "boohoo", "language": "fr"}, {"user_id": 3299569450, "user_statuses": 30354, "name": "kelyane_hery", "tweet": "@ChiinaSkuh quand je re\u00e7ois ma commande boohoo je te montrerai j\u2019ai pris 3 pantalon", "retweets": 0, "location": "94", "created": "05-Apr-2021", "followers": 1795, "is_user_verified": false, "favorite_count": 0, "in_reply_to_status_id": 1379060216713650176, "keyword": "boohoo", "language": "fr"}, {"user_id": 1081825981269241857, "user_statuses": 36183, "name": "ChiinaSkuh", "tweet": "@kelyane_hery V essayer boohoo allez", "retweets": 0, "location": "", "created": "05-Apr-2021", "followers": 719, "is_user_verified": false, "favorite_count": 0, "in_reply_to_status_id": 1379059818049253376, "keyword": "boohoo", "language": "fr"}, {"user_id": 3299569450, "user_statuses": 30354, "name": "kelyane_hery", "tweet": "@ChiinaSkuh ptdrr bah j\u2019te jure que boohoo et shein aussi surtout boohoo", "retweets": 0, "location": "94", "created": "05-Apr-2021", "followers": 1795, "is_user_verified": false, "favorite_count": 0, "in_reply_to_status_id": 1379059486476922880, "keyword": "boohoo", "language": "fr"}, {"user_id": 1299290061868064768, "user_statuses": 3607, "name": "inborngrace", "tweet": "@SSSambush Y\u2019en a sur plt ou boohoo j\u2019crois", "retweets": 1, "location": "", "created": "05-Apr-2021", "followers": 71, "is_user_verified": false, "favorite_count": 2, "in_reply_to_status_id": 1379042794107498499, "keyword": "boohoo", "language": "fr"}, {"user_id": 3299569450, "user_statuses": 30354, "name": "kelyane_hery", "tweet": "j\u2019suis trop press\u00e9e de recevoir ma commande shein et boohoo", "retweets": 0, "location": "94", "created": "05-Apr-2021", "followers": 1795, "is_user_verified": false, "favorite_count": 2, "in_reply_to_status_id": null, "keyword": "boohoo", "language": "fr"}, {"user_id": 1034819056359157760, "user_statuses": 53276, "name": "_pm110", "tweet": "Pourquoi y a que des robes pour les rondes sur boohoo la", "retweets": 0, "location": "", "created": "05-Apr-2021", "followers": 1052, "is_user_verified": false, "favorite_count": 0, "in_reply_to_status_id": null, "keyword": "boohoo", "language": "fr"}, {"user_id": 1009469446329655296, "user_statuses": 10151, "name": "Chamaliya92", "tweet": "\u00c9vitez boohoo les filles !!!!! \nLes prix sont accessibles certes mais la qualit\u00e9 est m\u00e9diocre https://t.co/qYi10dI7cO", "retweets": 0, "location": "Paris, France", "created": "05-Apr-2021", "followers": 204, "is_user_verified": false, "favorite_count": 0, "in_reply_to_status_id": null, "keyword": "boohoo", "language": "fr"}, {"user_id": 1193263606210715649, "user_statuses": 1948, "name": "marieccc_", "tweet": "On est confin\u00e9 j\u2019ai envie de faire du shopping compulsif sur PLT et Boohoo \ud83d\ude2d\ud83d\ude2d\ud83d\ude2d", "retweets": 0, "location": "Lyon, France", "created": "05-Apr-2021", "followers": 307, "is_user_verified": false, "favorite_count": 0, "in_reply_to_status_id": null, "keyword": "boohoo", "language": "fr"}, {"user_id": 387088059, "user_statuses": 238903, "name": "261297_", "tweet": "Fini l\u2019\u00e9poque du 34/XS je me voile la face il serait temps de faire un panier Shein ou boohoo \ud83d\ude44", "retweets": 0, "location": "", "created": "05-Apr-2021", "followers": 1907, "is_user_verified": false, "favorite_count": 0, "in_reply_to_status_id": 1378877803291148292, "keyword": "boohoo", "language": "fr"}, {"user_id": 1088906024877215745, "user_statuses": 39033, "name": "petitvicelard", "tweet": "@Diabs_sn Ptdrrrr ah celui-l\u00e0 j\u2019lai grave commander sur boohoo aussi, tu me dis si tu veux que je te le pr\u00eate", "retweets": 0, "location": "", "created": "05-Apr-2021", "followers": 1810, "is_user_verified": false, "favorite_count": 0, "in_reply_to_status_id": 1378862052559761418, "keyword": "boohoo", "language": "fr"}, {"user_id": 840774964676444160, "user_statuses": 13859, "name": "idykp", "tweet": "Wewe boohoo balancez un code promo", "retweets": 0, "location": "Paris _Bamako ", "created": "04-Apr-2021", "followers": 2105, "is_user_verified": false, "favorite_count": 0, "in_reply_to_status_id": null, "keyword": "boohoo", "language": "fr"}, {"user_id": 2754847372, "user_statuses": 184802, "name": "BadGuyAntoine", "tweet": "j\u2019ai valid\u00e9 ma commande boohoo je me sens bien", "retweets": 0, "location": "Mexico, Mexique", "created": "04-Apr-2021", "followers": 1769, "is_user_verified": false, "favorite_count": 1, "in_reply_to_status_id": null, "keyword": "boohoo", "language": "fr"}, {"user_id": 1276183216572043265, "user_statuses": 4845, "name": "NinaNon_", "tweet": "Ils veulent ma peau boohoo la j'ai un pull dans le panier https://t.co/NAQza1v7GH", "retweets": 0, "location": "", "created": "04-Apr-2021", "followers": 158, "is_user_verified": false, "favorite_count": 1, "in_reply_to_status_id": null, "keyword": "boohoo", "language": "fr"}, {"user_id": 1076396935110672384, "user_statuses": 3038, "name": "naluimy", "tweet": "la collection de boohoo x noholita l\u00e0 miam", "retweets": 0, "location": "Toulouse, France", "created": "04-Apr-2021", "followers": 521, "is_user_verified": false, "favorite_count": 0, "in_reply_to_status_id": null, "keyword": "boohoo", "language": "fr"}, {"user_id": 1314663914177794049, "user_statuses": 1252, "name": "wawa_fss", "tweet": "@yss78__ Boohoo, asos, plt tu mets sweat robe et il y en a plein", "retweets": 0, "location": "Paris-Oujda", "created": "04-Apr-2021", "followers": 123, "is_user_verified": false, "favorite_count": 1, "in_reply_to_status_id": 1378784850426142730, "keyword": "boohoo", "language": "fr"}, {"user_id": 716716374995894272, "user_statuses": 58876, "name": "HejaBaayna", "tweet": "Un site d habits a me conseiller ? Pcq plt missguided et boohoo j\u2019ai un peu la flemme en ce moment", "retweets": 0, "location": "Singapour", "created": "04-Apr-2021", "followers": 1328, "is_user_verified": false, "favorite_count": 0, "in_reply_to_status_id": null, "keyword": "boohoo", "language": "fr"}, {"user_id": 1227318072064839684, "user_statuses": 33702, "name": "semra_ylz", "tweet": "Att Att depuis quand y\u2019a des araign\u00e9es dans nos colis qui viennent de boohoo ?", "retweets": 0, "location": "E\u2661", "created": "04-Apr-2021", "followers": 720, "is_user_verified": false, "favorite_count": 6, "in_reply_to_status_id": null, "keyword": "boohoo", "language": "fr"}, {"user_id": 1214863478848196608, "user_statuses": 82848, "name": "nonod971", "tweet": "@JeSuis_Pamelaaa @_sandyxix Mdrrrrr tenez https://t.co/n9q0LmSpF7", "retweets": 0, "location": "Ile-de-France, France", "created": "04-Apr-2021", "followers": 3948, "is_user_verified": false, "favorite_count": 2, "in_reply_to_status_id": 1378760646154715143, "keyword": "boohoo", "language": "fr"}, {"user_id": 1214863478848196608, "user_statuses": 82848, "name": "nonod971", "tweet": "Svp les amis j\u2019ai besoin de votre aide. J\u2019ai envie de commander ces articles mais je sais si c\u2019est uniquement le sweat ou si c\u2019est l\u2019ensemble. Boohoo donne zero information... https://t.co/XTSTEzBUXh", "retweets": 2, "location": "Ile-de-France, France", "created": "04-Apr-2021", "followers": 3948, "is_user_verified": false, "favorite_count": 0, "in_reply_to_status_id": null, "keyword": "boohoo", "language": "fr"}, {"user_id": 2770962472, "user_statuses": 11574, "name": "_MG1996", "tweet": "Boohoo c\u2019est pas mal hun", "retweets": 0, "location": "Marseille ", "created": "04-Apr-2021", "followers": 2657, "is_user_verified": false, "favorite_count": 0, "in_reply_to_status_id": null, "keyword": "boohoo", "language": "fr"}, {"user_id": 1245936834493980672, "user_statuses": 10101, "name": "Soulacre_93", "tweet": "@Diaah_224 @sxxsweety Comme sur Boohoo au final c\u2019est juste les vrai prix qu\u2019on paye y\u2019a z\u00e9ro r\u00e9duction \ud83d\ude2d", "retweets": 0, "location": "93 ", "created": "04-Apr-2021", "followers": 1849, "is_user_verified": false, "favorite_count": 2, "in_reply_to_status_id": 1378739498918416386, "keyword": "boohoo", "language": "fr"}, {"user_id": 1233854816050438146, "user_statuses": 161, "name": "JBugaut", "tweet": "Ne rate pas l'article boohoo Blazers que je vends sur @VintedFR. Taille XS / 34 / 6 \u00e0 10,00\u00a0\u20ac \u20ac ! https://t.co/8PdNzLHIsW https://t.co/XoGnErhf6M", "retweets": 0, "location": "", "created": "04-Apr-2021", "followers": 1, "is_user_verified": false, "favorite_count": 0, "in_reply_to_status_id": null, "keyword": "boohoo", "language": "fr"}, {"user_id": 1375742211728478210, "user_statuses": 157, "name": "Nawllee", "tweet": "@loubnaxjeon Celui que yassouk a mis sur son Snap et un pantalon \u00e9vas\u00e9 \u00e0 rayure boohoo", "retweets": 0, "location": "district de Shiganshina", "created": "04-Apr-2021", "followers": 34, "is_user_verified": false, "favorite_count": 0, "in_reply_to_status_id": 1378713220849004547, "keyword": "boohoo", "language": "fr"}, {"user_id": 1374661296709373954, "user_statuses": 2544, "name": "123sssalm", "tweet": "@qlf_detp213 Oui wsh c\u2019est ce que j\u2019ai appris genre boohoo", "retweets": 0, "location": "", "created": "04-Apr-2021", "followers": 124, "is_user_verified": false, "favorite_count": 0, "in_reply_to_status_id": 1378681756119932930, "keyword": "boohoo", "language": "fr"}, {"user_id": 1307623881071620096, "user_statuses": 8953, "name": "Riensansmoi_", "tweet": "@123sssalm Boohoo oui et missguided s\u00fbrement si c\u2019est anglais", "retweets": 0, "location": "Gaza , palestine ", "created": "04-Apr-2021", "followers": 1285, "is_user_verified": false, "favorite_count": 0, "in_reply_to_status_id": 1378679961444319232, "keyword": "boohoo", "language": "fr"}, {"user_id": 1110848069434781697, "user_statuses": 1238, "name": "mehedd_", "tweet": "@juitheo boohoo mais mon reuf rupture dsl", "retweets": 0, "location": "Choisy-le-Roi, France", "created": "04-Apr-2021", "followers": 366, "is_user_verified": false, "favorite_count": 1, "in_reply_to_status_id": 1378669168946466817, "keyword": "boohoo", "language": "fr"}, {"user_id": 1368998114900795396, "user_statuses": 9, "name": "GabeauxP", "tweet": "@boohoo des incomp\u00e9tents et malhonn\u00eates il faut les fuirs", "retweets": 0, "location": "", "created": "04-Apr-2021", "followers": 0, "is_user_verified": false, "favorite_count": 0, "in_reply_to_status_id": null, "keyword": "boohoo", "language": "fr"}, {"user_id": 927382348576034816, "user_statuses": 110960, "name": "_Doudoune_", "tweet": "En ce dimanche de p\u00e2que je viens de valider mon panier SHEIN et je vais valider mon panier boohoo la \ud83d\ude2d\ud83d\udc80", "retweets": 0, "location": "Guadeloupe", "created": "04-Apr-2021", "followers": 1244, "is_user_verified": false, "favorite_count": 0, "in_reply_to_status_id": null, "keyword": "boohoo", "language": "fr"}, {"user_id": 617183348, "user_statuses": 2557, "name": "MokhtarBenAyed", "tweet": "Boohoo Coupon Codes April 2021 https://t.co/OMe6Suq6gT #Panarin", "retweets": 0, "location": "Tunisia", "created": "04-Apr-2021", "followers": 3789, "is_user_verified": false, "favorite_count": 0, "in_reply_to_status_id": null, "keyword": "boohoo", "language": "fr"}, {"user_id": 1035144931147427842, "user_statuses": 8433, "name": "ryry9721", "tweet": "@callmenaomie dmg vrmt mais boohoo y\u2019a grv des trucs mais pas de code puree", "retweets": 0, "location": "", "created": "03-Apr-2021", "followers": 203, "is_user_verified": false, "favorite_count": 0, "in_reply_to_status_id": 1378489479976075267, "keyword": "boohoo", "language": "fr"}, {"user_id": 1195357653754617857, "user_statuses": 6512, "name": "sabryztn", "tweet": "@benny80z boohoo viens pv frg j'tenvoie le lien", "retweets": 0, "location": "Bruxelles, Belgique", "created": "03-Apr-2021", "followers": 362, "is_user_verified": false, "favorite_count": 0, "in_reply_to_status_id": 1378479080459358208, "keyword": "boohoo", "language": "fr"}, {"user_id": 1349009184222797829, "user_statuses": 360, "name": "Gyuki__8", "tweet": "@smabinho Boohoo Asos vous en avez des beaux et pas trop chers", "retweets": 0, "location": "Konoha", "created": "03-Apr-2021", "followers": 8, "is_user_verified": false, "favorite_count": 0, "in_reply_to_status_id": 1378298210687582209, "keyword": "boohoo", "language": "fr"}, {"user_id": 1250817715457134592, "user_statuses": 7225, "name": "Konoha6777", "tweet": "@Bilaal_67 T\u00e9l\u00e9charge \u00e7a l'appli au milieu Boohoo Man https://t.co/MyMlgzxDNe", "retweets": 0, "location": "Strasbourg/nador", "created": "03-Apr-2021", "followers": 734, "is_user_verified": false, "favorite_count": 1, "in_reply_to_status_id": 1378447421483679759, "keyword": "boohoo", "language": "fr"}, {"user_id": 3300779428, "user_statuses": 28878, "name": "dlcsom", "tweet": "les varsity jackets de boohoo vmt \ud83e\udd0c\ud83e\udd0c j'ai envie de prendre toutes les couleurs", "retweets": 0, "location": "she/her ", "created": "03-Apr-2021", "followers": 1365, "is_user_verified": false, "favorite_count": 1, "in_reply_to_status_id": null, "keyword": "boohoo", "language": "fr"}, {"user_id": 2165291221, "user_statuses": 8608, "name": "ishoptodrop", "tweet": "https://t.co/EV2lI45bfc Voucher Codes, Promo Codes &amp; Discounts April 2021: https://t.co/dqdyKPfMCx", "retweets": 0, "location": "Guildford", "created": "03-Apr-2021", "followers": 99, "is_user_verified": false, "favorite_count": 0, "in_reply_to_status_id": null, "keyword": "boohoo", "language": "fr"}, {"user_id": 4074649156, "user_statuses": 11804, "name": "naiia_franche", "tweet": "@BsrClemence Boohoo, mes meilleurs trainings viennent de l\u00e0 bas \ud83e\udd70", "retweets": 0, "location": "Bruxelles, Belgique", "created": "03-Apr-2021", "followers": 2833, "is_user_verified": false, "favorite_count": 1, "in_reply_to_status_id": 1378432861531992065, "keyword": "boohoo", "language": "fr"}, {"user_id": 1185257577673875456, "user_statuses": 14162, "name": "ornetle", "tweet": "on est le 03 j\u2019ai fais une commande de 50\u20ac chez boohoo et une de 70\u20ac chez Shein \nFaut que je me trouve une occupation dans ma vie je peux pas \u00e9ternellement m\u2019acheter des v\u00eatements quand j\u2019ai un coup de mou \ud83e\udd27\ud83d\udd2b", "retweets": 0, "location": "", "created": "03-Apr-2021", "followers": 863, "is_user_verified": false, "favorite_count": 6, "in_reply_to_status_id": null, "keyword": "boohoo", "language": "fr"}, {"user_id": 1322860649760854016, "user_statuses": 1198, "name": "Lalyaact", "tweet": "J\u2019ai re\u00e7u un jean de chez Boohoo il m\u2019allait exactement comme \u00e7a \ud83d\ude21 https://t.co/VatIvgeCSb", "retweets": 0, "location": "Val-d'Oise, Ile-de-France", "created": "03-Apr-2021", "followers": 253, "is_user_verified": false, "favorite_count": 1, "in_reply_to_status_id": null, "keyword": "boohoo", "language": "fr"}, {"user_id": 1305670523871993856, "user_statuses": 4, "name": "sabinengm", "tweet": "@_maytall @MeriiemJr Les filles je suis comme vous  PLT , missguided et boohoo ont des taille \u00e0 partir d\u20191m70 du c\u00f4t\u00e9 tall j\u2019vous conseil d\u2019y faire un tour", "retweets": 0, "location": "", "created": "03-Apr-2021", "followers": 18, "is_user_verified": false, "favorite_count": 2, "in_reply_to_status_id": 1378085256847310853, "keyword": "boohoo", "language": "fr"}, {"user_id": 1086639348471214080, "user_statuses": 5912, "name": "Lexiiiie1", "tweet": "@boohoo faites d stock vous saoulez fr", "retweets": 0, "location": "Shiganshina ", "created": "03-Apr-2021", "followers": 147, "is_user_verified": false, "favorite_count": 1, "in_reply_to_status_id": null, "keyword": "boohoo", "language": "fr"}, {"user_id": 85813722, "user_statuses": 11456, "name": "Call_me_mika", "tweet": "La v\u00e9rit\u00e9!!! Quand je vois les taro sur boohoo j'ai envi de crier https://t.co/4LsQjOiHro", "retweets": 0, "location": "Lisbonne, Portugal", "created": "03-Apr-2021", "followers": 286, "is_user_verified": false, "favorite_count": 1, "in_reply_to_status_id": null, "keyword": "boohoo", "language": "fr"}, {"user_id": 83791760, "user_statuses": 74123, "name": "LovelyxNiha", "tweet": "Euh Boohoo qui vend des brassi\u00e8res \u00e0 15\u20ac ?! C\u2019est de l\u2019abus.", "retweets": 0, "location": "Paris, France", "created": "03-Apr-2021", "followers": 623, "is_user_verified": false, "favorite_count": 0, "in_reply_to_status_id": null, "keyword": "boohoo", "language": "fr"}, {"user_id": 1208846648560029696, "user_statuses": 5268, "name": "herlif_", "tweet": "Franchement boohoo pour la rapidit\u00e9 du remboursement vous \u00eates comme \u00e7a \ud83d\udc4d\ud83c\udffb", "retweets": 0, "location": "", "created": "03-Apr-2021", "followers": 58, "is_user_verified": false, "favorite_count": 0, "in_reply_to_status_id": null, "keyword": "boohoo", "language": "fr"}, {"user_id": 1345419841050697731, "user_statuses": 4397, "name": "Jouesbriochees", "tweet": "On va encore dire que je suis \u201cboujee\u201d mais j\u2019ai jamais achet\u00e9 une tenue compl\u00e8te \u00e0 moins de 50\u20ac\nDonnez vos adresses (hors PLT et Boohoo) https://t.co/Titxf2xDIX", "retweets": 0, "location": "", "created": "03-Apr-2021", "followers": 63, "is_user_verified": false, "favorite_count": 0, "in_reply_to_status_id": null, "keyword": "boohoo", "language": "fr"}, {"user_id": 152383220, "user_statuses": 35053, "name": "belindamrb", "tweet": "Mais enft les amis, un ensemble nike de femme co\u00fbte autant cher qu\u2019un ensemble nike d\u2019homme. Boohoo asos etc font aussi des training je pense, personne vous emp\u00eache d\u2019y acheter aussi hn.. https://t.co/dubnZL0iCq", "retweets": 2, "location": "Fire nation ", "created": "03-Apr-2021", "followers": 2090, "is_user_verified": false, "favorite_count": 2, "in_reply_to_status_id": null, "keyword": "boohoo", "language": "fr"}, {"user_id": 1017864407270002689, "user_statuses": 39866, "name": "hanamnzali76", "tweet": "Boohoo je les aime wsh pour 10\u20ac j\u2019ai un t-shirt dans les magasins physique j\u2019avais jamais les moyens de m\u2019acheter des habits cool maintenant je peux \u00eatre styl\u00e9 avec mon petit budget", "retweets": 0, "location": "Le Havre, France", "created": "03-Apr-2021", "followers": 613, "is_user_verified": false, "favorite_count": 0, "in_reply_to_status_id": null, "keyword": "boohoo", "language": "fr"}, {"user_id": 1283093645990789121, "user_statuses": 12215, "name": "MaadameBass", "tweet": "@bibi0ff https://t.co/IEFMORijtB\nDeja tiens celle l\u00e0 et normalement y\u2019en a d\u2019autre en bas chou\u2764\ufe0f", "retweets": 0, "location": "Bruxelles, Belgique", "created": "03-Apr-2021", "followers": 2207, "is_user_verified": false, "favorite_count": 0, "in_reply_to_status_id": 1378385131552014339, "keyword": "boohoo", "language": "fr"}, {"user_id": 810593516623630340, "user_statuses": 4811, "name": "zakaoua", "tweet": "Code r\u00e9duc Boohoo https://t.co/6zIxRQTLog #codepromoboohoo", "retweets": 0, "location": "France", "created": "03-Apr-2021", "followers": 29, "is_user_verified": false, "favorite_count": 2, "in_reply_to_status_id": null, "keyword": "boohoo", "language": "fr"}, {"user_id": 1029362977680580609, "user_statuses": 51232, "name": "lmskkk", "tweet": "@Maylow7_ Ahhh peut-\u00eatre sur boohoo", "retweets": 0, "location": "Bruxelles, Belgique", "created": "03-Apr-2021", "followers": 2276, "is_user_verified": false, "favorite_count": 1, "in_reply_to_status_id": 1378335708658737155, "keyword": "boohoo", "language": "fr"}, {"user_id": 1000079383942623232, "user_statuses": 42382, "name": "octaavinhoo", "tweet": "La vie sur Boohoo les survet ils sont frais https://t.co/Z246b1tDQ9", "retweets": 0, "location": "York Shin City", "created": "03-Apr-2021", "followers": 474, "is_user_verified": false, "favorite_count": 0, "in_reply_to_status_id": null, "keyword": "boohoo", "language": "fr"}, {"user_id": 536218295, "user_statuses": 43205, "name": "praizthesun", "tweet": "Dites-vous y\u2019a des mecs qui s\u2019habillent chez Boohoo qui pr\u00e9tendent \u00eatre h\u00e9t\u00e9rosexuel https://t.co/MZIwYu2dQ2", "retweets": 1, "location": "Lordran", "created": "03-Apr-2021", "followers": 220, "is_user_verified": false, "favorite_count": 1, "in_reply_to_status_id": null, "keyword": "boohoo", "language": "fr"}, {"user_id": 4754146823, "user_statuses": 20963, "name": "Vaskobrvms", "tweet": "@gavskooo boohoo les survet sont vraiment incroyable", "retweets": 0, "location": "Paris, France", "created": "03-Apr-2021", "followers": 1295, "is_user_verified": false, "favorite_count": 2, "in_reply_to_status_id": 1378311515644821507, "keyword": "boohoo", "language": "fr"}, {"user_id": 1347942599903031299, "user_statuses": 9132, "name": "gavskooo", "tweet": "Moi maintenant mes survet jvais les acheter sur boohoo ou asos", "retweets": 0, "location": "London, England", "created": "03-Apr-2021", "followers": 1145, "is_user_verified": false, "favorite_count": 4, "in_reply_to_status_id": null, "keyword": "boohoo", "language": "fr"}, {"user_id": 1106671838741045249, "user_statuses": 8952, "name": "_Banhbao_", "tweet": "Orh les mannequins boohoo je peux plus me les voir", "retweets": 0, "location": "", "created": "03-Apr-2021", "followers": 302, "is_user_verified": false, "favorite_count": 0, "in_reply_to_status_id": null, "keyword": "boohoo", "language": "fr"}, {"user_id": 1369723232803303425, "user_statuses": 1062, "name": "Kokopopssssss", "tweet": "Nike pour les femmes c'est aussi cher que pour les hommes et pour boohoo c'est pareille, \u00e7a sera moins cher homme comme femme", "retweets": 0, "location": "", "created": "03-Apr-2021", "followers": 36, "is_user_verified": false, "favorite_count": 1, "in_reply_to_status_id": 1378297940255633412, "keyword": "boohoo", "language": "fr"}, {"user_id": 1369723232803303425, "user_statuses": 1062, "name": "Kokopopssssss", "tweet": "Mdrrr si tu compares boohoo et nike forc\u00e9ment hein https://t.co/FRmiuFCIpo", "retweets": 0, "location": "", "created": "03-Apr-2021", "followers": 36, "is_user_verified": false, "favorite_count": 0, "in_reply_to_status_id": null, "keyword": "boohoo", "language": "fr"}, {"user_id": 415483500, "user_statuses": 4958, "name": "Marionbouu", "tweet": "@Nathalie_Dolivo Exploitation des travailleurs dans les usines Boohoo pour des fringues de merde ! Donc non on ne comprend pas pourquoi !", "retweets": 0, "location": "", "created": "03-Apr-2021", "followers": 126, "is_user_verified": false, "favorite_count": 2, "in_reply_to_status_id": 1378075902018342914, "keyword": "boohoo", "language": "fr"}, {"user_id": 1180807702441857024, "user_statuses": 49611, "name": "arl2ykz", "tweet": "@3mbrn mais jcrois y\u2019a des frais de douanes sur boohoo et plt mtn \ud83d\ude14\ud83d\ude14", "retweets": 0, "location": "la puenta ", "created": "03-Apr-2021", "followers": 1422, "is_user_verified": false, "favorite_count": 0, "in_reply_to_status_id": 1378271641898266629, "keyword": "boohoo", "language": "fr"}, {"user_id": 800385546, "user_statuses": 106485, "name": "johmasse", "tweet": "Si les anglais s\u2019habillent pas en Boohoo ils cr\u00e8vent ou quoi", "retweets": 0, "location": "", "created": "02-Apr-2021", "followers": 4308, "is_user_verified": false, "favorite_count": 0, "in_reply_to_status_id": null, "keyword": "boohoo", "language": "fr"}, {"user_id": 825853692, "user_statuses": 15021, "name": "SoniaGhen", "tweet": "Outr\u00e9e par ce reportage \u00e0 voir !! Boohoo \ud83d\uddd1 https://t.co/bocuWLIzU8", "retweets": 1, "location": "", "created": "02-Apr-2021", "followers": 234, "is_user_verified": false, "favorite_count": 0, "in_reply_to_status_id": null, "keyword": "boohoo", "language": "fr"}, {"user_id": 4203328653, "user_statuses": 12523, "name": "2amz8", "tweet": "@Just_Fly8 Boohoo va voir", "retweets": 0, "location": "\u00c7ADONNE\ud83e\udd0c", "created": "02-Apr-2021", "followers": 338, "is_user_verified": false, "favorite_count": 0, "in_reply_to_status_id": 1378104812361895937, "keyword": "boohoo", "language": "fr"}, {"user_id": 1268804190819811329, "user_statuses": 1594, "name": "sa_prl", "tweet": "J\u2019ai encore fait une commande sur boohoo \ud83d\udc49\ud83c\udffc\ud83d\udc48\ud83c\udffc \ud83d\ude36", "retweets": 0, "location": "92", "created": "02-Apr-2021", "followers": 28, "is_user_verified": false, "favorite_count": 0, "in_reply_to_status_id": null, "keyword": "boohoo", "language": "fr"}, {"user_id": 1091678731, "user_statuses": 70357, "name": "Nathalie_Dolivo", "tweet": "Boohoo x Noholita : d\u00e9couvrez la s\u00e9lection de Noholita pour le printemps 2021: Depuis des ann\u00e9es, Noholita est fan de la marque Boohoo... et on comprend pourquoi ! Pi\u00e8ces styl\u00e9es ou pi\u00e8ces intemporelles, le tout \u00e0 petits prix, l'eshop ne nous d\u00e9\u00e7oit\u2026 https://t.co/iP2RxVy4dC", "retweets": 0, "location": "", "created": "02-Apr-2021", "followers": 442, "is_user_verified": false, "favorite_count": 0, "in_reply_to_status_id": null, "keyword": "boohoo", "language": "fr"}, {"user_id": 1079391396866547712, "user_statuses": 327, "name": "Remaayo", "tweet": "@uhh_boohoo Mskn ce mec l\u00e0 hein @Rapapouel", "retweets": 0, "location": "", "created": "02-Apr-2021", "followers": 38, "is_user_verified": false, "favorite_count": 0, "in_reply_to_status_id": 1378046674329829381, "keyword": "boohoo", "language": "fr"}, {"user_id": 1107182161, "user_statuses": 98113, "name": "kika_lalah", "tweet": "comment \u00e7a boohoo me dit que mon colis est en Angleterre le 1er Avril. Si c'est une blague elle est pas dr\u00f4le donnez moi mes affaires !!!!!!! https://t.co/GuNSKil2VH", "retweets": 0, "location": "Land of the lustrous", "created": "02-Apr-2021", "followers": 428, "is_user_verified": false, "favorite_count": 2, "in_reply_to_status_id": null, "keyword": "boohoo", "language": "fr"}, {"user_id": 1189870786057834496, "user_statuses": 47520, "name": "shlaginiho", "tweet": "SUR BOOHOO C\u2019EST DES TAILLE AM\u00c9RICAINE ???", "retweets": 0, "location": "Ile-de-France, France", "created": "02-Apr-2021", "followers": 10416, "is_user_verified": false, "favorite_count": 1, "in_reply_to_status_id": null, "keyword": "boohoo", "language": "fr"}, {"user_id": 1284274427258175488, "user_statuses": 2179, "name": "dzzamrr", "tweet": "euh boohoo \u00e7a taille super petit en jean mom choqu\u00e9 jvais devoir prendre du 42 alors que je fais du 38", "retweets": 0, "location": "BeskraBatna", "created": "02-Apr-2021", "followers": 132, "is_user_verified": false, "favorite_count": 0, "in_reply_to_status_id": null, "keyword": "boohoo", "language": "fr"}, {"user_id": 934779480232595456, "user_statuses": 19707, "name": "nakad_1", "tweet": "Total look @boohoo . outfit inspo @nazjaa \ud83d\udda4\n\nTop FZZ84966\nVeste FZZ04555\nJeans FZZ05028\n\nIl y a une nouvelle vid\u00e9o sur ma cha\u00eene , lien dans ma bio \ud83d\ude0e \u00e0 Ile-de-France, France https://t.co/6ifbIC1FAZ", "retweets": 0, "location": "Ile-de-France", "created": "02-Apr-2021", "followers": 26, "is_user_verified": false, "favorite_count": 0, "in_reply_to_status_id": null, "keyword": "boohoo", "language": "fr"}, {"user_id": 1213756589510807552, "user_statuses": 22747, "name": "whoslina_", "tweet": "@_l0va jsp n\u2019importe aliexpress asos boohoo shein n\u2019importe", "retweets": 0, "location": "straykids", "created": "02-Apr-2021", "followers": 223, "is_user_verified": false, "favorite_count": 0, "in_reply_to_status_id": 1378036459115065350, "keyword": "boohoo", "language": "fr"}, {"user_id": 764083080, "user_statuses": 57812, "name": "Maimeety", "tweet": "jai fais des commandes chez boohoo et shein thlr ... des robes t\u2019as peur", "retweets": 0, "location": "", "created": "02-Apr-2021", "followers": 1058, "is_user_verified": false, "favorite_count": 0, "in_reply_to_status_id": null, "keyword": "boohoo", "language": "fr"}, {"user_id": 242381591, "user_statuses": 58020, "name": "InsidePublic", "tweet": "\ud83d\udea8 Boohoo x Noholita : d\u00e9couvrez la s\u00e9lection de Noholita pour le printemps 2021 https://t.co/QHELBovSBo https://t.co/AYNPSLdF57", "retweets": 1, "location": "Levallois-Perret", "created": "02-Apr-2021", "followers": 13344, "is_user_verified": true, "favorite_count": 0, "in_reply_to_status_id": null, "keyword": "boohoo", "language": "fr"}, {"user_id": 1531700534, "user_statuses": 21435, "name": "SandaleTendance", "tweet": "Boohoo x Noholita : d\u00e9couvrez la s\u00e9lection de Noholita pour le printemps 2021 - https://t.co/9zXwna4nHO https://t.co/J1jm1V0oeL", "retweets": 0, "location": "Paris", "created": "02-Apr-2021", "followers": 2408, "is_user_verified": false, "favorite_count": 0, "in_reply_to_status_id": null, "keyword": "boohoo", "language": "fr"}, {"user_id": 631551524, "user_statuses": 214927, "name": "_rockstarrrrr", "tweet": "qd boohoo me rembourse ca me\ud83e\udd70\ud83e\udd70\ud83e\udd70\ud83e\udd70\ud83e\udd70\ud83e\udd70\ud83e\udd70\ud83e\udd70\ud83e\udd70\ud83e\udd70\ud83e\udd70\ud83e\udd70\ud83e\udd70", "retweets": 0, "location": "", "created": "02-Apr-2021", "followers": 1561, "is_user_verified": false, "favorite_count": 1, "in_reply_to_status_id": null, "keyword": "boohoo", "language": "fr"}, {"user_id": 1347349640, "user_statuses": 22803, "name": "CaaitlinAskewxx", "tweet": "\ud83d\ude2d\ud83d\ude2d Bond? https://t.co/5bW51Md1UK", "retweets": 0, "location": "England, United Kingdom", "created": "02-Apr-2021", "followers": 280, "is_user_verified": false, "favorite_count": 0, "in_reply_to_status_id": null, "keyword": "boohoo", "language": "fr"}, {"user_id": 936968124, "user_statuses": 41172, "name": "docdocdocteur", "tweet": "Il y\u2019a de vrai pantalons chez Asos et Boohoo , vous allez cherchez loin chez Cos", "retweets": 0, "location": "Austin, TX", "created": "02-Apr-2021", "followers": 1575, "is_user_verified": false, "favorite_count": 0, "in_reply_to_status_id": null, "keyword": "boohoo", "language": "fr"}, {"user_id": 948289102843138048, "user_statuses": 15062, "name": "araboyy_", "tweet": "@mimi_sln T\u2019es une boohoo girl toi", "retweets": 0, "location": "", "created": "02-Apr-2021", "followers": 423, "is_user_verified": false, "favorite_count": 0, "in_reply_to_status_id": 1378007305623633927, "keyword": "boohoo", "language": "fr"}, {"user_id": 1115366609424650241, "user_statuses": 13069, "name": "mimi_sln", "tweet": "G trop la n contre boohoo c bon", "retweets": 0, "location": "", "created": "02-Apr-2021", "followers": 204, "is_user_verified": false, "favorite_count": 1, "in_reply_to_status_id": null, "keyword": "boohoo", "language": "fr"}, {"user_id": 723979144619524096, "user_statuses": 4824, "name": "Noemie_Rdj", "tweet": "Boohoo et Shein va falloir se d\u00e9p\u00eacher l\u00e0 par contre", "retweets": 0, "location": "Ile-de-France, France", "created": "02-Apr-2021", "followers": 815, "is_user_verified": false, "favorite_count": 1, "in_reply_to_status_id": null, "keyword": "boohoo", "language": "fr"}, {"user_id": 224371766, "user_statuses": 77281, "name": "Ines_Diane", "tweet": "@LaZonzon G\u00e9ant de la fast fashion \u00e0 l\u2019instar des Boohoo, Pretty little things et autres Missguided", "retweets": 0, "location": "", "created": "02-Apr-2021", "followers": 1343, "is_user_verified": false, "favorite_count": 0, "in_reply_to_status_id": 1377978582916534274, "keyword": "boohoo", "language": "fr"}, {"user_id": 2233322490, "user_statuses": 17281, "name": "neeyance", "tweet": "Franchement @boohoo je peut plus commander chez eux trop de mauvaises exp\u00e9riences entre les v\u00eatements qui taille mal et des colis jamais arriver \u00e0 destination! c\u2019est finis \ud83d\ude45\ud83c\udffe\u200d\u2640\ufe0f", "retweets": 0, "location": "AtL", "created": "02-Apr-2021", "followers": 265, "is_user_verified": false, "favorite_count": 1, "in_reply_to_status_id": null, "keyword": "boohoo", "language": "fr"}, {"user_id": 2500127203, "user_statuses": 2545, "name": "Ray_SarkarUK", "tweet": "@Swamy39 Rant Rant Rant..... Boohoo \ud83d\ude2d", "retweets": 0, "location": "United Kingdom", "created": "02-Apr-2021", "followers": 9, "is_user_verified": false, "favorite_count": 0, "in_reply_to_status_id": 1377943860546920450, "keyword": "boohoo", "language": "fr"}, {"user_id": 554167231, "user_statuses": 6383, "name": "ins_________", "tweet": "Boohoo ils abusent avec leurs ballerines s\u00e9rieux", "retweets": 0, "location": "", "created": "02-Apr-2021", "followers": 247, "is_user_verified": false, "favorite_count": 1, "in_reply_to_status_id": null, "keyword": "boohoo", "language": "fr"}, {"user_id": 1253280618466742273, "user_statuses": 16427, "name": "samazzzzz_", "tweet": "boohoo y\u2019a des frais de douane ?", "retweets": 0, "location": "cosa nostra ", "created": "02-Apr-2021", "followers": 1028, "is_user_verified": false, "favorite_count": 2, "in_reply_to_status_id": null, "keyword": "boohoo", "language": "fr"}, {"user_id": 1353699852434223104, "user_statuses": 2787, "name": "sarazine__", "tweet": "@iam_alaiaaa @Sensei922 Non non Jsuis heureuse avec boohoo et mes commandes d\u2019Instagram", "retweets": 0, "location": "Paris, France", "created": "02-Apr-2021", "followers": 897, "is_user_verified": false, "favorite_count": 0, "in_reply_to_status_id": 1377894086418530305, "keyword": "boohoo", "language": "fr"}, {"user_id": 1353699852434223104, "user_statuses": 2787, "name": "sarazine__", "tweet": "@Sensei922 Bershka et shein la qualit\u00e9 je trouve pas ouf des fois surtout pour les veste Je pr\u00e9f\u00e8re largement boohoo et les petits compte sur insta", "retweets": 0, "location": "Paris, France", "created": "02-Apr-2021", "followers": 897, "is_user_verified": false, "favorite_count": 0, "in_reply_to_status_id": 1377893817978908675, "keyword": "boohoo", "language": "fr"}, {"user_id": 1555763934, "user_statuses": 125235, "name": "Erinicka", "tweet": "Y\u2019a des frais de douanes pour PLt ? Boohoo je sais que non", "retweets": 0, "location": "France", "created": "02-Apr-2021", "followers": 1661, "is_user_verified": false, "favorite_count": 0, "in_reply_to_status_id": null, "keyword": "boohoo", "language": "fr"}, {"user_id": 2440041209, "user_statuses": 36189, "name": "LeoniieRgr", "tweet": "j\u2019ai h\u00e2te de recevoir ma commande boohoo elle est p\u00e9pite\ud83e\udd72", "retweets": 0, "location": "Orl\u00e9ans", "created": "02-Apr-2021", "followers": 504, "is_user_verified": false, "favorite_count": 1, "in_reply_to_status_id": null, "keyword": "boohoo", "language": "fr"}, {"user_id": 961290820610650119, "user_statuses": 2441, "name": "bonx_gordon", "tweet": "@CORCAS_AUTONOMY Boohoo l'Alg\u00e9rie l'Alg\u00e9rie l'Alg\u00e9rie \ud83e\udd23", "retweets": 0, "location": "Providence, RI", "created": "02-Apr-2021", "followers": 32, "is_user_verified": false, "favorite_count": 0, "in_reply_to_status_id": 1377747401117724672, "keyword": "boohoo", "language": "fr"}, {"user_id": 948556491514089472, "user_statuses": 35251, "name": "Aymenbgr", "tweet": "@wezyar Mais nan wsh ??? Asos c\u2019est surc\u00f4t\u00e9 et  c\u2019est super cher, regarde les sites du style boohoo man, et aussi change de tel.", "retweets": 0, "location": "59 ", "created": "01-Apr-2021", "followers": 1457, "is_user_verified": false, "favorite_count": 0, "in_reply_to_status_id": 1377739434372763654, "keyword": "boohoo", "language": "fr"}, {"user_id": 1151412295, "user_statuses": 95532, "name": "weesterbass", "tweet": "Nasty gal c'est r\u00e9ellement choquant comment ils gonflent les prix pour faire croire \u00e0 des grosses promos, eux et boohoo vrmt c'est ouf", "retweets": 0, "location": "Grenoble // London", "created": "01-Apr-2021", "followers": 4842, "is_user_verified": false, "favorite_count": 0, "in_reply_to_status_id": null, "keyword": "boohoo", "language": "fr"}, {"user_id": 347069115, "user_statuses": 3011, "name": "RhodesLisa", "tweet": "@kadymcdermottx @boohoo April fool!", "retweets": 0, "location": "", "created": "01-Apr-2021", "followers": 101, "is_user_verified": false, "favorite_count": 0, "in_reply_to_status_id": 1377539715725996032, "keyword": "boohoo", "language": "fr"}, {"user_id": 1289722723841855489, "user_statuses": 3134, "name": "Shaanou_", "tweet": "Donc l\u00e0 vous allez me dire qu\u2019avec Boohoo vous avez jamais eu de probl\u00e8mes de taille ??? Si c\u2019est fait expr\u00e8s dites le moi directement hyn", "retweets": 0, "location": "", "created": "01-Apr-2021", "followers": 116, "is_user_verified": false, "favorite_count": 1, "in_reply_to_status_id": null, "keyword": "boohoo", "language": "fr"}, {"user_id": 4076879962, "user_statuses": 42406, "name": "chrsito_j", "tweet": "J\u2019peu Enfin recommander sur Boohoo \u00e0 moi la dripOmax \ud83e\udd73\ud83e\udd73\ud83e\udd73\ud83d\udd7a\ud83c\udffe\ud83d\udd7a\ud83c\udffe\ud83d\udd7a\ud83c\udffe", "retweets": 0, "location": "Brooklyn, NY", "created": "01-Apr-2021", "followers": 2360, "is_user_verified": false, "favorite_count": 0, "in_reply_to_status_id": null, "keyword": "boohoo", "language": "fr"}, {"user_id": 853750240721108993, "user_statuses": 17215, "name": "l_ss34", "tweet": "@asdetp Regarde sur boohoo les robes sont 10x mieux", "retweets": 0, "location": "", "created": "01-Apr-2021", "followers": 4666, "is_user_verified": false, "favorite_count": 0, "in_reply_to_status_id": 1377685563642368008, "keyword": "boohoo", "language": "fr"}, {"user_id": 966515760, "user_statuses": 63193, "name": "1mecgenial", "tweet": "Boohoo man la qualit\u00e9 c\u2019est du march\u00e9 dsl \u00e7a taille mal, les tissus sont mal coup\u00e9, tout fin bref \u00e7a d\u00e9gage", "retweets": 0, "location": "", "created": "01-Apr-2021", "followers": 2850, "is_user_verified": false, "favorite_count": 0, "in_reply_to_status_id": null, "keyword": "boohoo", "language": "fr"}, {"user_id": 636843301, "user_statuses": 37841, "name": "Gawou_", "tweet": "Les ensembles de boohoo me tante tellement \ud83d\ude0d", "retweets": 0, "location": "", "created": "01-Apr-2021", "followers": 513, "is_user_verified": false, "favorite_count": 0, "in_reply_to_status_id": null, "keyword": "boohoo", "language": "fr"}, {"user_id": 1252347286744641536, "user_statuses": 1538, "name": "75ereh_", "tweet": "@r_bucciarati ah bon? putain je savais pas je vois pleins de gens acheter dessus, apr\u00e8s boohoo j'viens de me commander des pantalons et ils sont archiiii fins donc \u00e0 voir niveau qualit\u00e9, apr\u00e8s c'est des cargo pas des jeans donc", "retweets": 0, "location": "", "created": "01-Apr-2021", "followers": 379, "is_user_verified": false, "favorite_count": 0, "in_reply_to_status_id": 1377655077272444937, "keyword": "boohoo", "language": "fr"}, {"user_id": 723979144619524096, "user_statuses": 4824, "name": "Noemie_Rdj", "tweet": "Semaine prochaine je re\u00e7ois mes commandes PLT, Boohoo et Shein vous savez ce que \u00e7a veut dire ? Hmm oui oui je pr\u00e9pare un bon glow up la", "retweets": 0, "location": "Ile-de-France, France", "created": "01-Apr-2021", "followers": 815, "is_user_verified": false, "favorite_count": 4, "in_reply_to_status_id": null, "keyword": "boohoo", "language": "fr"}, {"user_id": 1313808873447403520, "user_statuses": 3322, "name": "ertkkx", "tweet": "@r_bucciarati toi aussi tu commande sur BOOHOO", "retweets": 0, "location": "+ 5K on YouTube ", "created": "01-Apr-2021", "followers": 665, "is_user_verified": false, "favorite_count": 1, "in_reply_to_status_id": 1377652472261578759, "keyword": "boohoo", "language": "fr"}, {"user_id": 1132825631379607552, "user_statuses": 41997, "name": "cxratdoll", "tweet": "Bon mtn si je recommande chez boohoo je prendrai chez les petites hein le cirque c\u2019est fini", "retweets": 0, "location": "Le gros fiak de seungkwan ", "created": "01-Apr-2021", "followers": 525, "is_user_verified": false, "favorite_count": 0, "in_reply_to_status_id": null, "keyword": "boohoo", "language": "fr"}, {"user_id": 865313670569525248, "user_statuses": 33764, "name": "sharonwya0", "tweet": "La moiti\u00e9 des articles de mon panier boohoo sont en ruptures de stock , j\u2019ai la raaage", "retweets": 0, "location": "Heaven", "created": "01-Apr-2021", "followers": 69, "is_user_verified": false, "favorite_count": 1, "in_reply_to_status_id": null, "keyword": "boohoo", "language": "fr"}, {"user_id": 1033005917170745345, "user_statuses": 22402, "name": "JustAeeshaa", "tweet": "@MansaMousso @MadameDsn Mais Asos c\u2019est juste il refournit ce qu\u2019il y a dans les magasins type pull and bear bershka missguided boohoo et tout non ?", "retweets": 0, "location": "Paris, France", "created": "01-Apr-2021", "followers": 898, "is_user_verified": false, "favorite_count": 1, "in_reply_to_status_id": 1377636558606598151, "keyword": "boohoo", "language": "fr"}, {"user_id": 877845207462682626, "user_statuses": 49400, "name": "erimenide", "tweet": "Boohoo, Zara et consors qui font bosser des gens pour m\u00eame pas la moiti\u00e9 du smic en angleterre, H&amp;M, Romwe, Shein qui profitent de l'exploitation des Ouighours et d'autres travailleurs le tout en d\u00e9truisant l'environnement c'est super important de le rappeler.", "retweets": 2, "location": "", "created": "01-Apr-2021", "followers": 1018, "is_user_verified": false, "favorite_count": 5, "in_reply_to_status_id": 1377599905385037826, "keyword": "boohoo", "language": "fr"}, {"user_id": 3411278265, "user_statuses": 999, "name": "x_sophlouise_x", "tweet": "@kadymcdermottx @boohoo April fools\ud83d\ude05", "retweets": 0, "location": "Wrexham, Wales", "created": "01-Apr-2021", "followers": 74, "is_user_verified": false, "favorite_count": 5, "in_reply_to_status_id": 1377539715725996032, "keyword": "boohoo", "language": "fr"}, {"user_id": 1163496509767376898, "user_statuses": 38535, "name": "faster0stronger", "tweet": "les boys drip drip ils aiment trop les t shirt boohoo, les pantalons cargo et les jordan 4/1", "retweets": 5, "location": "", "created": "01-Apr-2021", "followers": 450, "is_user_verified": false, "favorite_count": 13, "in_reply_to_status_id": null, "keyword": "boohoo", "language": "fr"}, {"user_id": 1181480421630136320, "user_statuses": 8254, "name": "MbalaKarl", "tweet": "Une commande boohoo d\u2019\u00e9t\u00e9 s\u2019impose", "retweets": 1, "location": "Chez le Hokage", "created": "01-Apr-2021", "followers": 376, "is_user_verified": false, "favorite_count": 5, "in_reply_to_status_id": null, "keyword": "boohoo", "language": "fr"}, {"user_id": 1050826760185683971, "user_statuses": 96915, "name": "math_hildee", "tweet": "@Jeenk_ Niveau qualit\u00e9 je trouve \u00e7a sup\u00e9rieur \u00e0 plt boohoo et tt et pour la livraison \u00e7a avait moins d\u2019une semaine il me semble, j\u2019espere avoir r\u00e9pondu \u00e0 tes questions \ud83e\udd70", "retweets": 0, "location": "Cartagena, Colombia", "created": "01-Apr-2021", "followers": 1064, "is_user_verified": false, "favorite_count": 0, "in_reply_to_status_id": 1377549645879054340, "keyword": "boohoo", "language": "fr"}, {"user_id": 1356003158951161858, "user_statuses": 3654, "name": "noorieeeeeeeeee", "tweet": "boohoo craqu\u00e9r", "retweets": 0, "location": "she/they 17", "created": "01-Apr-2021", "followers": 355, "is_user_verified": false, "favorite_count": 1, "in_reply_to_status_id": null, "keyword": "boohoo", "language": "fr"}, {"user_id": 4897525276, "user_statuses": 95, "name": "faithmorris555", "tweet": "@boohoo Migraines \ud83d\ude44\ud83d\ude44", "retweets": 0, "location": "", "created": "01-Apr-2021", "followers": 5, "is_user_verified": false, "favorite_count": 1, "in_reply_to_status_id": 1377546106666680321, "keyword": "boohoo", "language": "fr"}, {"user_id": 512590188, "user_statuses": 147672, "name": "JennyJenn93", "tweet": "\u00ab\u00a0Haul PLT/Boohoo/Missguided/Fashion Nova\u00a0\u00bb \u00ab\u00a0Tuto pose perruque\u00a0\u00bb et moi \u00e7a y est j\u2019abandonne \ud83d\ude2d\nOn est vraiment coinc\u00e9 dans une boucle temporelle pour le YTB beaut\u00e9 FR ptn\nJ\u2019vais m\u2019contenter des vid\u00e9os de vulgarisations scientifiques et des let\u2019s play on dirait bien\ud83d\ude14", "retweets": 0, "location": "Laugh Tale (93)", "created": "01-Apr-2021", "followers": 1245, "is_user_verified": false, "favorite_count": 1, "in_reply_to_status_id": null, "keyword": "boohoo", "language": "fr"}, {"user_id": 1308305068928782337, "user_statuses": 18058, "name": "NezukoYai", "tweet": "Mdr et c\u2019est m\u00eames l\u00e0 ach\u00e8tent sur PrettyLittleThings, Shein et Boohoo. https://t.co/wAXk8T8Hax", "retweets": 3, "location": "", "created": "01-Apr-2021", "followers": 1150, "is_user_verified": false, "favorite_count": 9, "in_reply_to_status_id": null, "keyword": "boohoo", "language": "fr"}, {"user_id": 1365753482746208258, "user_statuses": 101, "name": "xpretty_stars", "tweet": "Trop h\u00e2te de recevoir ma commande de chez boohoo mais bon \u00e7a fait trois jours que le colis est bloqu\u00e9 \ud83d\ude10", "retweets": 0, "location": "Paris, France", "created": "01-Apr-2021", "followers": 17, "is_user_verified": false, "favorite_count": 0, "in_reply_to_status_id": null, "keyword": "boohoo", "language": "fr"}, {"user_id": 1438433444, "user_statuses": 89945, "name": "Ai_ssata", "tweet": "Pourtant y\u2019a grave des offres sur Plt et Boohoo mais je r\u00e9siste", "retweets": 0, "location": "", "created": "01-Apr-2021", "followers": 600, "is_user_verified": false, "favorite_count": 0, "in_reply_to_status_id": null, "keyword": "boohoo", "language": "fr"}, {"user_id": 1290806634541981698, "user_statuses": 1572, "name": "a2s_07", "tweet": "Hier j\u2019ai re\u00e7u ma commande Zara, aujourd\u2019hui ma commande Shein et inshAllah dans la semaine j\u2019esp\u00e8re ma commande Boohoo \u263a\ufe0f", "retweets": 0, "location": "Rouen, France", "created": "31-Mar-2021", "followers": 87, "is_user_verified": false, "favorite_count": 3, "in_reply_to_status_id": null, "keyword": "boohoo", "language": "fr"}, {"user_id": 2153182395, "user_statuses": 43165, "name": "degeneve28", "tweet": "boohoo &gt;&gt;&gt;&gt; plt faut le dire !", "retweets": 0, "location": "", "created": "31-Mar-2021", "followers": 525, "is_user_verified": false, "favorite_count": 0, "in_reply_to_status_id": null, "keyword": "boohoo", "language": "fr"}, {"user_id": 1264704581566595072, "user_statuses": 2166, "name": "Nivlac84", "tweet": "@Zakthedrowned Tout est valid\u00e9 sauf le pantalon pur\u00e9e on dirait les pubs boohoo sur insta", "retweets": 0, "location": "Regardez Bleach", "created": "31-Mar-2021", "followers": 60, "is_user_verified": false, "favorite_count": 0, "in_reply_to_status_id": 1377337054288179201, "keyword": "boohoo", "language": "fr"}, {"user_id": 4397866792, "user_statuses": 10718, "name": "LouveBpolar", "tweet": "Je vais faire un panier boohoo et plt", "retweets": 0, "location": "", "created": "31-Mar-2021", "followers": 173, "is_user_verified": false, "favorite_count": 0, "in_reply_to_status_id": null, "keyword": "boohoo", "language": "fr"}, {"user_id": 985863453704441862, "user_statuses": 2364, "name": "JulieTis25", "tweet": "@sendurconfes_ Sur boohoo j'en ai jamais eu", "retweets": 0, "location": "", "created": "31-Mar-2021", "followers": 32, "is_user_verified": false, "favorite_count": 0, "in_reply_to_status_id": 1376992935615549442, "keyword": "boohoo", "language": "fr"}, {"user_id": 1153718326457196544, "user_statuses": 127965, "name": "Crumpemag", "tweet": "Boohoo x City Girls Collab est l\u00e0 pour \u00e9gayer votre\u00a0garde-robe https://t.co/ijsDbE5JtL", "retweets": 0, "location": "", "created": "31-Mar-2021", "followers": 106, "is_user_verified": false, "favorite_count": 0, "in_reply_to_status_id": null, "keyword": "boohoo", "language": "fr"}, {"user_id": 3308013872, "user_statuses": 46927, "name": "melmbwn", "tweet": "j\u2019voulais faire la iencli de service et acheter un truc de la collection boohoo/city girls mais y\u2019a plus rien :/", "retweets": 0, "location": "", "created": "31-Mar-2021", "followers": 43, "is_user_verified": false, "favorite_count": 0, "in_reply_to_status_id": null, "keyword": "boohoo", "language": "fr"}, {"user_id": 726834324633456640, "user_statuses": 28485, "name": "ngnabii", "tweet": "Y a une robe la Boohoo x city girls ptn elle me va trop bien c\u2019est ill\u00e9gal, j\u2019ai fais un haul sur insta", "retweets": 1, "location": "Paris, France", "created": "31-Mar-2021", "followers": 15641, "is_user_verified": false, "favorite_count": 40, "in_reply_to_status_id": null, "keyword": "boohoo", "language": "fr"}, {"user_id": 3635922802, "user_statuses": 11695, "name": "iamchloeaube", "tweet": "C'est ce jour que j'ai compris que je ne pouvais plus m'allonger dans des hautes herbes https://t.co/7p51YHNgZl", "retweets": 0, "location": "", "created": "31-Mar-2021", "followers": 260, "is_user_verified": false, "favorite_count": 0, "in_reply_to_status_id": null, "keyword": "boohoo", "language": "fr"}, {"user_id": 1229417974160875520, "user_statuses": 3021, "name": "3Blzzz", "tweet": "J\u2019vais cambrioler boohoo qui m\u2019accompagne ?", "retweets": 0, "location": "Clover", "created": "31-Mar-2021", "followers": 277, "is_user_verified": false, "favorite_count": 3, "in_reply_to_status_id": null, "keyword": "boohoo", "language": "fr"}, {"user_id": 1467403382, "user_statuses": 61258, "name": "Aissatgls", "tweet": "Boohoo ils dorment l\u00e0... \ud83d\ude14", "retweets": 0, "location": "Evry, France", "created": "31-Mar-2021", "followers": 1966, "is_user_verified": false, "favorite_count": 0, "in_reply_to_status_id": null, "keyword": "boohoo", "language": "fr"}, {"user_id": 1158866390893441024, "user_statuses": 1049, "name": "antillaize93", "tweet": "Mon panier sur boohoo incroyable quand m\u00eame", "retweets": 0, "location": "", "created": "31-Mar-2021", "followers": 50, "is_user_verified": false, "favorite_count": 0, "in_reply_to_status_id": null, "keyword": "boohoo", "language": "fr"}, {"user_id": 1514505966, "user_statuses": 129097, "name": "aureloading", "tweet": "Boohoo j\u2019ai content de ma commande", "retweets": 0, "location": "Paris, France", "created": "31-Mar-2021", "followers": 543, "is_user_verified": false, "favorite_count": 0, "in_reply_to_status_id": null, "keyword": "boohoo", "language": "fr"}, {"user_id": 833647238362578945, "user_statuses": 9078, "name": "llasdivinass", "tweet": "MDR @boohoo j\u2019ai laiss\u00e9 un panier avec des articles non sold\u00e9s \u00e0 20\u20ac je vais pour payer aujourd\u2019hui tout \u00e0 augmenter de 5-10\u20ac mais laisser moi rire \ud83d\ude02", "retweets": 0, "location": "", "created": "31-Mar-2021", "followers": 261, "is_user_verified": false, "favorite_count": 0, "in_reply_to_status_id": null, "keyword": "boohoo", "language": "fr"}, {"user_id": 3047338733, "user_statuses": 14575, "name": "yooniebabyjulie", "tweet": "Boohoo il est trop beau mon amour \ud83d\udc9c\nMa vintie \u00e9tait trop mims https://t.co/T2jN6rLybp", "retweets": 0, "location": "she/her", "created": "31-Mar-2021", "followers": 1068, "is_user_verified": false, "favorite_count": 1, "in_reply_to_status_id": null, "keyword": "boohoo", "language": "fr"}, {"user_id": 1122127820019388417, "user_statuses": 20787, "name": "iiam_mad", "tweet": "Cte conne essaye de me faire croire qu\u2019un ensemble sur boohoo ce vend a 38\u20ac mais c\u2019est une zinzin https://t.co/BG81WMUefr", "retweets": 0, "location": "Lyon ", "created": "31-Mar-2021", "followers": 462, "is_user_verified": false, "favorite_count": 0, "in_reply_to_status_id": null, "keyword": "boohoo", "language": "fr"}, {"user_id": 1024254438, "user_statuses": 15785, "name": "SARAHCRROCHE", "tweet": "J\u2019ai un panier sur Boohoo, le jour o\u00f9 je vais le valider c\u2019est que j\u2019aurais gagn\u00e9 \u00e0 l\u2019euromillion", "retweets": 0, "location": "", "created": "31-Mar-2021", "followers": 476, "is_user_verified": false, "favorite_count": 0, "in_reply_to_status_id": null, "keyword": "boohoo", "language": "fr"}, {"user_id": 1216680972973944832, "user_statuses": 16097, "name": "danielladrookep", "tweet": "Boohoo au niveau des jeans sa taille petit ou normal ?", "retweets": 0, "location": "", "created": "31-Mar-2021", "followers": 277, "is_user_verified": false, "favorite_count": 1, "in_reply_to_status_id": null, "keyword": "boohoo", "language": "fr"}, {"user_id": 617348296, "user_statuses": 87892, "name": "Sokhnvg", "tweet": "Boohoo ils n\u2019ont qu\u2019\u00e0 faire vite avec mes colis l\u00e0 rhooo", "retweets": 0, "location": "Paris, France", "created": "31-Mar-2021", "followers": 4061, "is_user_verified": false, "favorite_count": 1, "in_reply_to_status_id": null, "keyword": "boohoo", "language": "fr"}, {"user_id": 782090506096508928, "user_statuses": 8200, "name": "dii_mbonga", "tweet": "La livraison de boohoo c\u2019est 16$ \ud83d\ude05", "retweets": 0, "location": "", "created": "31-Mar-2021", "followers": 396, "is_user_verified": false, "favorite_count": 0, "in_reply_to_status_id": null, "keyword": "boohoo", "language": "fr"}, {"user_id": 882542135110754304, "user_statuses": 25903, "name": "OnikandBreezy", "tweet": "@itsmamichula Yes mais c\u2019est que sur le boohoo us", "retweets": 0, "location": "Atlanta", "created": "31-Mar-2021", "followers": 399, "is_user_verified": false, "favorite_count": 1, "in_reply_to_status_id": 1377178026929090561, "keyword": "boohoo", "language": "fr"}, {"user_id": 1022488509108678657, "user_statuses": 4584, "name": "itsmamichula", "tweet": "@OnikandBreezy Juuuure je savais m\u00eame pas pourtant j\u2019\u00e9tais sur Boohoo ce matin.", "retweets": 0, "location": "Paris, La Defense ", "created": "31-Mar-2021", "followers": 135, "is_user_verified": false, "favorite_count": 0, "in_reply_to_status_id": 1377168645759987720, "keyword": "boohoo", "language": "fr"}, {"user_id": 1365381835816067076, "user_statuses": 1500, "name": "rssnins", "tweet": "@falafelxdurum il fait beau, prend rose, (si c\u2019est pour une soir\u00e9e ou quoi prnef noir) sachant que boohoo souvent leurs robes sont transparentes", "retweets": 0, "location": "BE", "created": "31-Mar-2021", "followers": 398, "is_user_verified": false, "favorite_count": 1, "in_reply_to_status_id": 1377168923204800517, "keyword": "boohoo", "language": "fr"}, {"user_id": 1179826718837760001, "user_statuses": 4665, "name": "mula_d9", "tweet": "La collection boohoo x city girls c\u2019est tout ce qu\u2019il me fallait pour cet \u00e9t\u00e9 \ud83e\udd24", "retweets": 0, "location": "", "created": "31-Mar-2021", "followers": 411, "is_user_verified": false, "favorite_count": 0, "in_reply_to_status_id": null, "keyword": "boohoo", "language": "fr"}, {"user_id": 3873920903, "user_statuses": 14803, "name": "Saamiziii", "tweet": "@KANTISOCIAL_ Belek c'est une marque de gros boohoo", "retweets": 3, "location": "", "created": "31-Mar-2021", "followers": 238, "is_user_verified": false, "favorite_count": 1, "in_reply_to_status_id": 1377041822913073160, "keyword": "boohoo", "language": "fr"}, {"user_id": 726834324633456640, "user_statuses": 28485, "name": "ngnabii", "tweet": "J\u2019ai command\u00e9 la collection boohoo x city girls j\u2019ai trop h\u00e2te wsh\ud83e\udd70\ud83e\udd70\ud83e\udd70\ud83e\udd70", "retweets": 0, "location": "Paris, France", "created": "31-Mar-2021", "followers": 15641, "is_user_verified": false, "favorite_count": 16, "in_reply_to_status_id": null, "keyword": "boohoo", "language": "fr"}, {"user_id": 586915917, "user_statuses": 21440, "name": "justDumo", "tweet": "Ridiculous @boohoo https://t.co/vQZze1Rxja", "retweets": 0, "location": "", "created": "31-Mar-2021", "followers": 2065, "is_user_verified": false, "favorite_count": 1, "in_reply_to_status_id": null, "keyword": "boohoo", "language": "fr"}, {"user_id": 3386724785, "user_statuses": 74211, "name": "Banguli_e", "tweet": "Mddr en s\u2019moment ya rien sur Boohoo les femmes c vraiment des ndumba", "retweets": 6, "location": "Nanterre, France", "created": "31-Mar-2021", "followers": 2225, "is_user_verified": false, "favorite_count": 8, "in_reply_to_status_id": null, "keyword": "boohoo", "language": "fr"}, {"user_id": 853782545137360898, "user_statuses": 104022, "name": "KANTISOCIAL_", "tweet": "Wsh la taille L en pantalon Boohoo c\u2019est grand de ouf nan?", "retweets": 0, "location": "", "created": "30-Mar-2021", "followers": 747, "is_user_verified": false, "favorite_count": 1, "in_reply_to_status_id": null, "keyword": "boohoo", "language": "fr"}, {"user_id": 354521833, "user_statuses": 45753, "name": "CookiiePiink", "tweet": "La collection Boohoo x City Girls est trop moche. Bon apr\u00e8s je sais pas \u00e0 quoi je m\u2019attendais aussi, \u00e7a ne m\u2019\u00e9tonne pas.", "retweets": 0, "location": "Paris, France", "created": "30-Mar-2021", "followers": 502, "is_user_verified": false, "favorite_count": 0, "in_reply_to_status_id": null, "keyword": "boohoo", "language": "fr"}, {"user_id": 1324682409007321088, "user_statuses": 5410, "name": "91200s", "tweet": "@ddejaavuu Je l\u2019ai achet\u00e9 sur Boohoo y\u2019a 2 ans donc pour retrouver le lien exact c\u2019est compliqu\u00e9, d\u00e9sol\u00e9 \ud83d\ude16", "retweets": 0, "location": "", "created": "30-Mar-2021", "followers": 400, "is_user_verified": false, "favorite_count": 0, "in_reply_to_status_id": 1377022915972104193, "keyword": "boohoo", "language": "fr"}, {"user_id": 561310163, "user_statuses": 67018, "name": "abelxnne", "tweet": "@_zodmg C\u2019est de la merde (comme boohoo, missguided et nastygal)\ud83e\udd17", "retweets": 0, "location": "Lyon, France", "created": "30-Mar-2021", "followers": 151, "is_user_verified": false, "favorite_count": 1, "in_reply_to_status_id": 1376982133714120712, "keyword": "boohoo", "language": "fr"}, {"user_id": 3525717803, "user_statuses": 195814, "name": "sendurconfess_2", "tweet": "\u00ab\u00a0Y a encore des frais de douane sur pretty little thing et boohoo ?\u00a0\u00bb", "retweets": 0, "location": "instagram.com/sendurconfess_2", "created": "30-Mar-2021", "followers": 26771, "is_user_verified": false, "favorite_count": 1, "in_reply_to_status_id": null, "keyword": "boohoo", "language": "fr"}, {"user_id": 1136001861725630465, "user_statuses": 3411, "name": "Marquesinha109", "tweet": "Hier j\u2019ai pass\u00e9 une commande boohoo j\u2019esp\u00e8re que les v\u00eatements vont m\u2019aller ils sont trop beaux \ud83d\ude29", "retweets": 0, "location": "Clermont-Ferrand, France", "created": "30-Mar-2021", "followers": 434, "is_user_verified": false, "favorite_count": 0, "in_reply_to_status_id": null, "keyword": "boohoo", "language": "fr"}, {"user_id": 1115102509, "user_statuses": 68538, "name": "ParentLindsay", "tweet": "Donc, boohoo vient de me pr\u00e9lever 30 balles alors que j\u2019ai rien command\u00e9 ? Ah", "retweets": 0, "location": "", "created": "30-Mar-2021", "followers": 687, "is_user_verified": false, "favorite_count": 2, "in_reply_to_status_id": null, "keyword": "boohoo", "language": "fr"}, {"user_id": 3547412789, "user_statuses": 324527, "name": "planetanddrea", "tweet": "la collab Boohoo x City Girls est trop mignonne pur\u00e9e j\u2019aime trop", "retweets": 1, "location": "80/92", "created": "30-Mar-2021", "followers": 731, "is_user_verified": false, "favorite_count": 2, "in_reply_to_status_id": null, "keyword": "boohoo", "language": "fr"}, {"user_id": 949385177230438401, "user_statuses": 21778, "name": "sendurconfes_", "tweet": "\u00ab\u00a0Y a encore des frais de douane sur pretty little thing et boohoo ?\u00a0\u00bb", "retweets": 0, "location": "nos activit\u00e9s dans nos j\u2019aime!", "created": "30-Mar-2021", "followers": 6789, "is_user_verified": false, "favorite_count": 0, "in_reply_to_status_id": null, "keyword": "boohoo", "language": "fr"}, {"user_id": 1181603761795588101, "user_statuses": 3993, "name": "rotmaa", "tweet": "@sleyfn Comme shein quoi... C juste que je voyais pas mal de gens avoir de bons truc qui disait que c'\u00e9tait boohoo dcp jdmmd", "retweets": 0, "location": "ex : XVI, FLC", "created": "30-Mar-2021", "followers": 750, "is_user_verified": false, "favorite_count": 0, "in_reply_to_status_id": 1376980953164304385, "keyword": "boohoo", "language": "fr"}, {"user_id": 1372582126785327110, "user_statuses": 171, "name": "AlexBr63547573", "tweet": "@_XCII__ @Houza_MB Va sur iGraal https://t.co/ViqZiEWDfY et cherche boohoo\nIl y a 8% de cashback sur tous les achats et plein de codes promos en plus (10% pour les \u00e9tudiants, 30% pour les offres de printemps, ...)\nEn plus, tu gagnes 3\u20ac en t'inscrivant", "retweets": 0, "location": "", "created": "30-Mar-2021", "followers": 0, "is_user_verified": false, "favorite_count": 1, "in_reply_to_status_id": 1376958203267842050, "keyword": "boohoo", "language": "fr"}, {"user_id": 186420778, "user_statuses": 74565, "name": "VittoreMorgane", "tweet": "@Princess_Clebs @Oli1973 C\u2019est la nouvelle collection Boohoo. Donc des v\u00eatements destin\u00e9s \u00e0 la vie de tous les jours. Voil\u00e0 voil\u00e0.", "retweets": 0, "location": "Lyon, Rh\u00f4ne-Alpes", "created": "30-Mar-2021", "followers": 6522, "is_user_verified": false, "favorite_count": 0, "in_reply_to_status_id": 1376965635972988934, "keyword": "boohoo", "language": "fr"}, {"user_id": 186420778, "user_statuses": 74565, "name": "VittoreMorgane", "tweet": "@Odreynalyne C\u2019est en vente sur Boohoo. Je comprends pas l\u2019id\u00e9e, l\u00e0.", "retweets": 0, "location": "Lyon, Rh\u00f4ne-Alpes", "created": "30-Mar-2021", "followers": 6522, "is_user_verified": false, "favorite_count": 1, "in_reply_to_status_id": 1376964433973551111, "keyword": "boohoo", "language": "fr"}, {"user_id": 847791079, "user_statuses": 49967, "name": "Houza_MB", "tweet": "Quelqu\u2019un aurait un code promo pour Boohoo please ?", "retweets": 0, "location": "De Westeros \u00e0 Essos \ud83c\uddf0\ud83c\uddf2", "created": "30-Mar-2021", "followers": 1092, "is_user_verified": false, "favorite_count": 0, "in_reply_to_status_id": null, "keyword": "boohoo", "language": "fr"}, {"user_id": 1345783493268271106, "user_statuses": 4700, "name": "rymo2l", "tweet": "@madneessy sur boohoo y\u2019a des trucs quand m\u00eame mais j\u2019ai pas tout regarder tfzcon la", "retweets": 0, "location": "", "created": "30-Mar-2021", "followers": 352, "is_user_verified": false, "favorite_count": 1, "in_reply_to_status_id": 1376954180116570116, "keyword": "boohoo", "language": "fr"}, {"user_id": 4647925049, "user_statuses": 3774, "name": "hadja__29", "tweet": "je vais pr\u00e9parer un panier Shein/ PLT/ Boohoo , y\u2019a trop de solaire", "retweets": 0, "location": "Paris, France", "created": "30-Mar-2021", "followers": 273, "is_user_verified": false, "favorite_count": 1, "in_reply_to_status_id": null, "keyword": "boohoo", "language": "fr"}, {"user_id": 194893343, "user_statuses": 18992, "name": "galiano_house", "tweet": "Mon ch\u00e9ri il m\u2019a fait une commande boohoo \ud83e\udd24\ud83d\ude0d", "retweets": 0, "location": "", "created": "30-Mar-2021", "followers": 392, "is_user_verified": false, "favorite_count": 0, "in_reply_to_status_id": null, "keyword": "boohoo", "language": "fr"}, {"user_id": 1320022015579914242, "user_statuses": 532, "name": "elenvy_", "tweet": "qlqn a d\u00e9j\u00e0 command\u00e9 sur boohoo ? c\u2019est de la bonne qualit\u00e9 ?", "retweets": 0, "location": "", "created": "30-Mar-2021", "followers": 105, "is_user_verified": false, "favorite_count": 0, "in_reply_to_status_id": null, "keyword": "boohoo", "language": "fr"}, {"user_id": 1160648813524242433, "user_statuses": 1149, "name": "melaloula", "tweet": "@lnrnds J\u2019ai command\u00e9 sur boohoo 2 fois, les 2x c\u2019\u00e9tait de la daube \ud83e\udd2e", "retweets": 0, "location": "", "created": "30-Mar-2021", "followers": 36, "is_user_verified": false, "favorite_count": 0, "in_reply_to_status_id": 1376904968289009668, "keyword": "boohoo", "language": "fr"}, {"user_id": 1069359858602921985, "user_statuses": 39525, "name": "ettedodooh", "tweet": "@boohoo faut nous expliquer l\u00e0, y\u2019a pas un petit souci ? https://t.co/3deZEzB7fX", "retweets": 0, "location": "Bruxelles, Belgique", "created": "30-Mar-2021", "followers": 301, "is_user_verified": false, "favorite_count": 0, "in_reply_to_status_id": null, "keyword": "boohoo", "language": "fr"}, {"user_id": 883817614623072256, "user_statuses": 14349, "name": "0702tdr", "tweet": "boohoo ils savent pas doser, TOUS LES JOURS 50 emails", "retweets": 0, "location": "", "created": "30-Mar-2021", "followers": 150, "is_user_verified": false, "favorite_count": 0, "in_reply_to_status_id": null, "keyword": "boohoo", "language": "fr"}, {"user_id": 1069359858602921985, "user_statuses": 39525, "name": "ettedodooh", "tweet": "Wait c\u2019est la collection boohoo ? https://t.co/hJ4xT6hd1h", "retweets": 0, "location": "Bruxelles, Belgique", "created": "30-Mar-2021", "followers": 301, "is_user_verified": false, "favorite_count": 0, "in_reply_to_status_id": null, "keyword": "boohoo", "language": "fr"}, {"user_id": 732981611071963136, "user_statuses": 2909, "name": "ShotoGuess", "tweet": "Quelqu\u2019un a un code promo boohoo?", "retweets": 0, "location": "", "created": "30-Mar-2021", "followers": 339, "is_user_verified": false, "favorite_count": 1, "in_reply_to_status_id": null, "keyword": "boohoo", "language": "fr"}, {"user_id": 1080927509812781057, "user_statuses": 9106, "name": "mxlle_dydy", "tweet": "Je suis entrain de regarder un documentaire sur PLT, Boohoo et consort mddrrr \nJe suis sur qu'il y a un scandal cach\u00e9 comme pour H&amp;M ou encore ZARA ..", "retweets": 0, "location": "Guadeloupe", "created": "30-Mar-2021", "followers": 289, "is_user_verified": false, "favorite_count": 0, "in_reply_to_status_id": null, "keyword": "boohoo", "language": "fr"}, {"user_id": 405168139, "user_statuses": 106222, "name": "Saraji_", "tweet": "Go faire une commande PLT, Bershka et Boohoo, je treat myself je m\u00e9rite \ud83e\udd70", "retweets": 0, "location": "Paris, France", "created": "30-Mar-2021", "followers": 428, "is_user_verified": false, "favorite_count": 0, "in_reply_to_status_id": null, "keyword": "boohoo", "language": "fr"}, {"user_id": 1368998114900795396, "user_statuses": 9, "name": "GabeauxP", "tweet": "@boohooFrance Moi ils mon envoy\u00e9 un colis au mauvais endroit donc retour chez boohoo c etait lec18 d\u00e9cembre et aucun remboursement j ai du envoyer 250 mails et tout cela pour 20 \u20ac site a fuir ils sont incomp\u00e9tents et malhonn\u00eates il faut commander chez shei", "retweets": 0, "location": "", "created": "30-Mar-2021", "followers": 0, "is_user_verified": false, "favorite_count": 0, "in_reply_to_status_id": 1335520355675467777, "keyword": "boohoo", "language": "fr"}, {"user_id": 761540642, "user_statuses": 19483, "name": "Carlossa_", "tweet": "Euh les maillots de bain boohoo en vrai ils sont tokoss hein", "retweets": 0, "location": "Paris, France", "created": "30-Mar-2021", "followers": 237, "is_user_verified": false, "favorite_count": 0, "in_reply_to_status_id": null, "keyword": "boohoo", "language": "fr"}, {"user_id": 865867886795128832, "user_statuses": 13379, "name": "HONMONOCOZY", "tweet": "Une forte envie d\u2019acheter la collection de city girl sur boohoo", "retweets": 1, "location": "khh + hh", "created": "30-Mar-2021", "followers": 100, "is_user_verified": false, "favorite_count": 1, "in_reply_to_status_id": null, "keyword": "boohoo", "language": "fr"}, {"user_id": 1002158289382146048, "user_statuses": 40875, "name": "issa_skn", "tweet": "@eliii_skyyy @yng__reezy Tqt mon vieux tu vas finir sur Boohoo MAN", "retweets": 0, "location": "", "created": "30-Mar-2021", "followers": 1306, "is_user_verified": false, "favorite_count": 2, "in_reply_to_status_id": 1376838789289627648, "keyword": "boohoo", "language": "fr"}, {"user_id": 1248528434743119872, "user_statuses": 29941, "name": "TooSexyTooSee", "tweet": "@gIointhedark @bokiinpain @BOOHOO_ABI BHAHDHS", "retweets": 0, "location": "", "created": "30-Mar-2021", "followers": 693, "is_user_verified": false, "favorite_count": 2, "in_reply_to_status_id": 1376827583111831553, "keyword": "boohoo", "language": "fr"}, {"user_id": 342664302, "user_statuses": 116130, "name": "ehadie", "tweet": "@InesNumba9 @boohoo ok cimerr", "retweets": 0, "location": "", "created": "30-Mar-2021", "followers": 1317, "is_user_verified": false, "favorite_count": 0, "in_reply_to_status_id": 1376798809838256128, "keyword": "boohoo", "language": "fr"}, {"user_id": 3238976962, "user_statuses": 231747, "name": "InesNumba9", "tweet": "@ehadie @boohoo Va sur EU", "retweets": 0, "location": "", "created": "30-Mar-2021", "followers": 8207, "is_user_verified": false, "favorite_count": 0, "in_reply_to_status_id": 1376798709053276162, "keyword": "boohoo", "language": "fr"}, {"user_id": 3238976962, "user_statuses": 231747, "name": "InesNumba9", "tweet": "D\u00c9J\u00c0 boohoo vous \u00eates racistes pourquoi c\u2019est tous les autres qui ont -50% sauf le boohoo fr", "retweets": 1, "location": "", "created": "30-Mar-2021", "followers": 8207, "is_user_verified": false, "favorite_count": 3, "in_reply_to_status_id": null, "keyword": "boohoo", "language": "fr"}, {"user_id": 3238976962, "user_statuses": 231747, "name": "InesNumba9", "tweet": "@ehadie @boohoo T\u2019es sur boohoo fr ou eu", "retweets": 0, "location": "", "created": "30-Mar-2021", "followers": 8207, "is_user_verified": false, "favorite_count": 0, "in_reply_to_status_id": 1376798440617828354, "keyword": "boohoo", "language": "fr"}, {"user_id": 342664302, "user_statuses": 116130, "name": "ehadie", "tweet": "wsh le seul pull beau est en rupture de stock j'vous d\u00e9teste @boohoo", "retweets": 0, "location": "", "created": "30-Mar-2021", "followers": 1317, "is_user_verified": false, "favorite_count": 1, "in_reply_to_status_id": 1376798157137448960, "keyword": "boohoo", "language": "fr"}, {"user_id": 2340801386, "user_statuses": 106937, "name": "YaSama__", "tweet": "Quelqu\u2019un peut m\u2019acheter un ensemble que je viens de voir sur boohoo svp il me le faut pour ma sant\u00e9 mentale", "retweets": 0, "location": "", "created": "29-Mar-2021", "followers": 2161, "is_user_verified": false, "favorite_count": 1, "in_reply_to_status_id": null, "keyword": "boohoo", "language": "fr"}, {"user_id": 1056495894676365312, "user_statuses": 4075, "name": "MSTHUGGAA", "tweet": "pureeeee l\u2019ensemble boohoo man rouge l\u00e0, l\u2019ensemble de LA MORT. Je peux plus \u00e7a me d\u00e9go\u00fbte", "retweets": 1, "location": "", "created": "29-Mar-2021", "followers": 46, "is_user_verified": false, "favorite_count": 3, "in_reply_to_status_id": null, "keyword": "boohoo", "language": "fr"}, {"user_id": 1026918596751048705, "user_statuses": 54612, "name": "__rinou10", "tweet": "boohoo \u00e7a taille comment ?", "retweets": 0, "location": "", "created": "29-Mar-2021", "followers": 3159, "is_user_verified": false, "favorite_count": 0, "in_reply_to_status_id": null, "keyword": "boohoo", "language": "fr"}, {"user_id": 601769956, "user_statuses": 229459, "name": "pearlynextdoor", "tweet": "Boohoo \u00e7a arrive en combien de temps ?", "retweets": 0, "location": "Gen\u00e8ve, Suisse", "created": "29-Mar-2021", "followers": 5222, "is_user_verified": false, "favorite_count": 0, "in_reply_to_status_id": null, "keyword": "boohoo", "language": "fr"}, {"user_id": 1342920318298566656, "user_statuses": 2713, "name": "shintarooo____", "tweet": "@acecxntent__ Pk sale chien \ud83d\ude2d je l\u2019ai achet\u00e9 chez Boohoo", "retweets": 0, "location": "Sereitei", "created": "29-Mar-2021", "followers": 206, "is_user_verified": false, "favorite_count": 0, "in_reply_to_status_id": 1376620111776342019, "keyword": "boohoo", "language": "fr"}, {"user_id": 357407126, "user_statuses": 49897, "name": "TSBK_", "tweet": "Vous avez un code boohoo ??", "retweets": 0, "location": "", "created": "29-Mar-2021", "followers": 1284, "is_user_verified": false, "favorite_count": 2, "in_reply_to_status_id": null, "keyword": "boohoo", "language": "fr"}, {"user_id": 723979144619524096, "user_statuses": 4824, "name": "Noemie_Rdj", "tweet": "Remplir des paniers Boohoo et PLT parce que je m\u2019ennuie...tr\u00e8s tr\u00e8s mauvaise id\u00e9e", "retweets": 0, "location": "Ile-de-France, France", "created": "29-Mar-2021", "followers": 815, "is_user_verified": false, "favorite_count": 5, "in_reply_to_status_id": null, "keyword": "boohoo", "language": "fr"}, {"user_id": 4140747137, "user_statuses": 48385, "name": "livanna_a", "tweet": "\u26a0\ufe0f S\u2019il vous plait essayez de faire de - en - d\u2019achats sur des sites de fast fashion (shein, yesstyle, boohoo, zara,...etc) et privil\u00e9giez la seconde main, je vous assure que vous pouvez trouver tout autant votre bonheur (parfois m\u00eame moins cher!!)\nIl y a les fripes \u00e9videmment-", "retweets": 9, "location": "one piece supremacy // \ud83c\udde9\ud83c\uddff", "created": "29-Mar-2021", "followers": 704, "is_user_verified": false, "favorite_count": 18, "in_reply_to_status_id": null, "keyword": "boohoo", "language": "fr"}, {"user_id": 1329124890574614528, "user_statuses": 1186, "name": "OladapoAzzi", "tweet": "@Thalie60960982 @Imani_kiaLukeni La famille la plus riche du Royaume-Uni est indienne\n\nEt les indiens gagnent bien plus que les blancs. Beaucoup de start up britanniques appartiennent \u00e0 des personnes d\u2019origine indiennes\n\nM\u00eame en France les meufs vous connaissez Boohoo,PrettylittleThing\n\nhttps://t.co/AXkceH9i8n", "retweets": 0, "location": "", "created": "29-Mar-2021", "followers": 221, "is_user_verified": false, "favorite_count": 0, "in_reply_to_status_id": 1376573945495875584, "keyword": "boohoo", "language": "fr"}, {"user_id": 19014576, "user_statuses": 3314, "name": "ashleyclaire81", "tweet": "@YourSweeeet666 @Mayhem15118416 @MjSunbury @boohoo LOUISE! \ud83e\udd2b", "retweets": 0, "location": "Memphis, TN", "created": "29-Mar-2021", "followers": 703, "is_user_verified": false, "favorite_count": 2, "in_reply_to_status_id": 1376571322441011200, "keyword": "boohoo", "language": "fr"}, {"user_id": 1174248096567582725, "user_statuses": 2154, "name": "ProudThemboStud", "tweet": "@TransLesbienne Dans la vie quand on dit des choses il faut des sources, une origine, une explication. Dire : boohoo j\u2019aime pas le terme pipou donc il est psychophobe alors qu\u2018il est utilis\u00e9 par des racis\u00e9\u2019e\u2019s tout aussi handi psys que celleux que tu pr\u00e9tends d\u00e9fendre c\u2019est inutile et dangereux", "retweets": 1, "location": "19 y/o (iel ou rien)", "created": "29-Mar-2021", "followers": 486, "is_user_verified": false, "favorite_count": 3, "in_reply_to_status_id": 1376561223723012102, "keyword": "boohoo", "language": "fr"}, {"user_id": 1272237871118901248, "user_statuses": 62391, "name": "slvlb952", "tweet": "J\u2019ai fais ma commande boohoo essh", "retweets": 0, "location": "\ud83e\uddca", "created": "29-Mar-2021", "followers": 3206, "is_user_verified": false, "favorite_count": 3, "in_reply_to_status_id": null, "keyword": "boohoo", "language": "fr"}, {"user_id": 1167931493487980544, "user_statuses": 17679, "name": "sssmkv_", "tweet": "@DalilaSmi plt livrent pas en belgique mais boohoo jsp", "retweets": 0, "location": "bx", "created": "29-Mar-2021", "followers": 171, "is_user_verified": false, "favorite_count": 0, "in_reply_to_status_id": 1376516007901204482, "keyword": "boohoo", "language": "fr"}, {"user_id": 503146764, "user_statuses": 39181, "name": "KayMilkshack", "tweet": "Les ensemble joggo pull sur boohoo ( qualit\u00e9 She in ) etc ils sont \u00e0 60-70\u20ac tu rajoute 20\u20ac t\u2019en a un de marque \ud83e\udd37\ud83c\udffd\u200d\u2640\ufe0f", "retweets": 0, "location": "France", "created": "29-Mar-2021", "followers": 892, "is_user_verified": false, "favorite_count": 0, "in_reply_to_status_id": null, "keyword": "boohoo", "language": "fr"}, {"user_id": 717126499, "user_statuses": 373619, "name": "Soohml_", "tweet": "Ce soir je vais faire une petite commande boohoo", "retweets": 0, "location": "MALVINA \u2764\ufe0f", "created": "29-Mar-2021", "followers": 1251, "is_user_verified": false, "favorite_count": 0, "in_reply_to_status_id": null, "keyword": "boohoo", "language": "fr"}, {"user_id": 1103268692, "user_statuses": 51049, "name": "Anissaayarii", "tweet": "Recevoir une robe Boohoo taille 40 dans ma commande NastyGall au lieu d\u2019une jupe mdr ils se foutent de la gueule du monde \ud83d\udc80\ud83d\udc80", "retweets": 0, "location": "Duba\u00ef, Emirats Arabes Unis", "created": "29-Mar-2021", "followers": 2191, "is_user_verified": false, "favorite_count": 0, "in_reply_to_status_id": null, "keyword": "boohoo", "language": "fr"}, {"user_id": 1179816239633444864, "user_statuses": 10861, "name": "MajestyYessiica", "tweet": "@lhudivine Sur boohoo tu peux trouver des p\u00e9pites", "retweets": 0, "location": "Par\u00e0deios", "created": "29-Mar-2021", "followers": 235, "is_user_verified": false, "favorite_count": 2, "in_reply_to_status_id": 1376508109389201408, "keyword": "boohoo", "language": "fr"}, {"user_id": 1147957338923503617, "user_statuses": 29062, "name": "DalilaSmi", "tweet": "plt et boohoo ils livrent en belgique ?", "retweets": 0, "location": "\ud83c\uddf9\ud83c\uddf3\ud83e\udd0c\ud83c\udffc\ud83c\udde7\ud83c\uddea       BXL ZOO", "created": "29-Mar-2021", "followers": 1958, "is_user_verified": false, "favorite_count": 2, "in_reply_to_status_id": null, "keyword": "boohoo", "language": "fr"}, {"user_id": 1034537819820179456, "user_statuses": 22006, "name": "lnay24", "tweet": "Asos zalando boohoo nike aussi mais bon la plupart des trucs n\u2019ont pas mes tailles \ud83e\uddcd\ud83c\udfff\u200d\u2642\ufe0f https://t.co/mkzB6aLn1j", "retweets": 0, "location": "93 \ud83c\udded\ud83c\uddf9", "created": "29-Mar-2021", "followers": 893, "is_user_verified": false, "favorite_count": 3, "in_reply_to_status_id": null, "keyword": "boohoo", "language": "fr"}, {"user_id": 1148656948033859585, "user_statuses": 175, "name": "2zang1", "tweet": "SHEIN et BOOHOO ils sont trop bouillant en s\u2019moment, aucune piti\u00e9 pour nos CB", "retweets": 1, "location": "", "created": "29-Mar-2021", "followers": 80, "is_user_verified": false, "favorite_count": 7, "in_reply_to_status_id": null, "keyword": "boohoo", "language": "fr"}, {"user_id": 3380956709, "user_statuses": 2852, "name": "kwaleadmedia", "tweet": "-30% sur les collections de printemps ! Gr\u00e2ce aux codes promos @boohoo , obtenez 30% de remise sur vos achats. C'est le moment d'en profiter et de partager un max #Boohoo #promo @kwalead #TousKwaleaders @kwalead https://t.co/eJviPmFrEA", "retweets": 0, "location": "Cr\u00e9teil, France", "created": "29-Mar-2021", "followers": 3137, "is_user_verified": false, "favorite_count": 0, "in_reply_to_status_id": null, "keyword": "boohoo", "language": "fr"}]