[{"user_id": 2507848470, "user_statuses": 91557, "name": "pieceofyou", "tweet": "La pubblicit\u00e0 di Zalando \u00e8 una meraviglia \u2764\ufe0f", "retweets": 0, "location": "", "created": "31-Mar-2021", "followers": 1111, "is_user_verified": false, "favorite_count": 0, "in_reply_to_status_id": null, "keyword": "zalando", "language": "it"}, {"user_id": 2889293674, "user_statuses": 35879, "name": "nearmymind", "tweet": "Ma la bellezza della pubblicit\u00e0 di Zalando?", "retweets": 1, "location": "Torino capitale ", "created": "31-Mar-2021", "followers": 1195, "is_user_verified": false, "favorite_count": 1, "in_reply_to_status_id": null, "keyword": "zalando", "language": "it"}, {"user_id": 1103912832, "user_statuses": 34446, "name": "shelbyscompany", "tweet": "La pubblicit\u00e0 di Zalando \u00e8 stupenda #uominiedonne https://t.co/rArtnNwo6x", "retweets": 0, "location": "Milano", "created": "31-Mar-2021", "followers": 476, "is_user_verified": false, "favorite_count": 1, "in_reply_to_status_id": null, "keyword": "zalando", "language": "it"}, {"user_id": 557546582, "user_statuses": 1332, "name": "IreConsigliere", "tweet": "Laureate \u00abStem\u00bb: ecco le aziende tech che puntano sulle donne https://t.co/PsiuAwZGuX @AmazonIT @nexipayments @Facebook @microsoftitalia @NTTDATA_IT @SoprasteriaIT @Zalando @Corriere @L_Economia", "retweets": 0, "location": "", "created": "31-Mar-2021", "followers": 517, "is_user_verified": false, "favorite_count": 0, "in_reply_to_status_id": null, "keyword": "zalando", "language": "it"}, {"user_id": 3306881447, "user_statuses": 1089, "name": "EcomobileNews", "tweet": "#Zalando si fa sempre pi\u00f9 verde\n\nhttps://t.co/4545B00GbF https://t.co/07gjy8AZpP", "retweets": 0, "location": "Bologna, Emilia Romagna", "created": "31-Mar-2021", "followers": 143, "is_user_verified": false, "favorite_count": 0, "in_reply_to_status_id": null, "keyword": "zalando", "language": "it"}, {"user_id": 1369930626841915393, "user_statuses": 75, "name": "TetteColte", "tweet": "Carica.\nCarica sui glutei, dai, di pi\u00f9.\nDai con quei retaggi di vie della moda powered by Zalando. Pi\u00f9 forte.\nMettici del trucco, del filtro, tutorial dell'inganno moderno. Fai la faccia faticosamente compiaciuta e rimani ferma qualche ora di esposizione.\n0%.............|....100% https://t.co/cIOdCzX68L", "retweets": 0, "location": "", "created": "31-Mar-2021", "followers": 250, "is_user_verified": false, "favorite_count": 1, "in_reply_to_status_id": null, "keyword": "zalando", "language": "it"}, {"user_id": 2784142880, "user_statuses": 59775, "name": "calliopefleury", "tweet": "Voglio il mio ordine zalando \ud83d\ude20", "retweets": 0, "location": "\uff91\uff9a \u2661\ufe0e", "created": "31-Mar-2021", "followers": 4072, "is_user_verified": false, "favorite_count": 1, "in_reply_to_status_id": null, "keyword": "zalando", "language": "it"}, {"user_id": 96716561, "user_statuses": 48900, "name": "broby68", "tweet": "Le tecnologie AEG alleate dello stile Zalando https://t.co/tC9ySZjSiR", "retweets": 0, "location": "Milano", "created": "31-Mar-2021", "followers": 795, "is_user_verified": false, "favorite_count": 0, "in_reply_to_status_id": null, "keyword": "zalando", "language": "it"}, {"user_id": 520689268, "user_statuses": 30422, "name": "Millyzampa87", "tweet": "@zorziloml prova anche zalando se ce l'hai", "retweets": 0, "location": "", "created": "31-Mar-2021", "followers": 508, "is_user_verified": false, "favorite_count": 0, "in_reply_to_status_id": 1377204769928970242, "keyword": "zalando", "language": "it"}, {"user_id": 826688961452056576, "user_statuses": 6842, "name": "VillaggioTecno", "tweet": "Le tecnologie AEG alleate dello stile Zalando https://t.co/JErCbGtw0k https://t.co/eePrJXQ9jf", "retweets": 0, "location": "Milano, Lombardia", "created": "31-Mar-2021", "followers": 82, "is_user_verified": false, "favorite_count": 0, "in_reply_to_status_id": null, "keyword": "zalando", "language": "it"}, {"user_id": 1347937538665799682, "user_statuses": 521, "name": "matteozioso", "tweet": "ora vado alle poste in bici, illudendomi di compensare cos\u00ec le emissioni di CO2 che il reso di Zalando comporter\u00e0", "retweets": 0, "location": "on a bench in Coney Island", "created": "31-Mar-2021", "followers": 50, "is_user_verified": false, "favorite_count": 1, "in_reply_to_status_id": null, "keyword": "zalando", "language": "it"}, {"user_id": 624067671, "user_statuses": 191939, "name": "Y00NMINGUK", "tweet": "non zalando che abbassa il prezzo DOPO che io le ho comprate .. \ud83d\ude00 https://t.co/vReNBvFMYg", "retweets": 0, "location": "", "created": "31-Mar-2021", "followers": 13007, "is_user_verified": false, "favorite_count": 1, "in_reply_to_status_id": 1376998799089020930, "keyword": "zalando", "language": "it"}, {"user_id": 2198037502, "user_statuses": 26003, "name": "dobbyeelfo", "tweet": "Zalando non mi aveva mai deluso. Quando decide di farlo? Quando faccio un regalo. Scusa paolino era per te.", "retweets": 0, "location": "", "created": "31-Mar-2021", "followers": 651, "is_user_verified": false, "favorite_count": 4, "in_reply_to_status_id": null, "keyword": "zalando", "language": "it"}, {"user_id": 457767455, "user_statuses": 43962, "name": "masoproteggerti", "tweet": "aprite i negozi che mi scoccio di ordinare su Zalando e sbagliare le taglie", "retweets": 1, "location": "", "created": "31-Mar-2021", "followers": 810, "is_user_verified": false, "favorite_count": 1, "in_reply_to_status_id": null, "keyword": "zalando", "language": "it"}, {"user_id": 2198481850, "user_statuses": 68887, "name": "MinolloO", "tweet": "Ormai il corriere Zalando ha pigliat a residenza a casa mij!", "retweets": 1, "location": "", "created": "31-Mar-2021", "followers": 15273, "is_user_verified": false, "favorite_count": 102, "in_reply_to_status_id": null, "keyword": "zalando", "language": "it"}, {"user_id": 388891207, "user_statuses": 116322, "name": "ammaiFiamma", "tweet": "Anteprima #giraYoox che trovate tutto dettagliato nelle STORIES IG del giorno, dedicato alle Autumn e composto su @Zalando \nEsaminiamo i trench di stagione!\nhttps://t.co/9ofpFNe06Z https://t.co/qUoa36eBjL", "retweets": 0, "location": "Direttrice", "created": "31-Mar-2021", "followers": 1592, "is_user_verified": false, "favorite_count": 2, "in_reply_to_status_id": null, "keyword": "zalando", "language": "it"}, {"user_id": 751701549605351424, "user_statuses": 5614, "name": "lasFigaregna", "tweet": "Zalando \u00e8 un covo di roba Basic.", "retweets": 0, "location": "", "created": "31-Mar-2021", "followers": 696, "is_user_verified": false, "favorite_count": 1, "in_reply_to_status_id": null, "keyword": "zalando", "language": "it"}, {"user_id": 584273, "user_statuses": 49493, "name": "pgei", "tweet": "Gli acquisti #online sono sempre pi\u00f9 #sostenibili per il settore #Fashion https://t.co/4ZTSLjRkBr @NETAPORTER @yoox @Zalando @bonprixIT @ASOS_TiAiuta @Green__Planner", "retweets": 0, "location": "Milan, Italy", "created": "31-Mar-2021", "followers": 1267, "is_user_verified": false, "favorite_count": 0, "in_reply_to_status_id": null, "keyword": "zalando", "language": "it"}, {"user_id": 993522769412411393, "user_statuses": 268, "name": "SilviaGaiaG", "tweet": "@teozenoni Uff... l'ultima volta con zalando dopo due cambi ho desistito... speriamo di tornare presto arancioni (e che nel mentre non mi si rompano le scarpe!) Grazie!", "retweets": 0, "location": "", "created": "31-Mar-2021", "followers": 307, "is_user_verified": false, "favorite_count": 0, "in_reply_to_status_id": 1377163886818811904, "keyword": "zalando", "language": "it"}, {"user_id": 109303208, "user_statuses": 64935, "name": "lebbrosario", "tweet": "Eppure ci sono, i siti delle Universit\u00e0, delle comunit\u00e0 scientifiche, delle case farmaceutiche, c'\u00e8 il sito Nike, Apple, Samsung, Star Wars, e invece emerge e galleggia la solita merda di Wish, Amazon, Zalando, Wikihow, Iltuofarmacistapuntoit, filosofiainrete, repubblica, ansa.", "retweets": 1, "location": "Loculi, Sardegna", "created": "31-Mar-2021", "followers": 1477, "is_user_verified": false, "favorite_count": 6, "in_reply_to_status_id": 1377143554535870468, "keyword": "zalando", "language": "it"}, {"user_id": 1293137776230174721, "user_statuses": 377, "name": "antartjde", "tweet": "@Y0URESOGVLDEN io ne ho trovate alcune su zalando, altri non saprei", "retweets": 0, "location": "i'm going back to 505", "created": "30-Mar-2021", "followers": 29, "is_user_verified": false, "favorite_count": 0, "in_reply_to_status_id": 1377040497831776259, "keyword": "zalando", "language": "it"}, {"user_id": 1235060508761477120, "user_statuses": 40931, "name": "TiQiMotrat", "tweet": "@deezeay @Zalando_Press unnormal stabiler pensi bro", "retweets": 0, "location": "Kosovo", "created": "30-Mar-2021", "followers": 1814, "is_user_verified": false, "favorite_count": 3, "in_reply_to_status_id": 1377027320419074049, "keyword": "zalando", "language": "it"}, {"user_id": 624067671, "user_statuses": 191939, "name": "Y00NMINGUK", "tweet": "sis \u00e8 incazzata con me perch\u00e8 continuo a spendere soldi quando lei ha speso 200\u20ac su zalando nell\u2019ultima settimana e ogni camicetta che si compra costa minimo 40\u20ac \ud83e\udd3e\ud83c\udffb\u200d\u2642\ufe0f il bue che d\u00e0 del cornuto all\u2019asino io penso", "retweets": 0, "location": "", "created": "30-Mar-2021", "followers": 13007, "is_user_verified": false, "favorite_count": 0, "in_reply_to_status_id": null, "keyword": "zalando", "language": "it"}, {"user_id": 1244603340, "user_statuses": 86286, "name": "francezca_", "tweet": "Che fare se non mi arriva il pacco Zalando perch\u00e9 il corriere \u00e9 incompetente?", "retweets": 0, "location": "Alicante, Idris", "created": "30-Mar-2021", "followers": 1487, "is_user_verified": false, "favorite_count": 0, "in_reply_to_status_id": null, "keyword": "zalando", "language": "it"}, {"user_id": 1352802553, "user_statuses": 332, "name": "avvocristiano", "tweet": "@Zalando ma oltre a trattenere i soldi, non consegnare le spedizioni e rispondere che non potete fare niente, il vostro servizio di assistenza ai clienti \u00e8 pagato per fare qualcosa di simile all'assistenza clienti o sono l\u00ec solo per prendere in giro i malcapitati clienti?", "retweets": 0, "location": "Brescia, Lombardia", "created": "30-Mar-2021", "followers": 48, "is_user_verified": false, "favorite_count": 0, "in_reply_to_status_id": null, "keyword": "zalando", "language": "it"}, {"user_id": 906090109220610048, "user_statuses": 3605, "name": "sadivics", "tweet": "mi dovrebbero arrivare delle scarpe da zalando help sono bellissime can't wait", "retweets": 0, "location": "bangtantown | she/they~bi", "created": "30-Mar-2021", "followers": 98, "is_user_verified": false, "favorite_count": 0, "in_reply_to_status_id": null, "keyword": "zalando", "language": "it"}, {"user_id": 958599945417908224, "user_statuses": 74603, "name": "usato_di_sicuro", "tweet": "@GAngrilli Zalando si impara?\nNo, quella era l'altra ...\n\ud83d\ude09\ud83e\udd23\ud83e\udd42", "retweets": 0, "location": "Torino, Piemonte", "created": "30-Mar-2021", "followers": 1552, "is_user_verified": false, "favorite_count": 1, "in_reply_to_status_id": 1376969109448056833, "keyword": "zalando", "language": "it"}, {"user_id": 390032884, "user_statuses": 83967, "name": "GAngrilli", "tweet": "Avete visto la pubblicit\u00e0 di Zalando??? \n\ud83d\ude04\ud83d\ude04\ud83d\ude04\ud83d\ude04\ud83d\ude04\ud83d\ude04\ud83d\ude04\ud83d\ude04\n#Zalando #globalgovernance #politicallycorrect", "retweets": 0, "location": "Roma, Lazio", "created": "30-Mar-2021", "followers": 4275, "is_user_verified": false, "favorite_count": 1, "in_reply_to_status_id": null, "keyword": "zalando", "language": "it"}, {"user_id": 603836700, "user_statuses": 167542, "name": "cucchiaia", "tweet": "@xchocolatemilk Non saprei, da zalando non compro mai \ud83d\ude02", "retweets": 0, "location": "Cagliari, Italy ", "created": "30-Mar-2021", "followers": 23376, "is_user_verified": false, "favorite_count": 1, "in_reply_to_status_id": 1376951041216933890, "keyword": "zalando", "language": "it"}, {"user_id": 24319564, "user_statuses": 72157, "name": "IeSslo", "tweet": "@tortellina3 Ho giusto comprato tre paia di scarpe da Zalando... sneakers stringate! \ud83d\ude31", "retweets": 0, "location": "Mira, Venezia", "created": "30-Mar-2021", "followers": 2316, "is_user_verified": false, "favorite_count": 1, "in_reply_to_status_id": 1376945328746811400, "keyword": "zalando", "language": "it"}, {"user_id": 1315223066553782274, "user_statuses": 594, "name": "Trebbiii", "tweet": "@caffeine_ext @GhiglioneNicolo scopiamo per bene solebox zalando snieps e luisaviaroma \u2615\ufe0f\u2615\ufe0f", "retweets": 0, "location": "Roma, Lazio", "created": "30-Mar-2021", "followers": 9, "is_user_verified": false, "favorite_count": 0, "in_reply_to_status_id": 1376954565514387461, "keyword": "zalando", "language": "it"}, {"user_id": 3224904659, "user_statuses": 91184, "name": "xchocolatemilk", "tweet": "CHE PURE ZALANDO NON SCHERZA\nL'altro giorno \u00e8 venuto uno bonissimo e io sono scesa con il pigiama con il gattino sopra \ud83d\ude2d\ud83d\ude2d\ud83d\ude2d\ud83d\ude2d\ud83d\ude2d e i capelli di merda https://t.co/LX2tbNWCwd", "retweets": 0, "location": "Wattpad & bed ", "created": "30-Mar-2021", "followers": 1780, "is_user_verified": false, "favorite_count": 4, "in_reply_to_status_id": null, "keyword": "zalando", "language": "it"}, {"user_id": 498766319, "user_statuses": 39132, "name": "GretaSmara", "tweet": "Ho un amore smisurato per Zalando e le sue consegne veloci", "retweets": 0, "location": "bimba di Gianni Morandi ", "created": "30-Mar-2021", "followers": 839, "is_user_verified": false, "favorite_count": 1, "in_reply_to_status_id": null, "keyword": "zalando", "language": "it"}, {"user_id": 3247859001, "user_statuses": 24824, "name": "weirdovery", "tweet": "@martina_procopi Signora Pesca, si ricordi che la felicit\u00e0 che lo shopping da \u00e9 solo effimera ed \u00e9 frutto di un capitalismo eccessivo. Detto questo, me ne torno su Zalando", "retweets": 0, "location": "", "created": "30-Mar-2021", "followers": 906, "is_user_verified": false, "favorite_count": 3, "in_reply_to_status_id": 1376916427568001024, "keyword": "zalando", "language": "it"}, {"user_id": 879084319142285312, "user_statuses": 24104, "name": "larniam__", "tweet": "Io che ho l\u2019app della Prenatal ma non quella di Zalando sul cellulare.. dice molto", "retweets": 0, "location": "", "created": "30-Mar-2021", "followers": 305, "is_user_verified": false, "favorite_count": 0, "in_reply_to_status_id": null, "keyword": "zalando", "language": "it"}, {"user_id": 491429714, "user_statuses": 70302, "name": "gagasmysun", "tweet": "Entro su asos, h&amp;m, Zalando, con tutta la voglia di fare shopping che ha una che ha appena preso lo stipendio ma non mi piace nienteeeeeeee\ud83d\udc41\ud83d\udc44\ud83d\udc41", "retweets": 0, "location": "Rome", "created": "30-Mar-2021", "followers": 969, "is_user_verified": false, "favorite_count": 1, "in_reply_to_status_id": null, "keyword": "zalando", "language": "it"}, {"user_id": 899978374059352065, "user_statuses": 20524, "name": "Nuccia_88", "tweet": "@mariagraziafusa Oppure c \u00e8 Zalando ... \ud83d\ude02\ud83d\ude02", "retweets": 0, "location": "Motta San Giovanni, Calabria", "created": "30-Mar-2021", "followers": 507, "is_user_verified": false, "favorite_count": 1, "in_reply_to_status_id": 1376888258609750019, "keyword": "zalando", "language": "it"}, {"user_id": 2813989203, "user_statuses": 33607, "name": "valleinmogano", "tweet": "nel nuovo spot di Zalando si vede un photoshooting di una modella curvy e dopo una ragazza che vedendo le fotografie scattate si sente pi\u00f9 confident\u2026\nvorrei anch'io essere un po' pi\u00f9 sicura di me \ud83d\ude44", "retweets": 0, "location": "", "created": "30-Mar-2021", "followers": 3114, "is_user_verified": false, "favorite_count": 1, "in_reply_to_status_id": null, "keyword": "zalando", "language": "it"}, {"user_id": 4717519173, "user_statuses": 9818, "name": "blurryaure", "tweet": "mi \u00e8 arrivato il pacco da zalando ma ora voglio comprare altro", "retweets": 0, "location": "", "created": "30-Mar-2021", "followers": 1152, "is_user_verified": false, "favorite_count": 1, "in_reply_to_status_id": null, "keyword": "zalando", "language": "it"}, {"user_id": 609371625, "user_statuses": 2469, "name": "marcored24", "tweet": "@marysorriso79 Mia figlia le ha prese su Zalando", "retweets": 0, "location": "GROSSETO,TOSCANA,ITALIA", "created": "30-Mar-2021", "followers": 134, "is_user_verified": false, "favorite_count": 1, "in_reply_to_status_id": 1376856643607142401, "keyword": "zalando", "language": "it"}, {"user_id": 26463965, "user_statuses": 50679, "name": "NiColaCaRd", "tweet": "@marysorriso79 Su Zalando ne trovi un bel po'", "retweets": 0, "location": "Pavia, Lecce, Italy", "created": "30-Mar-2021", "followers": 1661, "is_user_verified": false, "favorite_count": 1, "in_reply_to_status_id": 1376844051815800833, "keyword": "zalando", "language": "it"}, {"user_id": 1208448120985735169, "user_statuses": 119, "name": "offwhite1488", "tweet": "@Zalando buongiorno ho un problema con il mio account risulta bloccato , attendo assistenza grazie", "retweets": 0, "location": "Italia", "created": "30-Mar-2021", "followers": 2, "is_user_verified": false, "favorite_count": 0, "in_reply_to_status_id": null, "keyword": "zalando", "language": "it"}, {"user_id": 1324044784995127297, "user_statuses": 2199, "name": "Ansiaaaaaaaaa", "tweet": "Ogni tanto la mia lista dei desideri si svuota ma non perch\u00e9 compro cose, ma perch\u00e9 non sono pi\u00f9 disponibili e le cancello \ud83e\udd72\n\n #zalando #30marzo \n@ansia_totale @trash_italiano", "retweets": 0, "location": "\u2468\u00be", "created": "30-Mar-2021", "followers": 310, "is_user_verified": false, "favorite_count": 1, "in_reply_to_status_id": null, "keyword": "zalando", "language": "it"}, {"user_id": 230470477, "user_statuses": 74253, "name": "acciofocaccia", "tweet": "@airadneggel Se non vuoi andare in negozio su Zalando le puoi tranquillamente provare prima e pagare dopo, se non ti piacciono le rispedisci indietro e basta non devi pagare niente", "retweets": 0, "location": "she/her", "created": "30-Mar-2021", "followers": 8385, "is_user_verified": false, "favorite_count": 2, "in_reply_to_status_id": 1376709615421947910, "keyword": "zalando", "language": "it"}, {"user_id": 854351186388013057, "user_statuses": 6475, "name": "unlighters", "tweet": "@airadneggel Io le dr classiche le ho prese tre anni fa su Amazon e mi sono arrivate originali e nuove, per\u00f2 anche su zalando mamma aveva preso delle Adidas e ci si \u00e8 trovata bene", "retweets": 0, "location": "Roma", "created": "30-Mar-2021", "followers": 180, "is_user_verified": false, "favorite_count": 0, "in_reply_to_status_id": 1376709615421947910, "keyword": "zalando", "language": "it"}, {"user_id": 1372218998, "user_statuses": 44531, "name": "aujourdtaek", "tweet": "@airadneggel scusa ti avevo risposto ma avevo letto male ahah comunque considera che su zalando hai pi\u00f9 tempo per il reso ed \u00e8 pi\u00f9 sicuro, se costano molto le prenderei su zalando per avere una garanzia in pi\u00f9, altrimenti mi accontenterei anche di amazon", "retweets": 0, "location": "", "created": "30-Mar-2021", "followers": 5161, "is_user_verified": false, "favorite_count": 0, "in_reply_to_status_id": 1376713502291865607, "keyword": "zalando", "language": "it"}, {"user_id": 335249305, "user_statuses": 90242, "name": "Happy4Trigger", "tweet": "@fremebonda Eh ma Zalando copre te.", "retweets": 0, "location": "Leiden, The Netherlands", "created": "30-Mar-2021", "followers": 2522, "is_user_verified": false, "favorite_count": 1, "in_reply_to_status_id": 1376810445445685249, "keyword": "zalando", "language": "it"}, {"user_id": 43083883, "user_statuses": 310684, "name": "fremebonda", "tweet": "@Happy4Trigger Mai coperto zalando in vita mia", "retweets": 0, "location": "Siena, Toscana", "created": "30-Mar-2021", "followers": 5988, "is_user_verified": false, "favorite_count": 0, "in_reply_to_status_id": 1376809827645673473, "keyword": "zalando", "language": "it"}, {"user_id": 43083883, "user_statuses": 310684, "name": "fremebonda", "tweet": "Quanto hanno rotto il cazzo da uno a un miliardo Zalando&amp;Amazon su YouTube?", "retweets": 0, "location": "Siena, Toscana", "created": "30-Mar-2021", "followers": 5988, "is_user_verified": false, "favorite_count": 7, "in_reply_to_status_id": null, "keyword": "zalando", "language": "it"}, {"user_id": 961210597357555713, "user_statuses": 4418, "name": "fraerys", "tweet": "Appena comprato dei vestitini estivi su Zalando \ud83d\udc40\ud83d\udc40\ud83d\udc40", "retweets": 0, "location": "\u2609\u2650\u2191\u264c\u263d\u2649", "created": "30-Mar-2021", "followers": 1137, "is_user_verified": false, "favorite_count": 0, "in_reply_to_status_id": null, "keyword": "zalando", "language": "it"}, {"user_id": 614490385, "user_statuses": 53928, "name": "FraVonV", "tweet": "Sto usando dei prodotti di Revolution presi su Zalando beauty per curiosit\u00e0 devo dire minima spesa fanno il loro lavoro.", "retweets": 0, "location": "Lugano ", "created": "30-Mar-2021", "followers": 7515, "is_user_verified": false, "favorite_count": 9, "in_reply_to_status_id": null, "keyword": "zalando", "language": "it"}, {"user_id": 1148473101782568960, "user_statuses": 2685, "name": "baffomaragas", "tweet": "Voto DIECIMILA alla pubblicit\u00e0 super inclusiva di #Zalando . Bravi \ud83d\udc93", "retweets": 0, "location": "Milano, Lombardia", "created": "29-Mar-2021", "followers": 890, "is_user_verified": false, "favorite_count": 1, "in_reply_to_status_id": null, "keyword": "zalando", "language": "it"}, {"user_id": 110694338, "user_statuses": 24593, "name": "gabriele_901", "tweet": "Tra assicurazione auto, Amazon e Zalando vado a dormire altrimenti mi sveglio sotto un ponte. Notte \ud83d\udca4", "retweets": 0, "location": "Jesolo ", "created": "29-Mar-2021", "followers": 939, "is_user_verified": false, "favorite_count": 3, "in_reply_to_status_id": null, "keyword": "zalando", "language": "it"}, {"user_id": 1153640719460065281, "user_statuses": 31983, "name": "wataruswaifu", "tweet": "vibing sulla canzone della pubblicit\u00e0 di zalando su youtube\n\nTURUTTUTURUTURURTUTURUTU", "retweets": 0, "location": "ceo of spinacini srl", "created": "29-Mar-2021", "followers": 266, "is_user_verified": false, "favorite_count": 1, "in_reply_to_status_id": null, "keyword": "zalando", "language": "it"}, {"user_id": 1281368782452273152, "user_statuses": 492, "name": "Saramauro2402", "tweet": "Chapeau all\u2019ultima pubblicit\u00e0 di Zalando\nYour values. Here to stay. | Spring 2021 | Zalando https://t.co/nL8CxyGbOt via @YouTube", "retweets": 0, "location": "", "created": "29-Mar-2021", "followers": 94, "is_user_verified": false, "favorite_count": 0, "in_reply_to_status_id": null, "keyword": "zalando", "language": "it"}, {"user_id": 1192512188797329408, "user_statuses": 383, "name": "vincax2", "tweet": "@djuud_ @MAD_scripts tanto non puoi cartare su zalando", "retweets": 0, "location": "", "created": "29-Mar-2021", "followers": 4, "is_user_verified": false, "favorite_count": 0, "in_reply_to_status_id": 1376629309889187841, "keyword": "zalando", "language": "it"}, {"user_id": 183968090, "user_statuses": 18915, "name": "niceut", "tweet": "Non so se esiste ancora qualcuno al mondo che non ha mai acquistato su #zalando per\u00f2 raga se vi serve qua 10 \u20ac di sconto https://t.co/rNZUhr3Y7P al primo acquisto", "retweets": 0, "location": "Out There, Milan, Italy.", "created": "29-Mar-2021", "followers": 819, "is_user_verified": false, "favorite_count": 0, "in_reply_to_status_id": null, "keyword": "zalando", "language": "it"}, {"user_id": 1339267211161112581, "user_statuses": 35674, "name": "ildpaa", "tweet": "E comunque Buffon a 50 anni \u00e8 pi\u00f9 forte di zalando prive", "retweets": 0, "location": "", "created": "29-Mar-2021", "followers": 971, "is_user_verified": false, "favorite_count": 8, "in_reply_to_status_id": null, "keyword": "zalando", "language": "it"}, {"user_id": 1245786965322104832, "user_statuses": 1576, "name": "Roberta67283980", "tweet": "@alice_ledda_ Non affidarti troppo alle taglie, ma considera il modello e le recensioni. Alcuni siti come Zalando specificano le misure della taglia indossata dalla persona in foto, in modo tale che tu possa farti un'idea.", "retweets": 0, "location": "", "created": "29-Mar-2021", "followers": 104, "is_user_verified": false, "favorite_count": 2, "in_reply_to_status_id": 1376531107550797830, "keyword": "zalando", "language": "it"}, {"user_id": 1334861089125883905, "user_statuses": 8156, "name": "TruppenStrunz", "tweet": "A questi arcobalenati, \ndategli Amazon, Zalando e Netflix che se ne strafottono\ndi tutta la distruzione economica che li circonda. https://t.co/M4aHFQQ1wG", "retweets": 0, "location": "", "created": "29-Mar-2021", "followers": 80, "is_user_verified": false, "favorite_count": 0, "in_reply_to_status_id": null, "keyword": "zalando", "language": "it"}, {"user_id": 514133448, "user_statuses": 17710, "name": "vulnerabletype", "tweet": "@Lepetitchat___ un po su tutti i siti online \ud83e\udd7a tipo zalando/asos", "retweets": 0, "location": "", "created": "29-Mar-2021", "followers": 4619, "is_user_verified": false, "favorite_count": 1, "in_reply_to_status_id": 1376516638309298177, "keyword": "zalando", "language": "it"}, {"user_id": 547421843, "user_statuses": 32574, "name": "antipaticq", "tweet": "ho comprato troppa roba su zalando madonna mia", "retweets": 0, "location": "she \u00a1 her ", "created": "29-Mar-2021", "followers": 3678, "is_user_verified": false, "favorite_count": 0, "in_reply_to_status_id": null, "keyword": "zalando", "language": "it"}, {"user_id": 1215959686106812416, "user_statuses": 13627, "name": "gabriel1919__", "tweet": "Se non mi arriva zalando entro pasqua mi faccio esplodere", "retweets": 0, "location": "Texas, USA", "created": "29-Mar-2021", "followers": 258, "is_user_verified": false, "favorite_count": 1, "in_reply_to_status_id": null, "keyword": "zalando", "language": "it"}, {"user_id": 833690862269956097, "user_statuses": 117, "name": "funkytarroDOC", "tweet": "Adesso, siccome non ho tanta voglia di lavorare, far\u00f2 una delle cose di cui posso vantare la mia maestria: comprer\u00f2 qualcosa su Amazon o su Zalando.\nSeguitemi per altri consigli su come  avere il conto in rosso. \nxoxo", "retweets": 0, "location": "Italia", "created": "29-Mar-2021", "followers": 19, "is_user_verified": false, "favorite_count": 0, "in_reply_to_status_id": null, "keyword": "zalando", "language": "it"}, {"user_id": 3169610315, "user_statuses": 3052, "name": "ElleEr_", "tweet": "Cio\u00e8, ne ho visti altri simili a questo, anche su Zalando, ma non mi piacciono tanto quanto questo \ud83d\ude02", "retweets": 0, "location": "", "created": "29-Mar-2021", "followers": 85, "is_user_verified": false, "favorite_count": 0, "in_reply_to_status_id": 1376455602944282627, "keyword": "zalando", "language": "it"}, {"user_id": 4846182899, "user_statuses": 22019, "name": "youfockingloser", "tweet": "zalando non mi fa tracciare l'ordine non ho idea di quando arrivi https://t.co/T6XqhK4VXD", "retweets": 0, "location": "louis and niall noticed", "created": "29-Mar-2021", "followers": 6119, "is_user_verified": false, "favorite_count": 0, "in_reply_to_status_id": null, "keyword": "zalando", "language": "it"}, {"user_id": 1081623058857766912, "user_statuses": 792, "name": "htts_potato", "tweet": "La pubblicit\u00e0 della Zalando \u00e8 molto bellanda vedere", "retweets": 0, "location": "", "created": "29-Mar-2021", "followers": 30, "is_user_verified": false, "favorite_count": 0, "in_reply_to_status_id": null, "keyword": "zalando", "language": "it"}, {"user_id": 1615230170, "user_statuses": 10732, "name": "Nayrobica_", "tweet": "avevo messo nel carrello di zalando un paio di scarpe aspettando qualche giorno per vedere se abbassasero il prezzo invece lo hanno aumentano rip", "retweets": 0, "location": "she/her", "created": "29-Mar-2021", "followers": 970, "is_user_verified": false, "favorite_count": 1, "in_reply_to_status_id": null, "keyword": "zalando", "language": "it"}, {"user_id": 862679263706849280, "user_statuses": 27196, "name": "twosweetghosts", "tweet": "@fearlvess Deve eliminare tutta la competizione cos\u00ec pu\u00f2 pensare solo agli Zalando", "retweets": 0, "location": "Torrenuvola ", "created": "29-Mar-2021", "followers": 885, "is_user_verified": false, "favorite_count": 2, "in_reply_to_status_id": 1376428680700911625, "keyword": "zalando", "language": "it"}, {"user_id": 349700326, "user_statuses": 20327, "name": "xrita_", "tweet": "\u201ctommaso hai rotto il cazzo, superalo il gf, basta postare robe con quello, ti unfollowo, superala, fomenti le fanatiche\u201d\n\u201c\ud83d\ude0d\ud83d\ude0d\ud83d\ude0d che belli gli zalando, piango, che dolci, maledetta primavera \ud83d\ude0d\ud83d\ude0d\ud83d\ude0d\u201d", "retweets": 3, "location": "anyway the wind blows", "created": "28-Mar-2021", "followers": 1194, "is_user_verified": false, "favorite_count": 89, "in_reply_to_status_id": null, "keyword": "zalando", "language": "it"}, {"user_id": 3435288599, "user_statuses": 26719, "name": "ErikaSpampinato", "tweet": "@julalbx Il social manager di Zalando che legge il tuo tweet: \ud83d\udc41\ufe0f\ud83d\udc44\ud83d\udc41\ufe0f", "retweets": 0, "location": "Italia", "created": "28-Mar-2021", "followers": 684, "is_user_verified": false, "favorite_count": 4, "in_reply_to_status_id": 1376312155717402631, "keyword": "zalando", "language": "it"}, {"user_id": 1318865314059292675, "user_statuses": 6824, "name": "julalbx", "tweet": "Io sono proprio 100% hater dei fan zalando ossessionati", "retweets": 3, "location": "Zorpe Pazze", "created": "28-Mar-2021", "followers": 1387, "is_user_verified": false, "favorite_count": 75, "in_reply_to_status_id": null, "keyword": "zalando", "language": "it"}, {"user_id": 2533129787, "user_statuses": 61311, "name": "avtistich", "tweet": "QUANTO ODIO LA PUBBLICIT\u00c0 DI ZALANDO SU YOUTUBE NON \u00c8 POSSIBILE CHE \u00c8 OVUNQUE", "retweets": 0, "location": "pizzeria ", "created": "28-Mar-2021", "followers": 4568, "is_user_verified": false, "favorite_count": 0, "in_reply_to_status_id": null, "keyword": "zalando", "language": "it"}, {"user_id": 1143677174, "user_statuses": 12512, "name": "sursumcorda29", "tweet": "@Viveteliberi Ricevevo la newsletter perch\u00e9 una volta comprai qualcosa, ma dopo quello schifo di spot ho messo #Zalando nelle spam!", "retweets": 1, "location": "Piemonte, Italia", "created": "28-Mar-2021", "followers": 1766, "is_user_verified": false, "favorite_count": 1, "in_reply_to_status_id": 1376299652010639362, "keyword": "zalando", "language": "it"}, {"user_id": 1339525654820339714, "user_statuses": 37605, "name": "TricoloreNat", "tweet": "Zalando : Affermare i propri valori !! \ud83d\ude21 Ma l' avete visto lo Spot ? Io penso il peggiore che ho visto fin ora !! Questo non sanno neanche che significa VALORI \ud83d\ude21\ud83d\ude21\ud83d\ude21\ud83d\ude21\ud83d\ude21", "retweets": 5, "location": "", "created": "28-Mar-2021", "followers": 1042, "is_user_verified": false, "favorite_count": 21, "in_reply_to_status_id": null, "keyword": "zalando", "language": "it"}, {"user_id": 878243594, "user_statuses": 1258, "name": "PBazzotti", "tweet": "#Zalando ha creato una pubblicit\u00e0 con due uomini che si baciano alla fine del video. In prima serata poi! Che schifo. Vergognosi #lgbt #gaypride #LBGT", "retweets": 0, "location": "Veneto", "created": "28-Mar-2021", "followers": 81, "is_user_verified": false, "favorite_count": 2, "in_reply_to_status_id": null, "keyword": "zalando", "language": "it"}, {"user_id": 851011347181711361, "user_statuses": 9610, "name": "_Strafanti", "tweet": "@lacamys L' ho guardati su zalando ma dicevano tutti nei commenti che la chiusura non \u00e9 sicura.", "retweets": 0, "location": "Treviso, Veneto", "created": "28-Mar-2021", "followers": 231, "is_user_verified": false, "favorite_count": 1, "in_reply_to_status_id": 1376251415044194318, "keyword": "zalando", "language": "it"}, {"user_id": 3341445826, "user_statuses": 4994, "name": "EvaMariaRaz_", "tweet": "Ho appena comprato due magliette della Levis su Zalando, mi gioco qualsiasi cosa che ho sicuramente sbagliato taglia", "retweets": 0, "location": "", "created": "28-Mar-2021", "followers": 188, "is_user_verified": false, "favorite_count": 0, "in_reply_to_status_id": null, "keyword": "zalando", "language": "it"}, {"user_id": 212622184, "user_statuses": 54955, "name": "incatenarsi", "tweet": "\ud83d\udcf8LOVBY: per chi ama fotografare o semplicemente postare sui social. Ci sono anche altre missioni: dal seguire pagine (fb / ig ) al mettere like, al rispondere a sondaggi! \n\nPremi: buoni amazon, mondadori, trony, ricariche, Zalando etc \n\nhttps://t.co/palFEV9cBI", "retweets": 0, "location": "", "created": "28-Mar-2021", "followers": 10066, "is_user_verified": false, "favorite_count": 1, "in_reply_to_status_id": 1376216658478518272, "keyword": "zalando", "language": "it"}, {"user_id": 1143130666290356225, "user_statuses": 7498, "name": "johanna46273152", "tweet": "cancella carrello Zalando...delete...delete...delete... https://t.co/16k4ntmKf7", "retweets": 0, "location": "", "created": "28-Mar-2021", "followers": 306, "is_user_verified": false, "favorite_count": 3, "in_reply_to_status_id": null, "keyword": "zalando", "language": "it"}, {"user_id": 1200100501456596993, "user_statuses": 631, "name": "fedegiannini1", "tweet": "A #Verona, @Zalando omaggia #Dante nel #Danted\u00ec sponsorizzando il restauro del monumento di piazza dei Signori dedicato al poeta\n\nhttps://t.co/jCKorv377A", "retweets": 4, "location": "", "created": "27-Mar-2021", "followers": 953, "is_user_verified": false, "favorite_count": 7, "in_reply_to_status_id": null, "keyword": "zalando", "language": "it"}, {"user_id": 250171655, "user_statuses": 82835, "name": "saturninox", "tweet": "@semplici8 @paolinab @Lukazzu @NOprisonersEVER @deb8479eaeef410 @ernoirsfina_ @JessRab94943151 @caterita2008 @consolefirmin @klaatu29 @wshaper @alepaolux @donnadimezzo @sydbarrett76 @alinocomicon @Rocco14410460 @realePadreTava @Lucalambrate @iggyHT @Voormas @UserQuidam @ahp68 @SaraLF74 @er_tenebra @Happy4Trigger @qO__Qp @SgrazX @Daniela33087050 @insudj @PiLu975 @Jessica97737031 @semedizecca @Cibermatico @Philo1936 @AndreC198 @lasxripartada @Luca78901689 @alPaoloMazza64 @Cassandrino @squopellediluna @Tas_89tas @f10rux @RagnacciG @zerocompromess @paztusipaz @Zbarskij @AccademiaCrusca Hai controllato Zalando?", "retweets": 0, "location": "piemonte", "created": "27-Mar-2021", "followers": 3518, "is_user_verified": false, "favorite_count": 4, "in_reply_to_status_id": 1375892894435962889, "keyword": "zalando", "language": "it"}, {"user_id": 1187485885283127301, "user_statuses": 342, "name": "Giorgitooo", "tweet": "I pubblicitari di Zalando hanno detto \u201clet\u2019s kill the boomers\u201d", "retweets": 0, "location": "Italia", "created": "27-Mar-2021", "followers": 212, "is_user_verified": false, "favorite_count": 1, "in_reply_to_status_id": null, "keyword": "zalando", "language": "it"}, {"user_id": 696421876529287169, "user_statuses": 20494, "name": "lookafterloueeh", "tweet": "Gli ordini di zalando ancora in attesa e la voglia di lanciare il telefono al muro", "retweets": 0, "location": "\u2112 & \u210b", "created": "27-Mar-2021", "followers": 407, "is_user_verified": false, "favorite_count": 0, "in_reply_to_status_id": null, "keyword": "zalando", "language": "it"}, {"user_id": 2934016737, "user_statuses": 46815, "name": "vilutini4", "tweet": "@elisa_m97 Elii\u2665\ufe0f\nCertoo l'ho presa su zalando ma \u00e8 la tuta di Bershka", "retweets": 0, "location": "11.239,96km ArgenTini", "created": "27-Mar-2021", "followers": 2822, "is_user_verified": false, "favorite_count": 1, "in_reply_to_status_id": 1375816556962267142, "keyword": "zalando", "language": "it"}, {"user_id": 1208492821, "user_statuses": 15183, "name": "slothjnv", "tweet": "cio\u00e8 in pratica ricevete 50 euro di cashback se comprate su zalando, asos, shein, amazon e altri siti vabb\u00e8 poi vedete da voi pls cagatemi", "retweets": 0, "location": "Toscana, Italia", "created": "27-Mar-2021", "followers": 307, "is_user_verified": false, "favorite_count": 0, "in_reply_to_status_id": 1375807434506309634, "keyword": "zalando", "language": "it"}, {"user_id": 1339267211161112581, "user_statuses": 35674, "name": "ildpaa", "tweet": "@acmilan Io voglio belotti Buendia e vlasic. Via zalando cacio e pepe e rebic", "retweets": 0, "location": "", "created": "27-Mar-2021", "followers": 971, "is_user_verified": false, "favorite_count": 6, "in_reply_to_status_id": 1375797904133259267, "keyword": "zalando", "language": "it"}, {"user_id": 181302619, "user_statuses": 65629, "name": "_Call_Me_Liv", "tweet": "Ma \u00e8 normale che io non posso chiudere una cartella al PC perch\u00e9 la strutturata deve usarlo per fare acquisti su Zalando?", "retweets": 0, "location": "Bari, Puglia", "created": "27-Mar-2021", "followers": 2256, "is_user_verified": false, "favorite_count": 4, "in_reply_to_status_id": null, "keyword": "zalando", "language": "it"}, {"user_id": 2784142880, "user_statuses": 59775, "name": "calliopefleury", "tweet": "Fav e mi consigliate se procedere al mio acquisto zalando", "retweets": 0, "location": "\uff91\uff9a \u2661\ufe0e", "created": "27-Mar-2021", "followers": 4072, "is_user_verified": false, "favorite_count": 6, "in_reply_to_status_id": null, "keyword": "zalando", "language": "it"}, {"user_id": 1146500399899316227, "user_statuses": 8907, "name": "giovane_pres", "tweet": "sto covid-19 no, non sta spaccando\nspero che quest\u2019anno vada migliorando\naltrimenti chiedo il reso frate come su zalando", "retweets": 0, "location": "Manerbio, Lombardia", "created": "27-Mar-2021", "followers": 763, "is_user_verified": false, "favorite_count": 4, "in_reply_to_status_id": null, "keyword": "zalando", "language": "it"}, {"user_id": 1294705365213478913, "user_statuses": 155, "name": "toniadetta", "tweet": "Io semper fidelis a Zalando, su consiglio di una mia amica tent\u00f2 il mio primo ordine su Shein nonostante la mia ritrosia. \n\u00c8 arrivato il pacco: capi sbagliati. \nIl mio sesto senso \u00e8 pi\u00f9 intelligente di me.", "retweets": 0, "location": "", "created": "27-Mar-2021", "followers": 12, "is_user_verified": false, "favorite_count": 0, "in_reply_to_status_id": null, "keyword": "zalando", "language": "it"}, {"user_id": 1242922407259758597, "user_statuses": 10949, "name": "hoIyperfume", "tweet": "@heydeIilah Amo io ti consiglio di vedere su Zalando e di prendere la taglia pi\u00f9 stretta. Considera questa \u00e8 la xs e io prima portavo una quinta \ud83e\udd75", "retweets": 0, "location": "", "created": "26-Mar-2021", "followers": 2338, "is_user_verified": false, "favorite_count": 1, "in_reply_to_status_id": 1375562900425826305, "keyword": "zalando", "language": "it"}, {"user_id": 1242922407259758597, "user_statuses": 10949, "name": "hoIyperfume", "tweet": "@heydeIilah Ah ahahahha l\u2019ho comprato su Zalando qualcosa come 6 anni fa non lo fanno pi\u00f9 \ud83d\ude29", "retweets": 0, "location": "", "created": "26-Mar-2021", "followers": 2338, "is_user_verified": false, "favorite_count": 0, "in_reply_to_status_id": 1375561191720947715, "keyword": "zalando", "language": "it"}, {"user_id": 102340519, "user_statuses": 8975, "name": "delsa18", "tweet": "@DylanmattiaBr Soprattutto si Zalando sono tutti fighissimi \ud83d\ude25", "retweets": 0, "location": "Vecchiano, Toscana", "created": "26-Mar-2021", "followers": 358, "is_user_verified": false, "favorite_count": 0, "in_reply_to_status_id": 1375560410942803969, "keyword": "zalando", "language": "it"}, {"user_id": 1850971981, "user_statuses": 32854, "name": "FinestreArte", "tweet": "A Verona, Zalando, il noto e-commerce di abbigliamento, sponsorizza il restauro del monumento del 1865 a Dante Alighieri in piazza dei Signori. https://t.co/sCSrEnUXDQ", "retweets": 2, "location": "Carrara", "created": "26-Mar-2021", "followers": 21943, "is_user_verified": false, "favorite_count": 2, "in_reply_to_status_id": null, "keyword": "zalando", "language": "it"}, {"user_id": 2704022416, "user_statuses": 4067, "name": "MassyJuve73", "tweet": "@juventino872 E mannaggia.... hai provato con zalando?\ud83d\ude02\ud83d\ude02\ud83e\udd26\u200d\u2642\ufe0f", "retweets": 0, "location": "Roma Italy", "created": "26-Mar-2021", "followers": 703, "is_user_verified": false, "favorite_count": 1, "in_reply_to_status_id": 1375461684966522886, "keyword": "zalando", "language": "it"}, {"user_id": 435266311, "user_statuses": 11175, "name": "Mahdubito", "tweet": "Mi arriva email Zalando.\n\"Nuovo look per Pasqua\" https://t.co/8fjQIEHGZq", "retweets": 0, "location": "Roma o gi\u00f9 di l\u00ec!", "created": "26-Mar-2021", "followers": 237, "is_user_verified": false, "favorite_count": 0, "in_reply_to_status_id": null, "keyword": "zalando", "language": "it"}, {"user_id": 3001138413, "user_statuses": 43139, "name": "prendiunabirra", "tweet": "Zalando mi prendi per il culo? https://t.co/XljU3JeNOY", "retweets": 0, "location": "", "created": "26-Mar-2021", "followers": 1519, "is_user_verified": false, "favorite_count": 2, "in_reply_to_status_id": null, "keyword": "zalando", "language": "it"}, {"user_id": 1027552289756729345, "user_statuses": 6344, "name": "romantiquehaz", "tweet": "fatto ordine su zalando", "retweets": 0, "location": "she/her", "created": "26-Mar-2021", "followers": 396, "is_user_verified": false, "favorite_count": 0, "in_reply_to_status_id": null, "keyword": "zalando", "language": "it"}, {"user_id": 2267686449, "user_statuses": 497, "name": "albyr98", "tweet": "#Zalando mi hai deluso", "retweets": 0, "location": "San Don\u00e0 di Piave, Veneto", "created": "26-Mar-2021", "followers": 50, "is_user_verified": false, "favorite_count": 0, "in_reply_to_status_id": null, "keyword": "zalando", "language": "it"}, {"user_id": 2876234927, "user_statuses": 38109, "name": "goldoux", "tweet": "vorrei comprare qualcosa su Zalando", "retweets": 0, "location": "\ud83c\uddee\ud83c\uddf9", "created": "26-Mar-2021", "followers": 1768, "is_user_verified": false, "favorite_count": 0, "in_reply_to_status_id": null, "keyword": "zalando", "language": "it"}, {"user_id": 1361277624388112384, "user_statuses": 127, "name": "darkl1na", "tweet": "buongiorno da mia madre che ha scambiato Zalando per Amazon e si \u00e8 letteralmente arrabbiata con me perch\u00e9 non trovava i libri che cercava. \ud83e\udd21", "retweets": 0, "location": "", "created": "26-Mar-2021", "followers": 57, "is_user_verified": false, "favorite_count": 0, "in_reply_to_status_id": null, "keyword": "zalando", "language": "it"}, {"user_id": 1020600515493810176, "user_statuses": 16855, "name": "fixsomg", "tweet": "Poi ci sono io che non mi so comprare manco degli stivali su zalando", "retweets": 0, "location": "\u2661 14/04/2019 \u2661", "created": "26-Mar-2021", "followers": 160, "is_user_verified": false, "favorite_count": 0, "in_reply_to_status_id": 1375413252000260097, "keyword": "zalando", "language": "it"}, {"user_id": 1242922407259758597, "user_statuses": 10949, "name": "hoIyperfume", "tweet": "Mi piace tantissimo il tuo stile, solitamente dove compri i vestiti? \ud83e\udd7a \u2014 Guarda non faccio shopping da una vita in verit\u00e0 per\u00f2 diciamo zalando/Zara/Bershka prevalentemente\nGrazie comunque \ud83e\udd7a\ud83e\udd7a\ud83e\udd7a\ud83e\udd7a https://t.co/oXyxXVhBP3", "retweets": 0, "location": "", "created": "26-Mar-2021", "followers": 2338, "is_user_verified": false, "favorite_count": 0, "in_reply_to_status_id": null, "keyword": "zalando", "language": "it"}, {"user_id": 1129796098527301632, "user_statuses": 3441, "name": "AgenoreG", "tweet": "@pleporace Zalando con Gls, Amazon con Bartolini, e nel primo pomeriggio \u00e8 programmata SDA. Non scherzo...", "retweets": 0, "location": "", "created": "26-Mar-2021", "followers": 39, "is_user_verified": false, "favorite_count": 0, "in_reply_to_status_id": 1375406855791476744, "keyword": "zalando", "language": "it"}, {"user_id": 1252750048938602496, "user_statuses": 5967, "name": "Guido_1927", "tweet": "@Nicoletta7692 Mi che ho comprato un giubbotto di jeans da Zalando, non me lo fare arrivare in ritardo \ud83e\udd23\ud83e\udd23\ud83e\udd23\ud83e\udd23", "retweets": 0, "location": "Sassari, Sardegna", "created": "26-Mar-2021", "followers": 111, "is_user_verified": false, "favorite_count": 0, "in_reply_to_status_id": 1375395190089863170, "keyword": "zalando", "language": "it"}, {"user_id": 421372473, "user_statuses": 27430, "name": "_Vale_ria_", "tweet": "@Teodori_Trad Grazie Laura, era per Zalando normale, fatto, non importa ma grazie mille", "retweets": 0, "location": "", "created": "26-Mar-2021", "followers": 1916, "is_user_verified": false, "favorite_count": 1, "in_reply_to_status_id": 1375388090416631815, "keyword": "zalando", "language": "it"}, {"user_id": 947861436910456834, "user_statuses": 63659, "name": "streetloveitaly", "tweet": "@ili_bibi Scusa ma \u00e8 zalando oppure dolce&amp;gabbana?? \ud83d\ude31", "retweets": 0, "location": "Roma, Lazio", "created": "26-Mar-2021", "followers": 313, "is_user_verified": false, "favorite_count": 2, "in_reply_to_status_id": 1375378645942943746, "keyword": "zalando", "language": "it"}, {"user_id": 2791952326, "user_statuses": 1583, "name": "Teodori_Trad", "tweet": "@_Vale_ria_ Ne ho uno per Zalando Prive 10% su spesa minima di 60 euro.", "retweets": 0, "location": "Bologna", "created": "26-Mar-2021", "followers": 69, "is_user_verified": false, "favorite_count": 0, "in_reply_to_status_id": 1375191920956342273, "keyword": "zalando", "language": "it"}, {"user_id": 1283047590519623682, "user_statuses": 30587, "name": "fallingxwoman", "tweet": "zalando dopo questa ti amo ancora di pi\u00f9 https://t.co/2zvqCHO0Pp", "retweets": 0, "location": "in ale and harry\u2019s arms", "created": "26-Mar-2021", "followers": 1926, "is_user_verified": false, "favorite_count": 12, "in_reply_to_status_id": null, "keyword": "zalando", "language": "it"}, {"user_id": 945102892956086272, "user_statuses": 51882, "name": "lorenzhaus", "tweet": "@ilrisolutoreIT B\u00e8h,  il contante si pu\u00f2 usare pure negli acquisti on line. V. Zalando, Amazon etc.", "retweets": 0, "location": "", "created": "26-Mar-2021", "followers": 646, "is_user_verified": false, "favorite_count": 0, "in_reply_to_status_id": 1375380182941466624, "keyword": "zalando", "language": "it"}, {"user_id": 76047935, "user_statuses": 12928, "name": "ili_bibi", "tweet": "Zalando che mi propone gonne a 760 euro non hai capito un cazzo proprio.", "retweets": 0, "location": "NO", "created": "26-Mar-2021", "followers": 4241, "is_user_verified": false, "favorite_count": 23, "in_reply_to_status_id": null, "keyword": "zalando", "language": "it"}, {"user_id": 3130647231, "user_statuses": 37682, "name": "_MR_MY__", "tweet": "Non \u00e8 da me fare #spam o proporre prodotti, per\u00f2 iscrivendovi qui da questo link parteciperete a semplici #sondaggi e vi ripagano con buoni #Amazon #Zalando #Carrefour #Decathlon ecc \ud83d\ude01\nNiente di complicato\n\ni-Say, partecipa a questionari e ottieni premi!  https://t.co/yNILoEhTvE", "retweets": 0, "location": "", "created": "26-Mar-2021", "followers": 1134, "is_user_verified": false, "favorite_count": 0, "in_reply_to_status_id": null, "keyword": "zalando", "language": "it"}, {"user_id": 1006154284340318208, "user_statuses": 1534, "name": "LoJackItalia", "tweet": "Ecco il programma che premia la guida sostenibile, dedicato in esclusiva ai clienti di Nuova 500\n#kiricoin #amazon #applemusic #netflix #spotify #zalando #score #programma #fiat #fiat500 #ecosostenibile #emobility #stellantis Continua a leggere la news https://t.co/t2rx6qRvcL", "retweets": 0, "location": "Italia", "created": "26-Mar-2021", "followers": 147, "is_user_verified": false, "favorite_count": 0, "in_reply_to_status_id": null, "keyword": "zalando", "language": "it"}, {"user_id": 1443706704, "user_statuses": 72785, "name": "laltrodiego", "tweet": "Visto ora lo spot di Zalando.\nNauseante.", "retweets": 0, "location": "ITALIA", "created": "25-Mar-2021", "followers": 5896, "is_user_verified": false, "favorite_count": 6, "in_reply_to_status_id": null, "keyword": "zalando", "language": "it"}, {"user_id": 703386818, "user_statuses": 128012, "name": "WaldoVanVerhoek", "tweet": "@paolovincenzi @giulianol @claudiocerasa Tu invece eri un imbecille ieri, lo sei oggi e lo sarai domani.\n\nSei una garanzia, come il reso di Zalando.", "retweets": 0, "location": "", "created": "25-Mar-2021", "followers": 3279, "is_user_verified": false, "favorite_count": 1, "in_reply_to_status_id": 1375141862923776003, "keyword": "zalando", "language": "it"}, {"user_id": 738849155565662208, "user_statuses": 54847, "name": "offkeyrhapsody", "tweet": "mi sono rifatta il guardaroba su zalando\npoi mi sono ricordata che non c'ho 1 euro\ne ho rispettosamente chiuso il sito", "retweets": 0, "location": "italy", "created": "25-Mar-2021", "followers": 482, "is_user_verified": false, "favorite_count": 1, "in_reply_to_status_id": null, "keyword": "zalando", "language": "it"}, {"user_id": 421372473, "user_statuses": 27430, "name": "_Vale_ria_", "tweet": "Abbiamo codici sconto Zalando?", "retweets": 0, "location": "", "created": "25-Mar-2021", "followers": 1916, "is_user_verified": false, "favorite_count": 1, "in_reply_to_status_id": null, "keyword": "zalando", "language": "it"}, {"user_id": 1018286869, "user_statuses": 20161, "name": "FolleFolleIDEA", "tweet": "@byb80 No.. a a me le mail me le mandano Zalando.. ho gi\u00e0 tre armadi pieni.", "retweets": 0, "location": "C\u00fcgos, MANTOVA (Uraniana)", "created": "25-Mar-2021", "followers": 1089, "is_user_verified": false, "favorite_count": 1, "in_reply_to_status_id": 1375046204648751105, "keyword": "zalando", "language": "it"}, {"user_id": 1085870378, "user_statuses": 42512, "name": "Bruciato_vivo", "tweet": "Ora la wishlist di zalando \u00e8 salita a circa 1000 euro", "retweets": 0, "location": "Colonia Extramondo", "created": "25-Mar-2021", "followers": 298, "is_user_verified": false, "favorite_count": 1, "in_reply_to_status_id": null, "keyword": "zalando", "language": "it"}, {"user_id": 1140535207, "user_statuses": 60782, "name": "____carlo____", "tweet": "Lo spot #zalando fa ribrezzo...", "retweets": 0, "location": "Lecco ", "created": "25-Mar-2021", "followers": 1300, "is_user_verified": false, "favorite_count": 1, "in_reply_to_status_id": null, "keyword": "zalando", "language": "it"}, {"user_id": 1648472989, "user_statuses": 23879, "name": "EhysonoEmi", "tweet": "@viverevdomani Prego\ud83d\ude18\nProva a vedere anche su zalando", "retweets": 0, "location": "", "created": "25-Mar-2021", "followers": 4539, "is_user_verified": false, "favorite_count": 1, "in_reply_to_status_id": 1375132729805836290, "keyword": "zalando", "language": "it"}, {"user_id": 1282409990775607297, "user_statuses": 1758, "name": "coeurdellion", "tweet": "Quando faccio un reso a Zalando e mi ridanno soldi che davo gi\u00e0 per persi https://t.co/aqtpHRcrpB", "retweets": 0, "location": "italy", "created": "25-Mar-2021", "followers": 39, "is_user_verified": false, "favorite_count": 0, "in_reply_to_status_id": null, "keyword": "zalando", "language": "it"}, {"user_id": 4924638706, "user_statuses": 27973, "name": "fletchersmile98", "tweet": "@mymoonstone_ Guarda io posso consigliarti su Zalando (ma anche depop, vinted e negozi dell\u2019usato della tua citt\u00e0 quando non siamo in zona rossa o arancione) i levis: una volta che capisci il modello che meglio ti calza e la tua taglia il gioco \u00e8 fatto!", "retweets": 0, "location": "Torino, Piemonte", "created": "25-Mar-2021", "followers": 2705, "is_user_verified": false, "favorite_count": 1, "in_reply_to_status_id": 1375126049680453632, "keyword": "zalando", "language": "it"}, {"user_id": 1270147956, "user_statuses": 407294, "name": "bimbadiziamara", "tweet": "voi ridete e scherzate ma io ancora qui a chiedermi che cazzo s\u00ec \u00e9 ordinato. Ora lo voglio proprio vedere questo pacco. Chiss\u00e0 se era Zalando o qualcosa di Amazon. \n\nVoi sottovalutate l\u2019importanza di un pacco.", "retweets": 0, "location": "Sicilia, Italia", "created": "25-Mar-2021", "followers": 3709, "is_user_verified": false, "favorite_count": 65, "in_reply_to_status_id": null, "keyword": "zalando", "language": "it"}, {"user_id": 109928603, "user_statuses": 13442, "name": "IolandaPompilio", "tweet": "Quanto mi piace la pubblicit\u00e0 di #zalando", "retweets": 0, "location": "Puglia", "created": "25-Mar-2021", "followers": 475, "is_user_verified": false, "favorite_count": 0, "in_reply_to_status_id": null, "keyword": "zalando", "language": "it"}, {"user_id": 1339267211161112581, "user_statuses": 35674, "name": "ildpaa", "tweet": "@FinallyMichele @_enz29 @jnterista_12 se tu vendi papera zalando a 50 hai molto piu di 50 da spendere dato che si tratta di pura plusvalenza", "retweets": 0, "location": "", "created": "25-Mar-2021", "followers": 971, "is_user_verified": false, "favorite_count": 1, "in_reply_to_status_id": 1375099141676806146, "keyword": "zalando", "language": "it"}, {"user_id": 1344020827587678211, "user_statuses": 9532, "name": "incazzzata", "tweet": "@sophieghissima @checazneso Sono abbastanza sfigata con sta roba della mail calcola che sto aspettando un paio di stivali su zalando da due mesi e anche quando beccai la mail inviata una mezz'ora prima erano tornati sold out", "retweets": 0, "location": "brasil no cora\u00e7\u00e3o\ud83c\udde7\ud83c\uddf7", "created": "25-Mar-2021", "followers": 283, "is_user_verified": false, "favorite_count": 2, "in_reply_to_status_id": 1375081866106142724, "keyword": "zalando", "language": "it"}, {"user_id": 1374728536066555909, "user_statuses": 7, "name": "fratrsgn", "tweet": "sto usando la mail istituzionale per avere lo sconto sui leggings zebrati su zalando", "retweets": 0, "location": "", "created": "25-Mar-2021", "followers": 8, "is_user_verified": false, "favorite_count": 4, "in_reply_to_status_id": null, "keyword": "zalando", "language": "it"}, {"user_id": 547421843, "user_statuses": 32574, "name": "antipaticq", "tweet": "sto per spendere due stipendi su zalando, fermatemi", "retweets": 0, "location": "she \u00a1 her ", "created": "25-Mar-2021", "followers": 3678, "is_user_verified": false, "favorite_count": 2, "in_reply_to_status_id": null, "keyword": "zalando", "language": "it"}, {"user_id": 859679965, "user_statuses": 26032, "name": "S7ILLWI7HJK", "tweet": "ci sono degli anfibi che voglio prendere su zalando ma sono scontatissime solo quelle bianche e io le voglio nere che obv sono a prezzo pieno \ud83d\ude20\ud83d\ude20\ud83d\ude20", "retweets": 0, "location": "italy", "created": "25-Mar-2021", "followers": 6448, "is_user_verified": false, "favorite_count": 0, "in_reply_to_status_id": null, "keyword": "zalando", "language": "it"}, {"user_id": 3292801099, "user_statuses": 4223, "name": "_artxfice", "tweet": "non so se sopporto di meno la pubblicit\u00e0 di zalando o quella di vinted", "retweets": 1, "location": "Beacon hills", "created": "25-Mar-2021", "followers": 295, "is_user_verified": false, "favorite_count": 1, "in_reply_to_status_id": null, "keyword": "zalando", "language": "it"}, {"user_id": 726085176, "user_statuses": 88070, "name": "piedipalmati", "tweet": "comunque avevo trovato le scarpe della vita su zalando era finito il numero avevo chiesto la notifica quando tornava e ora non ci sono neanche pi\u00f9 sul sito mi metto a piangere non le trovo da nessun'altra parteeee", "retweets": 0, "location": "Juventus Stadium ", "created": "25-Mar-2021", "followers": 1100, "is_user_verified": false, "favorite_count": 2, "in_reply_to_status_id": null, "keyword": "zalando", "language": "it"}, {"user_id": 1337077746170814467, "user_statuses": 2105, "name": "nostalgiacanag2", "tweet": "Buoni propositi della giornata:\nIgnorare le offerte \ndi Booking di Amazon e di Zalando", "retweets": 1, "location": "", "created": "25-Mar-2021", "followers": 295, "is_user_verified": false, "favorite_count": 6, "in_reply_to_status_id": null, "keyword": "zalando", "language": "it"}, {"user_id": 326247031, "user_statuses": 6650, "name": "comellini_it", "tweet": "E-commerce: sulle responsabilit\u00e0 dei marketplaces online (come Amazon, eBay, Zalando, ecc.) che rientrano a pieno titolo nella categoria degli Internet Service Providers (\u201cISP\u201d) il cui regime di responsabilit\u00e0 \u00e8 disciplinato dalla Direttiva n. 2000/31/CE https://t.co/xXijLvui4f", "retweets": 0, "location": "Bologna, Italy", "created": "25-Mar-2021", "followers": 6101, "is_user_verified": false, "favorite_count": 0, "in_reply_to_status_id": null, "keyword": "zalando", "language": "it"}, {"user_id": 701072167438516224, "user_statuses": 55984, "name": "n0st4Igia", "tweet": "ho questo bisogno di fare un ordine su zalando mi sto trattenendo per non spendere soldi", "retweets": 0, "location": "greendale", "created": "25-Mar-2021", "followers": 4031, "is_user_verified": false, "favorite_count": 3, "in_reply_to_status_id": null, "keyword": "zalando", "language": "it"}, {"user_id": 475854548, "user_statuses": 64603, "name": "_musixsaved", "tweet": "@xbowerssmile Se vai su zalando ad esempio ti spuntano quando sono sostenibili per tutti i capi di abbigliamento", "retweets": 0, "location": "Snapchat: Frankyedallas", "created": "25-Mar-2021", "followers": 2718, "is_user_verified": false, "favorite_count": 1, "in_reply_to_status_id": 1374983616745373697, "keyword": "zalando", "language": "it"}, {"user_id": 91668426, "user_statuses": 4207, "name": "AndreaPetoletti", "tweet": "Vista la nuova pubblicit\u00e0 di #Zalando?\n\ud83e\udd2e\ud83e\udd2e\ud83e\udd2e\ud83e\udd2e\ud83e\udd2e\ud83e\udd2e\ud83e\udd2e\ud83e\udd2e\ud83e\udd2e\ud83e\udd2e\ud83e\udd2e\ud83e\udd2e\n\nBasta, basta, basta !!!", "retweets": 0, "location": "Italy", "created": "25-Mar-2021", "followers": 118, "is_user_verified": false, "favorite_count": 0, "in_reply_to_status_id": null, "keyword": "zalando", "language": "it"}, {"user_id": 1321181911872659459, "user_statuses": 9786, "name": "barrycrumpp", "tweet": "@sxbef no purtroppo, ma se cerchi su Zalando dovrebbero esserci", "retweets": 0, "location": "New Orleans, LA", "created": "24-Mar-2021", "followers": 2209, "is_user_verified": false, "favorite_count": 0, "in_reply_to_status_id": 1374871397529497604, "keyword": "zalando", "language": "it"}, {"user_id": 2814212657, "user_statuses": 4348, "name": "riccardopoletty", "tweet": "@roscioasociale Quello di Zalando", "retweets": 0, "location": "Brescia, Lombardia", "created": "24-Mar-2021", "followers": 513, "is_user_verified": false, "favorite_count": 1, "in_reply_to_status_id": 1374820236256493568, "keyword": "zalando", "language": "it"}, {"user_id": 219713733, "user_statuses": 2324, "name": "lisabau1", "tweet": "Love Zalando che celebra la diversit\u00e0 #chilhavisto", "retweets": 0, "location": "France", "created": "24-Mar-2021", "followers": 39, "is_user_verified": false, "favorite_count": 0, "in_reply_to_status_id": null, "keyword": "zalando", "language": "it"}, {"user_id": 453965672, "user_statuses": 100846, "name": "GiuseppinaInfra", "tweet": "Il nuovo spot di Zalando \u00e8 superlativo \n#chilhavisto", "retweets": 0, "location": "Lugano, Svizzera", "created": "24-Mar-2021", "followers": 2052, "is_user_verified": false, "favorite_count": 2, "in_reply_to_status_id": null, "keyword": "zalando", "language": "it"}, {"user_id": 413303258, "user_statuses": 41270, "name": "highwiedermond", "tweet": "secondo ordine su zalando di prova poi paga ci sto prendendo gusto", "retweets": 0, "location": "fan account", "created": "24-Mar-2021", "followers": 2028, "is_user_verified": false, "favorite_count": 0, "in_reply_to_status_id": null, "keyword": "zalando", "language": "it"}, {"user_id": 1003379585847889920, "user_statuses": 11134, "name": "peppe_zk", "tweet": "disperatamente bisogno nella mia vita di @ramonatabita , sono stanco di stare mesi a creare look tra asos, shein e zalando ! Ho bisogno di una mente pi\u00f9 creativa della mia per il giorno degli orali di maturit\u00e0 !!!", "retweets": 0, "location": "Sicilia, Italia", "created": "24-Mar-2021", "followers": 104, "is_user_verified": false, "favorite_count": 0, "in_reply_to_status_id": null, "keyword": "zalando", "language": "it"}, {"user_id": 453965672, "user_statuses": 100846, "name": "GiuseppinaInfra", "tweet": "La nuova pubblicit\u00e0 Zalando \u00e8 a dir pico coraggiosa e spiazzante \ud83d\udc4f\ud83d\udc4f\ud83d\udc4f\ud83d\udc4f\ud83d\udc4f", "retweets": 0, "location": "Lugano, Svizzera", "created": "24-Mar-2021", "followers": 2052, "is_user_verified": false, "favorite_count": 1, "in_reply_to_status_id": null, "keyword": "zalando", "language": "it"}, {"user_id": 1062701020093054976, "user_statuses": 25180, "name": "whiskychim", "tweet": "La pubblicit\u00e0 di zalando\ud83d\udc97\ud83c\udf1f\u2728\ud83c\udf3a\ud83d\udc97\ud83c\udf1f\ud83d\udc95\ud83d\udc97\ud83c\udf3a\u2728\ud83c\udf1f\ud83d\udc97\ud83c\udf3a\ud83d\udc97\ud83c\udf1f\ud83d\udc95\ud83c\udf3a", "retweets": 0, "location": "", "created": "24-Mar-2021", "followers": 1715, "is_user_verified": false, "favorite_count": 0, "in_reply_to_status_id": null, "keyword": "zalando", "language": "it"}, {"user_id": 1112479771684933632, "user_statuses": 10498, "name": "Vaner791", "tweet": "@Vitaldent_es  @nocilla @Helvetia_ES  @elcorteingles @clinicasvivanta Vivaz\n@Vivus_spain  Gelocatil\nMeritene @voltadol_es \n@Zalando Orlando @Oreo", "retweets": 0, "location": "", "created": "24-Mar-2021", "followers": 275, "is_user_verified": false, "favorite_count": 0, "in_reply_to_status_id": 1374768570597580800, "keyword": "zalando", "language": "it"}, {"user_id": 2216148016, "user_statuses": 60060, "name": "blesscoldplay", "tweet": "Raga voi i tacchi su zalando li prendete delle vostra taglia o una pi\u00f9 piccola?", "retweets": 0, "location": "summer 1983", "created": "24-Mar-2021", "followers": 4009, "is_user_verified": false, "favorite_count": 0, "in_reply_to_status_id": null, "keyword": "zalando", "language": "it"}, {"user_id": 1154754265652576267, "user_statuses": 30633, "name": "Kobeesque", "tweet": "@missdoubtfire_ La tua carta di credito appena si accorge che hai aperto zalando https://t.co/8eV04CKIQ0", "retweets": 1, "location": "", "created": "24-Mar-2021", "followers": 510, "is_user_verified": false, "favorite_count": 1, "in_reply_to_status_id": 1374756455753125897, "keyword": "zalando", "language": "it"}, {"user_id": 196111881, "user_statuses": 6072, "name": "GrandinettiG", "tweet": "Zalando Digital Campaign with Negramaro. \u201cIl mondo \u00e8 qui, ancora qui, pronto a sorriderci \u201c Agency Ogilvy / CDP @thestylepusher / Styling @rebeccabaglini / Photographer @flavioefrank https://t.co/GE7vkLJ22o", "retweets": 0, "location": "Milano, Lombardia", "created": "24-Mar-2021", "followers": 775, "is_user_verified": false, "favorite_count": 0, "in_reply_to_status_id": null, "keyword": "zalando", "language": "it"}, {"user_id": 1241699735225929730, "user_statuses": 25016, "name": "Sweettaeta", "tweet": "Oggi mi doveva arrivare un pacco da Zalando, ma del corriere nemmeno l'ombra\ud83d\ude2d", "retweets": 0, "location": "Caserta, Campania", "created": "24-Mar-2021", "followers": 1547, "is_user_verified": false, "favorite_count": 0, "in_reply_to_status_id": null, "keyword": "zalando", "language": "it"}, {"user_id": 288196394, "user_statuses": 468, "name": "ilgiova70", "tweet": "Vi lamentate perch\u00e9 occorre stare in casa per il #COVID19 e poi vivete di #delivery, di #Amazon, #justeat, #zalando e i suoi fratelli...", "retweets": 0, "location": "", "created": "24-Mar-2021", "followers": 25, "is_user_verified": false, "favorite_count": 0, "in_reply_to_status_id": null, "keyword": "zalando", "language": "it"}, {"user_id": 498000464, "user_statuses": 95, "name": "DesyMazzola", "tweet": "Assistenza orribile! Il mio pacco non lo vedo da pi\u00f9 di una settimana nessuno mi aiuta e se chiedo il rimborso mi dicono di attendere il pacco! @Zalando schifoooo", "retweets": 0, "location": "Roma, Lazio", "created": "24-Mar-2021", "followers": 34, "is_user_verified": false, "favorite_count": 0, "in_reply_to_status_id": null, "keyword": "zalando", "language": "it"}, {"user_id": 3005410569, "user_statuses": 34913, "name": "edernroger", "tweet": "ho fatto un odine su zalando e non ho messo il numero civico", "retweets": 0, "location": "", "created": "24-Mar-2021", "followers": 3240, "is_user_verified": false, "favorite_count": 0, "in_reply_to_status_id": null, "keyword": "zalando", "language": "it"}, {"user_id": 96004709, "user_statuses": 2197, "name": "MarialleB", "tweet": "#Dantedi , @Zalando  restaura statua di Dante a piazza dei Signori a #Verona https://t.co/UHHxFRLsnH", "retweets": 0, "location": "Catania, Italy", "created": "24-Mar-2021", "followers": 860, "is_user_verified": false, "favorite_count": 0, "in_reply_to_status_id": null, "keyword": "zalando", "language": "it"}, {"user_id": 1316067656571793410, "user_statuses": 4837, "name": "tvlktozayn", "tweet": "@buckss__ Mi hai ricordato che il mio carrello di zalando \u00e8 vuoto da troppo", "retweets": 0, "location": "Fly me to the m\u263eon", "created": "24-Mar-2021", "followers": 1389, "is_user_verified": false, "favorite_count": 1, "in_reply_to_status_id": 1374678876224372738, "keyword": "zalando", "language": "it"}, {"user_id": 1365314904832491520, "user_statuses": 1408, "name": "vvalentinae", "tweet": "@gaiamagenis Vagabond :)\nCi sono spesso su Zalando Priv\u00e9 e si riescono a reperire scontati abbastanza facilmente anche su altre piattaforme (su Vinted credo di averli visti)", "retweets": 0, "location": "Brescia e dintorni ", "created": "24-Mar-2021", "followers": 506, "is_user_verified": false, "favorite_count": 2, "in_reply_to_status_id": 1374639303935070210, "keyword": "zalando", "language": "it"}, {"user_id": 1359058720664264706, "user_statuses": 7307, "name": "outxsid3", "tweet": "@cannyalsugo amo che palle per\u00f3 non sta su zalando", "retweets": 0, "location": "she/her ", "created": "24-Mar-2021", "followers": 1573, "is_user_verified": false, "favorite_count": 0, "in_reply_to_status_id": 1374667572923281409, "keyword": "zalando", "language": "it"}, {"user_id": 487830811, "user_statuses": 39158, "name": "flowofhappyness", "tweet": "@chitrio Allora forse \u00e8 terminata \ud83d\udc94 prova a vedere sul sito normale di Zalando se \u00e8 rimasto ancora qualcosa con lo sconto", "retweets": 0, "location": "Naples, Italy \ud83c\uddee\ud83c\uddf9", "created": "24-Mar-2021", "followers": 1735, "is_user_verified": false, "favorite_count": 1, "in_reply_to_status_id": 1374665222636638211, "keyword": "zalando", "language": "it"}, {"user_id": 487830811, "user_statuses": 39158, "name": "flowofhappyness", "tweet": "@chitrio Zalando priv\u00e8 c'\u00e8 la vendita promozionale", "retweets": 0, "location": "Naples, Italy \ud83c\uddee\ud83c\uddf9", "created": "24-Mar-2021", "followers": 1735, "is_user_verified": false, "favorite_count": 2, "in_reply_to_status_id": 1374646211949510656, "keyword": "zalando", "language": "it"}, {"user_id": 1548322675, "user_statuses": 45761, "name": "_moonljght", "tweet": "@_portamivia_ SDA questa estate doveva consegnarmi due pacchi di zalando e ha scritto che non ero a casa. Il giorno dopo \u00e8 venuto e il corriere si \u00e8 giustificato dicendo che, nel mio complesso, doveva consegnare anche un altro pacco e si seccava venire due volte, cos\u00ec ha fatto tutto insieme", "retweets": 0, "location": "i'm with the band/hogwarts.", "created": "24-Mar-2021", "followers": 3175, "is_user_verified": false, "favorite_count": 1, "in_reply_to_status_id": 1374661582899269633, "keyword": "zalando", "language": "it"}, {"user_id": 4915577638, "user_statuses": 60663, "name": "Franpesca_", "tweet": "@simo_zedd Tu vuoi essere bloccato subito? O dopo l\u2019arrivo del pacco di Zalando?", "retweets": 0, "location": "", "created": "24-Mar-2021", "followers": 5415, "is_user_verified": false, "favorite_count": 0, "in_reply_to_status_id": 1374640127402729478, "keyword": "zalando", "language": "it"}, {"user_id": 1076953328, "user_statuses": 2352, "name": "francesca_xe", "tweet": "@TreizeJeanne @Franciscktrue @idiosincratica_ A scanso d\u2019equivoci, non scherzo, non \u00e8 una battuta.Mi hai messo un\u2019angoscia che certamente non mi mette la persona gentilissima che mi porta la pizza o il pacco zalando o il collega d\u2019ufficio. Se rientro da sola la notte posso avere paura ma nel quotidiano no, sarebbe patologico", "retweets": 0, "location": "", "created": "24-Mar-2021", "followers": 288, "is_user_verified": false, "favorite_count": 4, "in_reply_to_status_id": 1374474519327305739, "keyword": "zalando", "language": "it"}, {"user_id": 66649996, "user_statuses": 126404, "name": "prettywho_", "tweet": "@flowofhappyness @Valenteena_ Su zalando privee non c'\u00e8 il mio numero o almeno sono finite quelle che mi piacciono", "retweets": 0, "location": "Napoli", "created": "23-Mar-2021", "followers": 6273, "is_user_verified": false, "favorite_count": 0, "in_reply_to_status_id": 1374490365479153671, "keyword": "zalando", "language": "it"}, {"user_id": 487830811, "user_statuses": 39158, "name": "flowofhappyness", "tweet": "@prettywho_ Vaiiii su Zalando priv\u00e8 sono in promo \ud83d\udd25", "retweets": 0, "location": "Naples, Italy \ud83c\uddee\ud83c\uddf9", "created": "23-Mar-2021", "followers": 1735, "is_user_verified": false, "favorite_count": 1, "in_reply_to_status_id": 1374489659225501696, "keyword": "zalando", "language": "it"}, {"user_id": 1373282101739581441, "user_statuses": 421, "name": "YNGH0ONS", "tweet": "@WONLY0NE guarda io le avevo prese su asos scontate di un bel po\u2019, ti conviene guardare su zalando, asos di solito ci sono sempre un po\u2019 di sconti !! su che colori sei indecisa ?", "retweets": 0, "location": "SHE / HER", "created": "23-Mar-2021", "followers": 141, "is_user_verified": false, "favorite_count": 0, "in_reply_to_status_id": 1374473703057068032, "keyword": "zalando", "language": "it"}, {"user_id": 1327724962199834624, "user_statuses": 523, "name": "ariannaacasella", "tweet": "ho fatto danni sia da zara che su zalando", "retweets": 0, "location": "", "created": "23-Mar-2021", "followers": 214, "is_user_verified": false, "favorite_count": 2, "in_reply_to_status_id": null, "keyword": "zalando", "language": "it"}, {"user_id": 930187122761400321, "user_statuses": 35522, "name": "SkylarIre", "tweet": "@Franciii02 Al momento sui vari siti non so cosa c'\u00e8 ma sicuramente asos e zalando qualcosa hanno.. Ne ho viste tanto nei negozi vintage non so se vicino a te ci sono", "retweets": 0, "location": "\ud83c\udf0d ", "created": "23-Mar-2021", "followers": 224, "is_user_verified": false, "favorite_count": 0, "in_reply_to_status_id": 1374455636449132553, "keyword": "zalando", "language": "it"}, {"user_id": 1352177738870882304, "user_statuses": 3724, "name": "Princes06744635", "tweet": "@bevllisario @limecade83 Prova su zalando. C'\u00e8 l'opzione prima prova poi paga \ud83d\ude05\ud83d\ude02", "retweets": 0, "location": "Puglia, Italia", "created": "23-Mar-2021", "followers": 424, "is_user_verified": false, "favorite_count": 1, "in_reply_to_status_id": 1374425382577864707, "keyword": "zalando", "language": "it"}, {"user_id": 958527913, "user_statuses": 3044, "name": "elenapison", "tweet": "Caro @Zalando che mi mandi un numero di scarpe diverso rispetto a quello che ho ordinato, perch\u00e9 secondo te va bene cos\u00ec, cosa devo fare con il pezzo di dito che non ci sta?", "retweets": 0, "location": "", "created": "23-Mar-2021", "followers": 123, "is_user_verified": false, "favorite_count": 0, "in_reply_to_status_id": null, "keyword": "zalando", "language": "it"}, {"user_id": 1293547488637603841, "user_statuses": 1807, "name": "aryy111", "tweet": "Ho fatto vedere ci\u00f2 che comprato su Shein e Zalando alla mia best. Mi ha bocciato tutto.", "retweets": 0, "location": "", "created": "23-Mar-2021", "followers": 119, "is_user_verified": false, "favorite_count": 0, "in_reply_to_status_id": null, "keyword": "zalando", "language": "it"}, {"user_id": 827108244, "user_statuses": 157271, "name": "piccolohoran", "tweet": "-CLUBNUOVEIDEE\n\naltra app di sondaggi per riscuotere buoni amazon, zalando e tanto altro! https://t.co/mwgRPGb9ts", "retweets": 0, "location": "in Liam's arms ", "created": "23-Mar-2021", "followers": 14824, "is_user_verified": false, "favorite_count": 0, "in_reply_to_status_id": null, "keyword": "zalando", "language": "it"}, {"user_id": 1367849653153185797, "user_statuses": 935, "name": "LolitaD53672639", "tweet": "Okay, corriere di Zalando dacci l'indirizzo.\n#mellos #dayanemello", "retweets": 0, "location": "", "created": "23-Mar-2021", "followers": 37, "is_user_verified": false, "favorite_count": 2, "in_reply_to_status_id": null, "keyword": "zalando", "language": "it"}, {"user_id": 366525998, "user_statuses": 25966, "name": "OpheliaFra", "tweet": "@fracostanzo Io sono rosicona... ma rosicona del tipo che magari mi fomento tantissimo, e poi boh, senza nessun reale motivo e in una frazione di secondo passo alla modalit\u00e0 \u201cvabb\u00e8 sticazzi, uh guarda, Zalando ha messo in offerta le scarpe che da 5 anni avevo nel carrello!\u201d", "retweets": 0, "location": "Leccelandia", "created": "23-Mar-2021", "followers": 571, "is_user_verified": false, "favorite_count": 0, "in_reply_to_status_id": 1374381171836997634, "keyword": "zalando", "language": "it"}, {"user_id": 514133448, "user_statuses": 17710, "name": "vulnerabletype", "tweet": "@Gworldmywrld guarda puoi trovarli su vari siti tipo zalando/shein", "retweets": 0, "location": "", "created": "23-Mar-2021", "followers": 4619, "is_user_verified": false, "favorite_count": 0, "in_reply_to_status_id": 1374377248095043585, "keyword": "zalando", "language": "it"}, {"user_id": 995437874, "user_statuses": 36602, "name": "acidonitrosoo", "tweet": "ho messo mille robe nei preferiti di zalando ma che cazzo compro che stiamo chiusi in casa", "retweets": 0, "location": "", "created": "23-Mar-2021", "followers": 503, "is_user_verified": false, "favorite_count": 1, "in_reply_to_status_id": null, "keyword": "zalando", "language": "it"}, {"user_id": 932660407793344513, "user_statuses": 42571, "name": "prplbl00n", "tweet": "girando su zalando ho visto una maglietta di cui non ho assolutamente bisogno ma che mi ricorda taehyung might cedere al capitalismo anche oggi", "retweets": 0, "location": "she/her KTH1 IS COMING", "created": "23-Mar-2021", "followers": 265, "is_user_verified": false, "favorite_count": 1, "in_reply_to_status_id": null, "keyword": "zalando", "language": "it"}, {"user_id": 349678851, "user_statuses": 17503, "name": "crawlinback2y0u", "tweet": "@Franpesca_ https://t.co/j3UQYIeEIh il migliore che ho provato fino ad ora (4G) ma consiglio di scegliere la circonferenza di una taglia in meno", "retweets": 0, "location": "INFJ-T", "created": "23-Mar-2021", "followers": 257, "is_user_verified": false, "favorite_count": 1, "in_reply_to_status_id": 1374344735259774982, "keyword": "zalando", "language": "it"}, {"user_id": 1174798964870303756, "user_statuses": 1118, "name": "sserenissimass", "tweet": "Ma che problemi ha Zalando ogni volta che metto qualcosa nel carrello dopo 5 minuti \u00e8 sol out anche se sono scarpe che non si caga nessuno ma ohhhh", "retweets": 0, "location": "", "created": "23-Mar-2021", "followers": 39, "is_user_verified": false, "favorite_count": 0, "in_reply_to_status_id": null, "keyword": "zalando", "language": "it"}]