[{"user_id": 1092187814689685505, "user_statuses": 8962, "name": "7H30NLYF3RNZ74N", "tweet": "@CartiDrop1629 boohoo homo", "retweets": 0, "location": "", "created": "26-Mar-2021", "followers": 432, "is_user_verified": false, "favorite_count": 0, "in_reply_to_status_id": 1375276634094338051, "keyword": "boohoo", "language": "es"}, {"user_id": 298816863, "user_statuses": 32644, "name": "pulpficti0ner", "tweet": "@theawildo @josephsha2001 Next qu\u00e9? Next lloradera por vainas que no existen o next ya vas a salir del closet y dejar a los marcos tranquilos? Boohoo los gays hacen que dude de si quiero casarme o no con una mujer. Gafo.", "retweets": 0, "location": "CS30 server", "created": "25-Mar-2021", "followers": 675, "is_user_verified": false, "favorite_count": 8, "in_reply_to_status_id": 1375153762134806531, "keyword": "boohoo", "language": "es"}, {"user_id": 1079908563793989632, "user_statuses": 17310, "name": "jiminiemu", "tweet": "Ayy boohoo la pobrecita hetero no encuentra una pelicula :(\nen serio no te da verg\u00fcenza? Todas las peliculas lgbtq ponen una imagen de gays horrenda, si vas a llorar porque de las MILES de pelis hetero no encuentras una que te guste maybe you should stop being an entitled brat https://t.co/vLyJke6bP9", "retweets": 0, "location": "\ud83c\udde8\ud83c\uddf7", "created": "25-Mar-2021", "followers": 548, "is_user_verified": false, "favorite_count": 0, "in_reply_to_status_id": null, "keyword": "boohoo", "language": "es"}, {"user_id": 746372332285894656, "user_statuses": 16479, "name": "FNW_LATAM", "tweet": "Boohoo reduce su lista de proveedores y admite problemas \"claramente inaceptables\" en su cadena de suministro https://t.co/Px6xyuL2xd https://t.co/pMHPE0sQkN", "retweets": 0, "location": "", "created": "25-Mar-2021", "followers": 886, "is_user_verified": false, "favorite_count": 0, "in_reply_to_status_id": null, "keyword": "boohoo", "language": "es"}, {"user_id": 4054838933, "user_statuses": 3114, "name": "FNW_ES", "tweet": "Boohoo reduce su lista de proveedores y admite problemas \"claramente inaceptables\" en su cadena de suministro https://t.co/KB4y7myYzr https://t.co/lj9p8ydIkS", "retweets": 0, "location": "", "created": "25-Mar-2021", "followers": 418, "is_user_verified": false, "favorite_count": 0, "in_reply_to_status_id": null, "keyword": "boohoo", "language": "es"}, {"user_id": 1210558860928270336, "user_statuses": 6764, "name": "Boohoo_Cracker_", "tweet": "@ozonebella Yo bestie", "retweets": 0, "location": "Denial", "created": "25-Mar-2021", "followers": 332, "is_user_verified": false, "favorite_count": 0, "in_reply_to_status_id": 1374813244213370882, "keyword": "boohoo", "language": "es"}, {"user_id": 816649569186566145, "user_statuses": 2786, "name": "tonirluis1976", "tweet": "@Disney_Alli @pleaser_shoes @boohoo Esas piernas perfectas y acabando en esos tacones de charol negros una locura y no se puede pedir m\u00e1s \ud83d\ude0d\ud83d\ude0d\ud83d\ude0d\ud83d\ude0d\ud83d\ude0d", "retweets": 0, "location": "", "created": "25-Mar-2021", "followers": 541, "is_user_verified": false, "favorite_count": 1, "in_reply_to_status_id": 1374925914681700354, "keyword": "boohoo", "language": "es"}, {"user_id": 32613426, "user_statuses": 5362, "name": "GabyGoby", "tweet": "@pollitamarela @migrainegirlrf Boohoo verdad que ya no te gusto subirte a tu ladrillo de privilegio?", "retweets": 0, "location": "Mexico", "created": "25-Mar-2021", "followers": 271, "is_user_verified": false, "favorite_count": 0, "in_reply_to_status_id": 1374943358335000577, "keyword": "boohoo", "language": "es"}, {"user_id": 2263779985, "user_statuses": 50063, "name": "sobredxsis", "tweet": "no sab\u00eda que estaba embarazada me siento una vieja https://t.co/8fKC4icbcS", "retweets": 0, "location": "Argentina", "created": "24-Mar-2021", "followers": 19061, "is_user_verified": false, "favorite_count": 21, "in_reply_to_status_id": null, "keyword": "boohoo", "language": "es"}, {"user_id": 422895790, "user_statuses": 37559, "name": "MPerdiT", "tweet": "@heleena_95 @boohoo Cu\u00e1ndo dices que vamos a comernos uno de estos? \ud83e\udd24", "retweets": 0, "location": "DISNEY ", "created": "24-Mar-2021", "followers": 283, "is_user_verified": false, "favorite_count": 0, "in_reply_to_status_id": 1374438393736691723, "keyword": "boohoo", "language": "es"}, {"user_id": 1249833798, "user_statuses": 37986, "name": "sav_griffin", "tweet": "@boohoo Milo\ud83e\udd70 https://t.co/WMSHz1qDSG", "retweets": 0, "location": "Bristol", "created": "24-Mar-2021", "followers": 4448, "is_user_verified": false, "favorite_count": 1, "in_reply_to_status_id": 1374375382762221578, "keyword": "boohoo", "language": "es"}, {"user_id": 113343617, "user_statuses": 107916, "name": "baaaf459", "tweet": "@boohoo Mario https://t.co/6a6wjOuMKz", "retweets": 0, "location": "North West, England", "created": "24-Mar-2021", "followers": 1923, "is_user_verified": false, "favorite_count": 0, "in_reply_to_status_id": 1374375382762221578, "keyword": "boohoo", "language": "es"}, {"user_id": 2352736537, "user_statuses": 63587, "name": "emeritusthird", "tweet": "@WHlTENOlZ porque es una idiota que no sabe lo que quiere, se fue por a\u00f1os sin hablarle a chloe y despues es boohoo siempre te quise chloe *destruye una ciudad por ella* \ud83e\udd74", "retweets": 0, "location": "", "created": "23-Mar-2021", "followers": 754, "is_user_verified": false, "favorite_count": 0, "in_reply_to_status_id": 1374475886255214604, "keyword": "boohoo", "language": "es"}, {"user_id": 431814708, "user_statuses": 19007, "name": "bowersharleeeey", "tweet": "@boohoo Milo\ud83e\udd70\ud83e\udd70 https://t.co/bIEyFhp7ku", "retweets": 0, "location": "Bristol, England", "created": "23-Mar-2021", "followers": 686, "is_user_verified": false, "favorite_count": 3, "in_reply_to_status_id": 1374375382762221578, "keyword": "boohoo", "language": "es"}, {"user_id": 772388161, "user_statuses": 6426, "name": "SaammyyH", "tweet": "@boohoo Coco\ud83d\udc9b https://t.co/I92aKNuTz5", "retweets": 0, "location": "", "created": "23-Mar-2021", "followers": 391, "is_user_verified": false, "favorite_count": 0, "in_reply_to_status_id": 1374375382762221578, "keyword": "boohoo", "language": "es"}, {"user_id": 2720124454, "user_statuses": 1738, "name": "eleanor_gun", "tweet": "@boohoo Arlo \ud83d\udc3e https://t.co/GyDqnXawQ9", "retweets": 0, "location": "scotland", "created": "23-Mar-2021", "followers": 252, "is_user_verified": false, "favorite_count": 0, "in_reply_to_status_id": 1374375382762221578, "keyword": "boohoo", "language": "es"}, {"user_id": 191201617, "user_statuses": 3146, "name": "BexXxM", "tweet": "@boohoo Coco the chihuahua \u2764\ufe0f #NationalPuppyDay https://t.co/s7LuOEQ0NI", "retweets": 0, "location": "Barrow in Furness", "created": "23-Mar-2021", "followers": 116, "is_user_verified": false, "favorite_count": 0, "in_reply_to_status_id": 1374375382762221578, "keyword": "boohoo", "language": "es"}, {"user_id": 410139002, "user_statuses": 5782, "name": "JoelyRobinson1", "tweet": "@boohoo Luna \ud83c\udf19 https://t.co/WMaau8wkvL", "retweets": 0, "location": "Essex ", "created": "23-Mar-2021", "followers": 341, "is_user_verified": false, "favorite_count": 0, "in_reply_to_status_id": 1374375382762221578, "keyword": "boohoo", "language": "es"}, {"user_id": 410139002, "user_statuses": 5782, "name": "JoelyRobinson1", "tweet": "@boohoo Luna \ud83c\udf19 https://t.co/yyG6t6BDVf", "retweets": 0, "location": "Essex ", "created": "23-Mar-2021", "followers": 341, "is_user_verified": false, "favorite_count": 0, "in_reply_to_status_id": 1374375382762221578, "keyword": "boohoo", "language": "es"}, {"user_id": 1296625390887358465, "user_statuses": 9297, "name": "auronsunlight", "tweet": "@N0tDENISSE Boohoo - The Neighbourhood\nApenas descubr\u00ed esa canci\u00f3n y es buen\u00edsima", "retweets": 0, "location": "", "created": "22-Mar-2021", "followers": 1367, "is_user_verified": false, "favorite_count": 1, "in_reply_to_status_id": 1374129116396597250, "keyword": "boohoo", "language": "es"}, {"user_id": 1282534834133446656, "user_statuses": 3220, "name": "stardusteve", "tweet": "@_lenazepam jajaja hombres enojados que est\u00e1n enojados boohoo \ud83d\ude29\ud83d\ude29\ud83d\ude29\ud83e\udd70\ud83e\udd70\ud83e\udd21\ud83e\udd21\ud83e\udd21\ud83e\udd21\ud83e\udd21\ud83e\udd21", "retweets": 0, "location": "", "created": "22-Mar-2021", "followers": 442, "is_user_verified": false, "favorite_count": 0, "in_reply_to_status_id": 1373968552890408969, "keyword": "boohoo", "language": "es"}, {"user_id": 21185544, "user_statuses": 117987, "name": "vickyspooky", "tweet": "Ponedme veinte botellas. https://t.co/WJxvKA6VxE", "retweets": 0, "location": "She / Her", "created": "22-Mar-2021", "followers": 3359, "is_user_verified": false, "favorite_count": 6, "in_reply_to_status_id": null, "keyword": "boohoo", "language": "es"}, {"user_id": 1310555812230701057, "user_statuses": 760, "name": "FungousAmongous", "tweet": "@chuchiitos Boohoo cabr\u00f3n", "retweets": 0, "location": "", "created": "22-Mar-2021", "followers": 9, "is_user_verified": false, "favorite_count": 1, "in_reply_to_status_id": 1373874052805267459, "keyword": "boohoo", "language": "es"}, {"user_id": 626113267, "user_statuses": 2003, "name": "AzuTurneer", "tweet": "Me encanta \ud83e\udd0d https://t.co/NiQhYbZQaj", "retweets": 0, "location": "", "created": "22-Mar-2021", "followers": 73, "is_user_verified": false, "favorite_count": 0, "in_reply_to_status_id": null, "keyword": "boohoo", "language": "es"}, {"user_id": 47528148, "user_statuses": 3747, "name": "pinedape", "tweet": "Best 40 seconds. Con ese clip hice mi primera presentaci\u00f3n de Lola Green en el curso de Design Thinking #3a\u00f1osya #comopasaeltiempo https://t.co/Hq6fT8YrLz", "retweets": 0, "location": "Lima- Per\u00fa", "created": "21-Mar-2021", "followers": 528, "is_user_verified": false, "favorite_count": 0, "in_reply_to_status_id": null, "keyword": "boohoo", "language": "es"}, {"user_id": 58611689, "user_statuses": 215711, "name": "NikatheSiren", "tweet": "Gente que hace los tiers: pos Xinyan no es tan wena porque tiene mucho CD y no hace mucho da\u00f1o as\u00ed que no compensa, boohoo.\nYo: *inserte aqu\u00ed v\u00eddeo de Auron gritando 'c\u00f3meme los huevos'*", "retweets": 0, "location": "Handsome Jackpot", "created": "20-Mar-2021", "followers": 1246, "is_user_verified": false, "favorite_count": 0, "in_reply_to_status_id": 1373404747336679429, "keyword": "boohoo", "language": "es"}, {"user_id": 1262488725025677314, "user_statuses": 227, "name": "lcrowth", "tweet": "@boohoo Tequila \ud83e\udd22", "retweets": 0, "location": "", "created": "20-Mar-2021", "followers": 15, "is_user_verified": false, "favorite_count": 0, "in_reply_to_status_id": 1372880532258705415, "keyword": "boohoo", "language": "es"}, {"user_id": 481217525, "user_statuses": 175475, "name": "ShonaDuffy1", "tweet": "@boohoo Tequila \ud83e\udd22", "retweets": 0, "location": "Bolton", "created": "20-Mar-2021", "followers": 2191, "is_user_verified": false, "favorite_count": 0, "in_reply_to_status_id": 1372880532258705415, "keyword": "boohoo", "language": "es"}, {"user_id": 52173693, "user_statuses": 4527, "name": "linzjubb", "tweet": "@boohoo Tequila", "retweets": 0, "location": "", "created": "20-Mar-2021", "followers": 605, "is_user_verified": false, "favorite_count": 0, "in_reply_to_status_id": 1372880532258705415, "keyword": "boohoo", "language": "es"}, {"user_id": 267803645, "user_statuses": 6133, "name": "gabriellavk1", "tweet": "@boohoo_cshelp No response.....", "retweets": 0, "location": "London", "created": "20-Mar-2021", "followers": 572, "is_user_verified": false, "favorite_count": 0, "in_reply_to_status_id": 1372850972007993347, "keyword": "boohoo", "language": "es"}, {"user_id": 1370696530840129538, "user_statuses": 726, "name": "DebLondon82", "tweet": "@boohoo Tequila!\ud83e\udd22", "retweets": 0, "location": "", "created": "19-Mar-2021", "followers": 104, "is_user_verified": false, "favorite_count": 1, "in_reply_to_status_id": 1372880532258705415, "keyword": "boohoo", "language": "es"}, {"user_id": 2865604755, "user_statuses": 8701, "name": "katielhannah", "tweet": "@boohoo Tequila... https://t.co/NrGsJb8d6C", "retweets": 0, "location": "United Kingdom", "created": "19-Mar-2021", "followers": 779, "is_user_verified": false, "favorite_count": 0, "in_reply_to_status_id": 1372880532258705415, "keyword": "boohoo", "language": "es"}, {"user_id": 962281039321329664, "user_statuses": 12796, "name": "TraceyTedford", "tweet": "@boohoo Tequila \ud83d\ude02", "retweets": 0, "location": "Tandragee, Northern Ireland", "created": "19-Mar-2021", "followers": 119, "is_user_verified": false, "favorite_count": 0, "in_reply_to_status_id": 1372880532258705415, "keyword": "boohoo", "language": "es"}, {"user_id": 3215385377, "user_statuses": 2950, "name": "reymohmd", "tweet": "Pantes https://t.co/AXSfqtKM05", "retweets": 0, "location": "Kota Bandung, Jawa Barat", "created": "19-Mar-2021", "followers": 89, "is_user_verified": false, "favorite_count": 0, "in_reply_to_status_id": null, "keyword": "boohoo", "language": "es"}, {"user_id": 1241865101453467659, "user_statuses": 4112, "name": "iLM4RK", "tweet": "Ah\u00ed te voy \u00e1lbum de Justin Bieber https://t.co/36IUk6zkH7", "retweets": 0, "location": "any pronoun \u22c6 \u30de\u30fc\u30af\u306b\u611f\u8b1d\u3057\u307e", "created": "19-Mar-2021", "followers": 163, "is_user_verified": false, "favorite_count": 0, "in_reply_to_status_id": null, "keyword": "boohoo", "language": "es"}, {"user_id": 1200395757037248513, "user_statuses": 6880, "name": "Blonde2221", "tweet": "@boohoo Perno \ud83d\ude48", "retweets": 0, "location": "", "created": "19-Mar-2021", "followers": 51, "is_user_verified": false, "favorite_count": 0, "in_reply_to_status_id": 1372880532258705415, "keyword": "boohoo", "language": "es"}, {"user_id": 616138543, "user_statuses": 3077, "name": "juiceluce79", "tweet": "@boohoo Tequila", "retweets": 0, "location": "Cardiff, Wales \ud83c\udff4\udb40\udc67\udb40\udc62\udb40\udc77\udb40\udc6c\udb40\udc73\udb40\udc7f", "created": "19-Mar-2021", "followers": 444, "is_user_verified": false, "favorite_count": 2, "in_reply_to_status_id": 1372880532258705415, "keyword": "boohoo", "language": "es"}, {"user_id": 33505991, "user_statuses": 4676, "name": "noragasparr", "tweet": "TEQUILA \ud83d\ude05 https://t.co/mMo7h38QoA", "retweets": 0, "location": "London, England", "created": "19-Mar-2021", "followers": 483, "is_user_verified": false, "favorite_count": 0, "in_reply_to_status_id": null, "keyword": "boohoo", "language": "es"}, {"user_id": 1612449739, "user_statuses": 2223, "name": "1Rmcgregor", "tweet": "@boohoo Desperado beer", "retweets": 0, "location": "Sheffield, England", "created": "19-Mar-2021", "followers": 152, "is_user_verified": false, "favorite_count": 2, "in_reply_to_status_id": 1372880532258705415, "keyword": "boohoo", "language": "es"}, {"user_id": 2362418472, "user_statuses": 5007, "name": "JordiTorrijos78", "tweet": "@NoemiCarro @tldrMarketing Gracias, no lo sab\u00eda. \n\nDespu\u00e9s de ver tu mensaje, he buscado un poco y s\u00ed, llevan utilizando esta tecnolog\u00eda unos a\u00f1os.\n\nPD: Se nota que no compro mucha ropa online. \ud83d\ude05\n\nhttps://t.co/UjanhTivmb", "retweets": 0, "location": "Valencia", "created": "19-Mar-2021", "followers": 1522, "is_user_verified": false, "favorite_count": 1, "in_reply_to_status_id": 1372898079247110146, "keyword": "boohoo", "language": "es"}, {"user_id": 1229445534, "user_statuses": 21632, "name": "Goobygal", "tweet": "@boohoo Tequila", "retweets": 0, "location": "Norfolk", "created": "19-Mar-2021", "followers": 196, "is_user_verified": false, "favorite_count": 1, "in_reply_to_status_id": 1372880532258705415, "keyword": "boohoo", "language": "es"}, {"user_id": 1226519203341049858, "user_statuses": 679, "name": "Sophiedones1991", "tweet": "@boohoo Tequilla \ud83e\udd2e", "retweets": 0, "location": "", "created": "19-Mar-2021", "followers": 349, "is_user_verified": false, "favorite_count": 1, "in_reply_to_status_id": 1372880532258705415, "keyword": "boohoo", "language": "es"}, {"user_id": 591242955, "user_statuses": 18748, "name": "sophatkinsxo", "tweet": "@boohoo Tequila!! \ud83e\udd22", "retweets": 0, "location": "Enfield, London", "created": "19-Mar-2021", "followers": 336, "is_user_verified": false, "favorite_count": 1, "in_reply_to_status_id": 1372880532258705415, "keyword": "boohoo", "language": "es"}, {"user_id": 566696364, "user_statuses": 17347, "name": "AshSaxon", "tweet": "@boohoo Tequila \ud83d\ude30", "retweets": 0, "location": "Manchester ", "created": "19-Mar-2021", "followers": 1627, "is_user_verified": false, "favorite_count": 2, "in_reply_to_status_id": 1372880532258705415, "keyword": "boohoo", "language": "es"}, {"user_id": 305638601, "user_statuses": 20507, "name": "KatyxMarie", "tweet": "@boohoo Tequilla \ud83d\ude2b", "retweets": 0, "location": "London, England", "created": "19-Mar-2021", "followers": 394, "is_user_verified": false, "favorite_count": 1, "in_reply_to_status_id": 1372880532258705415, "keyword": "boohoo", "language": "es"}, {"user_id": 1202256115158917123, "user_statuses": 12290, "name": "nLE0RIO13", "tweet": "tengo mieds https://t.co/V6Z5Xi7M5e", "retweets": 0, "location": "she/her", "created": "19-Mar-2021", "followers": 814, "is_user_verified": false, "favorite_count": 0, "in_reply_to_status_id": null, "keyword": "boohoo", "language": "es"}, {"user_id": 1310659856316194818, "user_statuses": 6240, "name": "chxrryantidote", "tweet": "Mi cancion \u203c\ufe0f https://t.co/x7MKEZtjrt", "retweets": 0, "location": "be a lover give love choose love. love everyone, always", "created": "19-Mar-2021", "followers": 586, "is_user_verified": false, "favorite_count": 0, "in_reply_to_status_id": null, "keyword": "boohoo", "language": "es"}, {"user_id": 1177693672156078082, "user_statuses": 17665, "name": "elsolenaries", "tweet": "pelo oscuro es un power move https://t.co/bYL3LrUkHO", "retweets": 0, "location": "Lima, Peru", "created": "19-Mar-2021", "followers": 2783, "is_user_verified": false, "favorite_count": 14, "in_reply_to_status_id": null, "keyword": "boohoo", "language": "es"}, {"user_id": 1326746515713355776, "user_statuses": 3269, "name": "aryawoolridge", "tweet": "@boohoo @LDRaddic @LanaDelRey Lana del rey chemtrails\nLana del rey album \nLana del rey queen of alt \nLana del rey vynil\nLANA IS COMING\nLANA IS COMING\nLANA IS COMING\n#ChemTrailsOverTheCountryClub", "retweets": 0, "location": "", "created": "19-Mar-2021", "followers": 1257, "is_user_verified": false, "favorite_count": 1, "in_reply_to_status_id": 1372676881322024961, "keyword": "boohoo", "language": "es"}, {"user_id": 1344933618100166657, "user_statuses": 2001, "name": "nurusasa", "tweet": "@nausadzuiqu yuos sobre todo t\u00fa shbdjsk a m\u00ed me hace gracia que su motivo sea que le peg\u00f3 al prota boohoo", "retweets": 0, "location": "she/her | 20+ | canary islands", "created": "18-Mar-2021", "followers": 93, "is_user_verified": false, "favorite_count": 1, "in_reply_to_status_id": 1372653794920648709, "keyword": "boohoo", "language": "es"}, {"user_id": 512543384, "user_statuses": 8956, "name": "SoniaMariAndres", "tweet": "S\u00e9 la mejor versi\u00f3n de ti mismo \ud83e\udde1 @boohoo \n\nP.D.: mucha risa por aqu\u00ed pero hoy nos ha tocado \ud83c\udf51 en @square.fitness.studio y no puedo ni sentarme. \n\n#deporte #motivation #vida #training #workout #goals en Madrid, Spain https://t.co/w1c3LSXwKL", "retweets": 0, "location": "Espa\u00f1a", "created": "18-Mar-2021", "followers": 12610, "is_user_verified": false, "favorite_count": 0, "in_reply_to_status_id": null, "keyword": "boohoo", "language": "es"}, {"user_id": 1269786970277978119, "user_statuses": 10107, "name": "dropvividcandy", "tweet": "WAAAAAHHHH EN LA NUEVA CANCI\u00d3N DE USSS HUBO PARTICIPACI\u00d3N DE DECO*27 Y TEDDYLOID I'M DYING I LOVE THIS BOOHOO OWAAH OWAAH", "retweets": 0, "location": "\u00a1He/Him!", "created": "18-Mar-2021", "followers": 227, "is_user_verified": false, "favorite_count": 0, "in_reply_to_status_id": null, "keyword": "boohoo", "language": "es"}, {"user_id": 927186938032984064, "user_statuses": 34383, "name": "PinkySinC", "tweet": "Sigo progresando boohoo sipor", "retweets": 0, "location": "Argentina", "created": "18-Mar-2021", "followers": 527, "is_user_verified": false, "favorite_count": 0, "in_reply_to_status_id": null, "keyword": "boohoo", "language": "es"}]